Workbook

Sheet Premisas
A1: BANCO CAPITAL S.A. | D1: PRESUPUESTO 2026
A2: PRINCIPALES PREMISAS PRESUPUESTARIAS | C2: meses | G2: # créditos vehículos
A4: Colocación cartera de crédito bruta | B4: 2026 | C4: 12 | D4: =SUM(F4:F8) -> 87703148 | E4: PRODUCTIVO | F4: =ProyCartCre!I6 -> 232150.98
A5: 2026: enero a diciembre | E5: CONSUMO | F5: =ProyCartCre!I7 -> 66796619 | G5: =F5/B115 -> 3710.9233
E6: MICROCREDITO | F6: =ProyCartCre!I8 -> 20410290 | G6: =F6/B115 -> 1133.905
E7: REFINANCIADA | F7: =ProyCartCre!I9 -> 110815.48
E8: REESTRUCTURADA | F8: =ProyCartCre!I10 -> 153271.99
A10: Recuperación cartera de crédito | B10: 2026 | C10: 12 | D10: =SUM(F10:F14) -> 15969548 | E10: PRODUCTIVO | F10: =ProyCartCre!E6+ProyCartCre!F6 -> 232150.98
A11: 2026: enero a diciembre | E11: CONSUMO | F11: =ProyCartCre!E7+ProyCartCre!F7 -> 12559019 | G11: =F11/B115 -> 697.72329
E12: MICROCREDITO | F12: =ProyCartCre!E8+ProyCartCre!F8 -> 2914290.5 | G12: =F12/B115 -> 161.90503
E13: REFINANCIADA | F13: =ProyCartCre!E9+ProyCartCre!F9 -> 110815.48
E14: REESTRUCTURADA | F14: =ProyCartCre!E10+ProyCartCre!F10 -> 153271.99
A16: Crecimiento cartera de crédito bruta | B16: 2026 | C16: 12 | D16: =SUM(F16:F20) -> 53733600 | E16: PRODUCTIVO | F16: =ProyCartCre!M6 -> 0
A17: 2026: enero a diciembre | E17: CONSUMO | F17: =ProyCartCre!M7 -> 36237600 | G17: =F17/B115 -> 2013.2
E18: MICROCREDITO | F18: =ProyCartCre!M8 -> 17496000 | G18: =F18/B115 -> 972
E19: REFINANCIADA | F19: =ProyCartCre!M9 -> 0
E20: REESTRUCTURADA | F20: =ProyCartCre!M10 -> 0
A22: Generación, venta y administración cartera | B22: 2026 | C22: 12 | D22: =F22 -> 18000000 | E22: CONSUMO | F22: =OVA!P6 -> 18000000 | G22: =F22/B115 -> 1000
A23: =A17 -> 2026: enero a diciembre | D23: =ROUND(D22/B115,0) -> 1000 | E23: # créditos
A24: Promedio mensual | D24: =D23/C22 -> 83.333333 | E24: # créditos
A25: Portafolio de inversiones | D25: Comportamiento en virtud del movimiento de fondos disponibles, precautelando mantener el suficiente activo líquido para las operaciones del Banco.
A26: Crecimiento depósitos a la vista | B26: 2023* | C26: 1 | D26: =F26/C26 -> 10000 | E26: promedio mensual | F26: 10000 | G26: anual
A27: Crecimiento depósitos a plazo | B27: 2023* | C27: 1 | D27: =F27/C27 -> -500000 | E27: promedio mensual | F27: -500000 | G27: anual
A29: Crecimiento depósitos a la vista | B29: 2026 | C29: 12 | D29: =F29/C29 -> 200000 | E29: promedio mensual | F29: 2400000 | G29: 12 meses
A30: Crecimiento depósitos a plazo | B30: 2026 | C30: 12 | D30: =F30/C30 -> 6196500 | E30: promedio mensual | F30: =B117*85% -> 74358000 | G30: 12 meses
A31: Recuperación de activos castigados (cartera y cuentas por cobrar) | B31: 2026 | C31: 12 | D31: =F31/C31 -> 12136.004 | E31: promedio mensual | F31: =SUM(BRhoriz!I194:P194) -> 145632.05 | G31: 12 meses
A32: Recuperación de activos castigados (cartera y cuentas por cobrar) | B32: 2026 | C32: 12 | D32: =F32/C32 -> 20833.333 | E32: promedio mensual | F32: 250000 | G32: 12 meses
A33: Reversión de provisiones (cartera, cuentas por cobrar, bienes recibidos en dación en pago) | B33: 2026 | C33: 12 | D33: =F33/C33 -> 24198.258 | E33: promedio mensual | F33: =SUM(BRhoriz!BE195:BJ195) -> 290379.1 | G33: 12 meses
A34: Inversión en sistemas y tecnología | B34: 2026 | C34: 12 | D34: 10000 | E34: promedio mensual | F34: =C34*D34 -> 120000 | G34: 12 meses
A35: Inversión en sistemas y tecnología | B35: 2026 | C35: 12 | D35: =F35/C35 -> 10000 | E35: promedio mensual | F35: 120000 | G35: 12 meses
A36: Inversión en nueva imagen del Banco | B36: 2026 | C36: 12 | D36: =F36/C36 -> 4166.6667 | E36: promedio mensual | F36: 50000 | G36: 12 meses
A37: Venta de casa recibida en dación en pago | B37: 2026 | D37: 0
A38: CAPITALIZACION | B38: 2026 | D38: 0
B39: 2023* - 2024
A41: Rendimiento inversiones disponibles para venta | B41: 2024 | C41: 0.0781 | D41: Rendimiento promedio ponderado Ene a Jun2024
A42: Rendimiento inversiones mantenidas hasta vcto | B42: 2024 | C42: 0.05 | D42: Rendimiento promedio ponderado proyectado
A43: Rendimiento cartera de crédito productivo | B43: 2024 | C43: =AVERAGE(BGhoriz!Q369:V369) -> 0.098611866 | D43: Tasa promedio ponderada Ene a Jun2024
A44: Rendimiento cartera de crédito consumo | B44: 2024 | C44: 0.15 | D44: Tasa estimada
A45: Rendimiento cartera de microcrédito | B45: 2024 | C45: 0.15 | D45: =D44 -> Tasa estimada
A46: Rendimiento cartera refinanciada | B46: 2024 | C46: =AVERAGE(BGhoriz!Q376:V376) -> 0.13468632 | D46: Tasa promedio ponderada Ene a Jun2024
A47: Rendimiento cartera reestructurada | B47: 2024 | C47: =AVERAGE(BGhoriz!Q377:V377) -> 0.15543587 | D47: =D46 -> Tasa promedio ponderada Ene a Jun2024
A48: Costo depósitos de ahorro | B48: 2024 | C48: 0.025 | D48: Costo promedio ponderado proyectado
A49: Costo depósitos a plazo | B49: 2024 | C49: 0.08 | D49: Costo promedio ponderado proyectado
B50: 2023* - 2024
A51: Indicador de mora crédito productivo | B51: 46023 | C51: 0.02 | D51: Morosidad promedio ponderado Ene a Jun2024 | F51: Reducción % mora
B52: 46054 | C52: 0.02 | D52: Morosidad proyectada | F52: 0.005
B53: 46082 | C53: 0.02 | D53: Morosidad proyectada | F53: 0.005
B54: 46113 | C54: 0.02 | D54: Morosidad proyectada | F54: 0.005
B55: 46143 | C55: 0.02 | D55: Morosidad proyectada | F55: 0.005
B56: 46174 | C56: 0.02 | D56: Morosidad proyectada | F56: 0.005
B57: 46204 | C57: 0.02 | D57: Morosidad proyectada | F57: 0.005
B58: 46235 | C58: 0.02 | D58: Morosidad proyectada | F58: 0.005
B59: 46266 | C59: 0.02 | D59: Morosidad proyectada | F59: =F57 -> 0.005
B60: 46296 | C60: 0.02 | D60: Morosidad proyectada | F60: =F59 -> 0.005
B61: 46327 | C61: 0.02 | D61: Morosidad proyectada | F61: =F60 -> 0.005
B62: 46357 | C62: 0.02 | D62: Morosidad proyectada | F62: =F61 -> 0.005
A63: Indicador de mora crédito consumo | B63: 46023 | C63: 0.02 | D63: =D51 -> Morosidad promedio ponderado Ene a Jun2024
B64: 46054 | C64: 0.02
B65: 46082 | C65: 0.02
B66: 46113 | C66: 0.02
B67: 46143 | C67: 0.02
B68: 46174 | C68: 0.02
B69: 46204 | C69: 0.02
B70: 46235 | C70: 0.02
B71: 46266 | C71: 0.02 | D71: Morosidad proyectada | F71: 0.015
B72: 46296 | C72: 0.02 | D72: Morosidad proyectada | F72: =F71 -> 0.015
B73: 46327 | C73: 0.02 | D73: Morosidad proyectada | F73: =F72 -> 0.015
B74: 46357 | C74: 0.02 | D74: Morosidad proyectada | F74: =F73 -> 0.015
A75: Indicador de mora microcrédito | B75: 46023 | C75: 0.02 | D75: =D63 -> Morosidad promedio ponderado Ene a Jun2024
B76: 46054 | C76: 0.02
B77: 46082 | C77: 0.02
B78: 46113 | C78: 0.02
B79: 46143 | C79: 0.02
B80: 46174 | C80: 0.02
B81: 46204 | C81: 0.02
B82: 46235 | C82: 0.02 | D82: Morosidad proyectada | F82: 0.015
B83: 46266 | C83: 0.02 | D83: Morosidad proyectada | F83: =F82 -> 0.015
B84: 46296 | C84: 0.02 | D84: Morosidad proyectada | F84: =F83 -> 0.015
B85: 46327 | C85: 0.02 | D85: Morosidad proyectada | F85: =F84 -> 0.015
B86: 45627 | C86: 0.02 | D86: Morosidad proyectada | F86: =F85 -> 0.015
A87: Indicador de mora crédito refinanciado | B87: 46023 | C87: 0.02 | D87: =D75 -> Morosidad promedio ponderado Ene a Jun2024
B88: 46054 | C88: 0.02
B89: 46082 | C89: 0.02
B90: 46113 | C90: 0.02
B91: 46143 | C91: 0.02
B92: 46174 | C92: 0.02
B93: 46204 | C93: 0.02
B94: 46235 | C94: 0.02 | D94: Morosidad proyectada | F94: 0.02
B95: 46266 | C95: 0.02 | D95: Morosidad proyectada | F95: =F94 -> 0.02
B96: 46296 | C96: 0.02 | D96: Morosidad proyectada | F96: =F95 -> 0.02
B97: 46327 | C97: 0.02 | D97: Morosidad proyectada | F97: =F96 -> 0.02
B98: 45627 | C98: 0.02 | D98: Morosidad proyectada | F98: =F97 -> 0.02
A99: Indicador de mora crédito reestructurado | B99: 46023 | C99: 0.02 | D99: =D87 -> Morosidad promedio ponderado Ene a Jun2024
B100: 46054 | C100: 0.02
B101: 46082 | C101: 0.02
B102: 46113 | C102: 0.02
B103: 46143 | C103: 0.02
B104: 46174 | C104: 0.02
B105: 46204 | C105: 0.02
B106: 46235 | C106: 0.02 | D106: Morosidad proyectada | F106: 0.02
...

Sheet EEFFun
B1: =Premisas!A1 -> BANCO CAPITAL S.A. | D1: ESTADOS FINANCIEROS A ÚLTIMO NIVEL | E1: ESTADOS FINANCIEROS A ÚLTIMO NIVEL | N1: ESTADOS FINANCIEROS A ÚLTIMO NIVEL
D2: 12 | E2: 1 | F2: 2 | G2: 3 | H2: 4 | I2: 5 | J2: 6 | K2: 7 | L2: 8 | M2: 9 | N2: 10 | O2: 11 | P2: 12 | Q2: 1 | R2: 2 | S2: 3 | T2: 4 | U2: 5 | V2: 6 | W2: 7 | X2: 8 | Y2: 9 | Z2: 10 | AA2: 11 | AB2: 12 | AC2: 1 | AD2: 2 | AE2: 3 | AF2: 4 | AG2: 5 | AH2: 6 | AI2: 7 | AJ2: 8 | AK2: 9 | AL2: 10 | AM2: 11 | AN2: 12 | AO2: 1 | AP2: 2 | AQ2: 3 | AR2: 4 | AS2: 5 | AT2: 6 | AU2: 7 | AV2: 8 | AW2: 9 | AX2: 10
A3: D | B3: CODIGO | C3: Cuenta | D3: 44561 | E3: 44592 | F3: 44620 | G3: 44651 | H3: 44681 | I3: 44712 | J3: 44742 | K3: 44773 | L3: 44804 | M3: 44834 | N3: 44865 | O3: 44895 | P3: 44926 | Q3: 44957 | R3: 44985 | S3: 45016 | T3: 45046 | U3: 45077 | V3: 45107 | W3: 45138 | X3: 45169 | Y3: 45199 | Z3: 45230 | AA3: 45260 | AB3: 45291 | AC3: 45322 | AD3: 45351 | AE3: 45382 | AF3: 45412 | AG3: 45443 | AH3: 45473 | AI3: 45504 | AJ3: 45535 | AK3: 45565 | AL3: 45596 | AM3: 45626 | AN3: 45657 | AO3: 45688 | AP3: 45716 | AQ3: 45747 | AR3: 45777 | AS3: 45808 | AT3: 45838 | AU3: 45869 | AV3: 45900 | AW3: 45930 | AX3: 45961
B4: 1 | C4: ACTIVOS | D4: 36785499 | E4: 36893446 | F4: 38348823 | G4: 38779119 | H4: 39117859 | I4: 39637060 | J4: 40115413 | K4: 40602162 | L4: 40166533 | M4: 42392654 | N4: 42463256 | O4: 42545573 | P4: 41871995 | Q4: 41428485 | R4: 41342572 | S4: 41608837 | T4: 41402927 | U4: 40814797 | V4: 39918747 | W4: 38859684 | X4: 38554650 | Y4: 38446164 | Z4: 39087530 | AA4: 38587003 | AB4: 38163618 | AC4: 38284842 | AD4: 37819571 | AE4: 38313322 | AF4: 38567040 | AG4: 41817124 | AH4: 47062540 | AI4: 47113341 | AJ4: 47711065 | AK4: 48144336 | AL4: 49311534 | AM4: 50621766 | AN4: 51800193 | AO4: 54248199 | AP4: 56369251 | AQ4: 61925193 | AR4: 59395369 | AS4: 61701051 | AT4: 63381053 | AU4: 66525948 | AV4: 68613984 | AW4: 69701630 | AX4: 72243574 | BF4: 1 | BG4: ACTIVOS | BH4: 47062540 | BI4: 1 | BJ4: ACTIVOS | BK4: 47113341
B5: 11 | C5: FONDOS DISPONIBLES | D5: 2686087 | E5: 2804100.2 | F5: 2695224.8 | G5: 2589769.2 | H5: 2923643.5 | I5: 2383972.8 | J5: 2540920.3 | K5: 2723411.2 | L5: 2143680.2 | M5: 3680138.1 | N5: 3077894.4 | O5: 2694462.4 | P5: 1875049.3 | Q5: 2157721.8 | R5: 1067075.5 | S5: 1371077.2 | T5: 1367417.2 | U5: 639585.39 | V5: 1015149.9 | W5: 1439298.4 | X5: 1405357.7 | Y5: 1420921.5 | Z5: 3468050.7 | AA5: 1823814 | AB5: 2030867.1 | AC5: 2478250.7 | AD5: 2693317.6 | AE5: 2647740 | AF5: 2607961.3 | AG5: 5634923.1 | AH5: 4254536.5 | AI5: 4099296 | AJ5: 4958217.3 | AK5: 4296254.5 | AL5: 4298604.7 | AM5: 3676654.6 | AN5: 4049699.8 | AO5: 5062709.1 | AP5: 5849402.1 | AQ5: 10155982 | AR5: 4699001.7 | AS5: 4336396.1 | AT5: 4550594.8 | AU5: 5911836.4 | AV5: 4866030.1 | AW5: 3430395.2 | AX5: 4340169 | BF5: 11 | BG5: FONDOS DISPONIBLES | BH5: 4254536.5 | BI5: 11 | BJ5: FONDOS DISPONIBLES | BK5: 4099296
B6: 1101 | C6: Caja | D6: 407928.36 | E6: 364748.68 | F6: 398771.2 | G6: 441259.02 | H6: 206209.45 | I6: 245002.16 | J6: 263087.73 | K6: 205228.55 | L6: 225069.1 | M6: 186808.61 | N6: 236209.4 | O6: 215810.59 | P6: 214026.13 | Q6: 277847.72 | R6: 286876.51 | S6: 204150.86 | T6: 160152.06 | U6: 131044.46 | V6: 176055.54 | W6: 198561.99 | X6: 195871.78 | Y6: 228922.32 | Z6: 283560.04 | AA6: 222619.25 | AB6: 208164.9 | AC6: 251432.59 | AD6: 240875.19 | AE6: 253033.42 | AF6: 187632.89 | AG6: 220439.2 | AH6: 310851.54 | AI6: 283281.66 | AJ6: 199494.72 | AK6: 278582.66 | AL6: 259551.5 | AM6: 199927.71 | AN6: 262062.05 | AO6: 277749.16 | AP6: 318505.87 | AQ6: 230466.86 | AR6: 234403.27 | AS6: 253245.71 | AT6: 310211.12 | AU6: 243391.61 | AV6: 197845.36 | AW6: 112996.15 | AX6: 163888.03 | BF6: 1101 | BG6: Caja | BH6: 310851.54 | BI6: 1101 | BJ6: Caja | BK6: 283281.66
B7: 110105 | C7: Efectivo | D7: 407228.36 | E7: 364048.68 | F7: 398071.2 | G7: 440559.02 | H7: 205509.45 | I7: 244302.16 | J7: 262387.73 | K7: 204528.55 | L7: 224369.1 | M7: 186108.61 | N7: 235509.4 | O7: 215110.59 | P7: 213326.13 | Q7: 277147.72 | R7: 286476.51 | S7: 203550.86 | T7: 159552.06 | U7: 130444.46 | V7: 175455.54 | W7: 197961.99 | X7: 195271.78 | Y7: 228322.32 | Z7: 282960.04 | AA7: 222019.25 | AB7: 207564.9 | AC7: 250832.59 | AD7: 240275.19 | AE7: 252433.42 | AF7: 187032.89 | AG7: 219839.2 | AH7: 310251.54 | AI7: 282681.66 | AJ7: 198894.72 | AK7: 277932.66 | AL7: 258901.5 | AM7: 199277.71 | AN7: 261412.05 | AO7: 277099.16 | AP7: 317855.87 | AQ7: 229816.86 | AR7: 233753.27 | AS7: 252595.71 | AT7: 309561.12 | AU7: 242741.61 | AV7: 197195.36 | AW7: 112346.15 | AX7: 163238.03 | BF7: 110105 | BG7: Efectivo | BH7: 310251.54 | BI7: 110105 | BJ7: Efectivo | BK7: 282681.66
B8: 11010505 | C8: EFECTIVO CAJEROS | D8: 228618.54 | E8: 185518.85 | F8: 225499.47 | G8: 267105.75 | H8: 197286.22 | I8: 236078.93 | J8: 254164.5 | K8: 196305.32 | L8: 216145.87 | M8: 177885.38 | N8: 227286.17 | O8: 215110.59 | P8: 213326.13 | Q8: 277147.72 | R8: 286476.51 | S8: 203550.86 | T8: 159552.06 | U8: 130444.46 | V8: 175455.54 | W8: 197961.99 | X8: 195271.78 | Y8: 228322.32 | Z8: 282960.04 | AA8: 222019.25 | AB8: 207564.9 | AC8: 250832.59 | AD8: 240275.19 | AE8: 252433.42 | AF8: 187032.89 | AG8: 219839.2 | AH8: 310251.54 | AI8: 282681.66 | AJ8: 198894.72 | AK8: 277932.66 | AL8: 258901.5 | AM8: 199277.71 | AN8: 261412.05 | AO8: 277099.16 | AP8: 317855.87 | AQ8: 229816.86 | AR8: 233753.27 | AS8: 252595.71 | AT8: 309561.12 | AU8: 242741.61 | AV8: 197195.36 | AW8: 112346.15 | AX8: 163238.03 | BF8: 11010505 | BG8: EFECTIVO CAJEROS | BH8: 310251.54 | BI8: 11010505 | BJ8: EFECTIVO CAJEROS | BK8: 282681.66
B9: 11010510 | C9: EFECTIVO SERVIPAGOS | D9: 178609.82 | E9: 178529.83 | F9: 172571.73 | G9: 173453.27 | H9: 8223.23 | I9: 8223.23 | J9: 8223.23 | K9: 8223.23 | L9: 8223.23 | M9: 8223.23 | N9: 8223.23 | AJ9: 0 | AK9: 0 | AL9: 0 | AM9: 0 | AN9: 0 | AO9: 0 | AP9: 0 | AQ9: 0 | AR9: 0 | AS9: 0 | AT9: 0 | AU9: 0 | AV9: 0 | AW9: 0 | AX9: 0
B10: 110110 | C10: Caja chica | D10: 700 | E10: 700 | F10: 700 | G10: 700 | H10: 700 | I10: 700 | J10: 700 | K10: 700 | L10: 700 | M10: 700 | N10: 700 | O10: 700 | P10: 700 | Q10: 700 | R10: 400 | S10: 600 | T10: 600 | U10: 600 | V10: 600 | W10: 600 | X10: 600 | Y10: 600 | Z10: 600 | AA10: 600 | AB10: 600 | AC10: 600 | AD10: 600 | AE10: 600 | AF10: 600 | AG10: 600 | AH10: 600 | AI10: 600 | AJ10: 600 | AK10: 650 | AL10: 650 | AM10: 650 | AN10: 650 | AO10: 650 | AP10: 650 | AQ10: 650 | AR10: 650 | AS10: 650 | AT10: 650 | AU10: 650 | AV10: 650 | AW10: 650 | AX10: 650 | BF10: 110110 | BG10: Caja chica | BH10: 600 | BI10: 110110 | BJ10: Caja chica | BK10: 600
B11: 1102 | C11: Depósitos para encaje | D11: 723166.33 | E11: 968383.13 | F11: 862945.84 | G11: 1459649.1 | H11: 1619818.6 | I11: 1689645.9 | J11: 1992147.8 | K11: 1923298.5 | L11: 1360725.8 | M11: 1805091.8 | N11: 2220619.2 | O11: 1756268.9 | P11: 1458459.1 | Q11: 1655874.6 | R11: 696024.36 | S11: 729617.53 | T11: 914088.16 | U11: 395720.74 | V11: 661246.05 | W11: 905886.15 | X11: 949534.49 | Y11: 1009525.2 | Z11: 2385698 | AA11: 1334167.7 | AB11: 1405746.8 | AC11: 1859123.1 | AD11: 2003168.1 | AE11: 2045474.5 | AF11: 1976303.9 | AG11: 3928148.2 | AH11: 3143751 | AI11: 2806504 | AJ11: 2163759.4 | AK11: 2242781.5 | AL11: 1709911.1 | AM11: 1638916.9 | AN11: 2070537.4 | AO11: 2642596.5 | AP11: 3166958.7 | AQ11: 6287760.7 | AR11: 2911875.5 | AS11: 2377694.2 | AT11: 2062558.2 | AU11: 2061537.2 | AV11: 1873146.7 | AW11: 2308812.5 | AX11: 1771523.1 | BF11: 1102 | BG11: Depósitos para encaje | BH11: 3143751 | BI11: 1102 | BJ11: Depósitos para encaje | BK11: 2806504
B12: 110205 | C12: Banco Central del Ecuador | D12: 723166.33 | E12: 968383.13 | F12: 862945.84 | G12: 1766788.9 | H12: 1619818.6 | I12: 1689645.9 | J12: 1992147.8 | K12: 1923298.5 | L12: 1360725.8 | M12: 1805091.8 | N12: 2220619.2 | O12: 1756268.9 | P12: 1458459.1 | Q12: 1655874.6 | R12: 696024.36 | S12: 729617.53 | T12: 914088.16 | U12: 395720.74 | V12: 661246.05 | W12: 905886.15 | X12: 949534.49 | Y12: 1009525.2 | Z12: 2385698 | AA12: 1334167.7 | AB12: 1405746.8 | AC12: 1859123.1 | AD12: 2003168.1 | AE12: 2045474.5 | AF12: 1976303.9 | AG12: 3928148.2 | AH12: 3143751 | AI12: 2806504 | AJ12: 2163759.4 | AK12: 2242781.5 | AL12: 1709911.1 | AM12: 1638916.9 | AN12: 2070537.4 | AO12: 2642596.5 | AP12: 3166958.7 | AQ12: 6287760.7 | AR12: 2911875.5 | AS12: 2377694.2 | AT12: 2062558.2 | AU12: 2061537.2 | AV12: 1873146.7 | AW12: 2308812.5 | AX12: 1771523.1 | BF12: 110205 | BG12: Banco Central del Ecuador | BH12: 3143751 | BI12: 110205 | BJ12: Banco Central del Ecuador | BK12: 2806504
B13: 1103 | C13: Bancos y otras instituciones financieras | D13: 1506823.3 | E13: 1401397 | F13: 1412256.6 | G13: 656553.18 | H13: 1015569.6 | I13: 438283.88 | J13: 210269.42 | K13: 549386.81 | L13: 447251.88 | M13: 1324072.7 | N13: 489999.22 | O13: 536468.17 | P13: 158169.61 | Q13: 195182.12 | R13: 71708.75 | S13: 422965.87 | T13: 281591.29 | U13: 98347.3 | V13: 169766.14 | W13: 318895.57 | X13: 232485.38 | Y13: 167037.38 | Z13: 694592.63 | AA13: 235800.14 | AB13: 244049.01 | AC13: 348962.61 | AD13: 389760.87 | AE13: 336932.08 | AF13: 435474.52 | AG13: 1455911 | AH13: 779934.02 | AI13: 1007131.2 | AJ13: 2594573.1 | AK13: 1758795.6 | AL13: 2319909.5 | AM13: 1832736.2 | AN13: 1675024.8 | AO13: 2062363.4 | AP13: 2263741.4 | AQ13: 3621125.2 | AR13: 1503949.6 | AS13: 1590635.2 | AT13: 2021103.7 | AU13: 3579970.1 | AV13: 2658908 | AW13: 908586.61 | AX13: 2378842.1 | BF13: 1103 | BG13: Bancos y otras instituciones financieras | BH13: 779934.02 | BI13: 1103 | BJ13: Bancos y otras instituciones financieras | BK13: 1007131.2
B14: 110310 | C14: Bancos e instituciones financieras locales | D14: 1492860.1 | E14: 1387433.8 | F14: 1398292.9 | G14: 642589.49 | H14: 1001605.9 | I14: 424320.19 | J14: 196305.73 | K14: 535423.12 | L14: 433288.19 | M14: 1310109 | N14: 481279.12 | O14: 527748.07 | P14: 149402.61 | Q14: 186391.8 | R14: 62918.43 | S14: 414175.55 | T14: 272800.97 | U14: 89556.98 | V14: 160975.82 | W14: 310105.25 | X14: 223695.06 | Y14: 158247.06 | Z14: 685718.35 | AA14: 226925.86 | AB14: 235174.73 | AC14: 340088.33 | AD14: 380886.59 | AE14: 328057.8 | AF14: 426600.24 | AG14: 1447036.8 | AH14: 771059.74 | AI14: 998256.87 | AJ14: 2585698.8 | AK14: 1749921.3 | AL14: 2311035.3 | AM14: 1823861.9 | AN14: 1666150.5 | AO14: 2053489.2 | AP14: 2254867.1 | AQ14: 3612250.9 | AR14: 1495075.4 | AS14: 1581760.9 | AT14: 2012229.4 | AU14: 3571095.8 | AV14: 2650033.7 | AW14: 899712.33 | AX14: 2369967.9 | BF14: 110310 | BG14: Bancos e instituciones financieras locales | BH14: 771059.74 | BI14: 110310 | BJ14: Bancos e instituciones financieras locales | BK14: 998256.87
B15: 110315 | C15: Bancos e instituciones financieras del exterior | D15: 13963.15 | E15: 13963.15 | F15: 13963.69 | G15: 13963.69 | H15: 13963.69 | I15: 13963.69 | J15: 13963.69 | K15: 13963.69 | L15: 13963.69 | M15: 13963.69 | N15: 8720.1 | O15: 8720.1 | P15: 8767 | Q15: 8790.32 | R15: 8790.32 | S15: 8790.32 | T15: 8790.32 | U15: 8790.32 | V15: 8790.32 | W15: 8790.32 | X15: 8790.32 | Y15: 8790.32 | Z15: 8874.28 | AA15: 8874.28 | AB15: 8874.28 | AC15: 8874.28 | AD15: 8874.28 | AE15: 8874.28 | AF15: 8874.28 | AG15: 8874.28 | AH15: 8874.28 | AI15: 8874.28 | AJ15: 8874.28 | AK15: 8874.28 | AL15: 8874.28 | AM15: 8874.28 | AN15: 8874.28 | AO15: 8874.28 | AP15: 8874.28 | AQ15: 8874.28 | AR15: 8874.28 | AS15: 8874.28 | AT15: 8874.28 | AU15: 8874.28 | AV15: 8874.28 | AW15: 8874.28 | AX15: 8874.28 | BF15: 110315 | BG15: Bancos e instituciones financieras del exterior | BH15: 8874.28 | BI15: 110315 | BJ15: Bancos e instituciones financieras del exterior | BK15: 8874.28
B16: 1104 | C16: Efectos de cobro inmediato | D16: 48169.06 | E16: 69571.44 | F16: 21251.11 | G16: 32307.88 | H16: 82045.86 | I16: 11040.81 | J16: 75415.34 | K16: 45497.37 | L16: 110633.45 | M16: 364165.07 | N16: 131066.59 | O16: 185914.73 | P16: 44394.42 | Q16: 28817.37 | R16: 12465.85 | S16: 14342.96 | T16: 11585.67 | U16: 14472.89 | V16: 8082.17 | W16: 15954.67 | X16: 27466.02 | Y16: 15436.64 | Z16: 104200 | AA16: 31226.91 | AB16: 172906.43 | AC16: 18732.34 | AD16: 59513.5 | AE16: 12300 | AF16: 8550 | AG16: 30424.61 | AH16: 20000 | AI16: 2379.15 | AJ16: 390.07 | AK16: 16094.73 | AL16: 9232.53 | AM16: 5073.8 | AN16: 42075.6 | AO16: 80000 | AP16: 100196.19 | AQ16: 16629.5 | AR16: 48773.38 | AS16: 114820.99 | AT16: 156721.71 | AU16: 26937.47 | AV16: 136130.02 | AW16: 100000 | AX16: 25915.8 | BF16: 1104 | BG16: Efectos de cobro inmediato | BH16: 20000 | BI16: 1104 | BJ16: Efectos de cobro inmediato | BK16: 2379.15
B17: 110405 | C17: EFECTOS INGRESADOS A CAJA | D17: 2004.54 | E17: 2004.54 | F17: 2004.54 | G17: 2004.54 | H17: 2004.54 | I17: 2004.54 | J17: 2004.54 | AJ17: 0 | AK17: 0 | AL17: 0 | AM17: 0 | AN17: 0 | AO17: 0 | AP17: 0 | AQ17: 0 | AR17: 0 | AS17: 0 | AT17: 0 | AU17: 0 | AV17: 0 | AW17: 0 | AX17: 0
B18: 110410 | C18: VALORES ENVIADOS A CÁMARA DE COMPENSACIÓN | D18: 46164.52 | E18: 67566.9 | F18: 19246.57 | G18: 30303.34 | H18: 80041.32 | I18: 9036.27 | J18: 73410.8 | K18: 45497.37 | L18: 110633.45 | M18: 364165.07 | N18: 131066.59 | O18: 185914.73 | P18: 44394.42 | Q18: 28817.37 | R18: 12465.85 | S18: 14342.96 | T18: 11585.67 | U18: 14472.89 | V18: 8082.17 | W18: 15954.67 | X18: 27466.02 | Y18: 15436.64 | Z18: 104200 | AA18: 31226.91 | AB18: 172906.43 | AC18: 18732.34 | AD18: 59513.5 | AE18: 12300 | AF18: 8550 | AG18: 30424.61 | AH18: 20000 | AI18: 2379.15 | AJ18: 390.07 | AK18: 16094.73 | AL18: 9232.53 | AM18: 2798.76 | AN18: 25000 | AO18: 80000 | AP18: 86700.69 | AQ18: 3134 | AR18: 48773.38 | AS18: 114420.99 | AT18: 156721.71 | AU18: 26937.47 | AV18: 136130.02 | AW18: 100000 | AX18: 25915.8 | BF18: 110410 | BG18: VALORES ENVIADOS A CÁMARA DE COMPENSACIÓN | BH18: 20000 | BI18: 110410 | BJ18: VALORES ENVIADOS A CÁMARA DE COMPENSACIÓN | BK18: 2379.15
B19: 13 | C19: INVERSIONES | D19: 5705796.3 | E19: 5110401.8 | F19: 5706550.3 | G19: 4642393.1 | H19: 4135535.7 | I19: 4208787.1 | J19: 4208726 | K19: 4102857.7 | L19: 4109775.8 | M19: 5136909.8 | N19: 5414946.9 | O19: 5432407.7 | P19: 4569816.5 | Q19: 4396213.9 | R19: 4304281.3 | S19: 3882342.1 | T19: 3717634.7 | U19: 3705733.6 | V19: 3355464.7 | W19: 2765240.9 | X19: 2749371.4 | Y19: 2738719.7 | Z19: 2140533.1 | AA19: 3155413.9 | AB19: 5472959.3 | AC19: 5593231.5 | AD19: 5619865.4 | AE19: 5768860.9 | AF19: 5990435 | AG19: 6535690.2 | AH19: 6902967.2 | AI19: 6494256.5 | AJ19: 6306447.7 | AK19: 6725858.3 | AL19: 7257820.6 | AM19: 7421635.4 | AN19: 7437172.5 | AO19: 8068951.5 | AP19: 8156070.3 | AQ19: 8475496.9 | AR19: 8588335.1 | AS19: 8657652.1 | AT19: 7871172 | AU19: 8339019 | AV19: 8332154.9 | AW19: 8240933.2 | AX19: 6909362.7 | BF19: 13 | BG19: INVERSIONES | BH19: 6902967.2 | BI19: 13 | BJ19: INVERSIONES | BK19: 6494256.5
B20: 1303 | C20: Disponibles para la venta de entidades del sector privado | D20: 2270718.8 | E20: 1476474.9 | F20: 1981443.3 | G20: 984132.65 | H20: 613516.93 | I20: 636788.11 | J20: 685266.72 | K20: 587236.61 | L20: 590288.39 | M20: 1567215.6 | N20: 1576222.8 | O20: 1735420.4 | P20: 873535.46 | Q20: 675506.01 | R20: 571537.73 | S20: 159326.22 | AA20: 989738.94 | AB20: 3293488 | AC20: 3203322 | AD20: 3224550.5 | AE20: 3286443 | AF20: 3319558.5 | AG20: 3643661.2 | AH20: 3501862.1 | AI20: 2930627.8 | AJ20: 2951359.5 | AK20: 3210364 | AL20: 3747715 | AM20: 3772843.1 | AN20: 3736839.7 | AO20: 4047091.1 | AP20: 4071250.8 | AQ20: 4325367.7 | AR20: 4170377.3 | AS20: 4176153.7 | AT20: 3394593.6 | AU20: 3638363.8 | AV20: 3524422.2 | AW20: 3244758.1 | AX20: 1333972.4 | BF20: 1303 | BG20: Disponibles para la venta de entidades del sector | BH20: 3501862.1 | BI20: 1303 | BJ20: Disponibles para la venta de entidades del sector | BK20: 2930627.8
B21: 130305 | C21: De 1 a 30 días | D21: 2262351.5 | E21: 1468046.6 | F21: 1471590.6 | G21: 473768.42 | H21: 404292.91 | I21: 202827.73 | J21: 101249.93 | K21: 432278.99 | L21: 330519.45 | N21: 153358.33 | O21: 966698.78 | P21: 202034.17 | Q21: 107021.85 | R21: 413146.67 | S21: 159326.22 | AB21: 93029.17 | AD21: 45140.92 | AE21: 94083.53 | AG21: 147355.87 | AH21: 549108.12 | AJ21: 45311.4 | AK21: 94104.07 | AL21: 50014.59 | AM21: 401448.89 | AN21: 752988.15 | AO21: 180958.11 | AP21: 538713.65 | AQ21: 1184575.4 | AR21: 789389 | AS21: 836215.76 | AT21: 767890.25 | AU21: 393345.64 | AV21: 1356503.6 | AW21: 1421996.4 | AX21: 823359.35 | BF21: 130305 | BG21: De 1 a 30 días | BH21: 549108.12
B22: 130310 | C22: De 31 a 90 días | F22: 300694.44 | G22: 403193.75 | H22: 101426.39 | I22: 427653.57 | J22: 429928.36 | L22: 151706.25 | M22: 807441.81 | N22: 708954.67 | O22: 206998.86 | P22: 514890.08 | Q22: 568484.16 | R22: 158391.06 | AA22: 44540.01 | AB22: 44475.87 | AC22: 137670.47 | AD22: 93446.72 | AE22: 145324.17 | AF22: 389401.73 | AG22: 545416.85 | AH22: 44624.19 | AI22: 137818.79 | AJ22: 0 | AK22: 0 | AL22: 0 | AM22: 0 | AN22: 0 | AO22: 0 | AP22: 0 | AQ22: 0 | AR22: 0 | AS22: 0 | AT22: 0 | AU22: 0 | AV22: 0 | AW22: 0 | AX22: 0 | BF22: 130310 | BG22: De 31 a 90 días | BH22: 44624.19 | BI22: 130310 | BJ22: De 31 a 90 días | BK22: 137818.79
B23: 130315 | C23: De 91 a 180 días | F23: 200675 | G23: 100952.78 | H23: 101536.11 | J23: 154088.43 | K23: 154957.62 | L23: 108062.69 | M23: 605937.95 | N23: 713909.79 | O23: 561722.71 | P23: 156611.21 | AA23: 44540.01 | AB23: 149958.83 | AC23: 137670.47 | AD23: 138587.64 | AE23: 138718.81 | AF23: 137798.26 | AG23: 138778.69 | AH23: 138707.72 | AI23: 137818.79 | AJ23: 0 | AK23: 0 | AL23: 0 | AM23: 0 | AN23: 0 | AO23: 0 | AP23: 0 | AQ23: 0 | AR23: 0 | AS23: 0 | AT23: 0 | AU23: 0 | AV23: 0 | AW23: 0 | AX23: 0 | BF23: 130315 | BG23: De 91 a 180 días | BH23: 138707.72 | BI23: 130315 | BJ23: De 91 a 180 días | BK23: 137818.79
B24: 130320 | C24: De 181 a 360 días | D24: 8367.33 | E24: 8428.22 | F24: 8483.29 | G24: 6217.7 | H24: 6261.52 | I24: 6306.81 | M24: 153835.86 | AA24: 89080.03 | AB24: 262556.32 | AC24: 275340.96 | AD24: 277175.29 | AE24: 277437.62 | AF24: 275596.52 | AG24: 277557.38 | AH24: 277415.43 | AI24: 275637.57 | AJ24: 277598.41 | AK24: 277461.81 | AL24: 275649.22 | AM24: 277552.97 | AN24: 277478.68 | AO24: 275659.74 | AP24: 277430.82 | AQ24: 277396.57 | AR24: 179949.74 | AS24: 181254.44 | AT24: 225610.63 | AU24: 214290.17 | AV24: 110414.95 | AW24: 111142.79 | AX24: 0 | BF24: 130320 | BG24: De 181 a 360 días | BH24: 277415.43 | BI24: 130320 | BJ24: De 181 a 360 días | BK24: 275637.57
B25: 130325 | C25: De más de 360 días | AA25: 811578.89 | AB25: 2743467.8 | AC25: 2652640.1 | AD25: 2670199.9 | AE25: 2630878.8 | AF25: 2516762 | AG25: 2534552.4 | AH25: 2492006.6 | AI25: 2379352.6 | AJ25: 2396162.7 | AK25: 2353721.6 | AL25: 2241608.2 | AM25: 2256966.2 | AN25: 2215090.7 | AO25: 2103846.3 | AP25: 2117258.5 | AQ25: 2075655.9 | AR25: 2022468.7 | AS25: 2021779.2 | AT25: 1639782.5 | AU25: 1511810.1 | AV25: 638778.97 | AW25: 642989.8 | AX25: 0 | BF25: 130325 | BG25: De más de 360 días | BH25: 2492006.6 | BI25: 130325 | BJ25: De más de 360 días | BK25: 2379352.6
B26: 1304 | C26: Disponibles para la venta del estado o de entidades sector público | D26: 1312196.2 | E26: 1422005.2 | F26: 1421784.6 | G26: 1312657.6 | H26: 1146094.3 | I26: 1164864.9 | J26: 1114805.9 | K26: 1116018.4 | L26: 1113708 | M26: 1154693.4 | N26: 1356530.8 | O26: 1198346.7 | P26: 1195356.7 | Q26: 1198541.3 | R26: 1201417.8 | S26: 1204602.4 | T26: 1207684.3 | U26: 1210868.9 | V26: 892037.29 | W26: 332131.87 | X26: 332972.21 | Y26: 333785.44 | Z26: 119572.78 | AA26: 119864.07 | AB26: 119506.7 | AC26: 318411.53 | AD26: 319022.94 | AE26: 418285.24 | AF26: 597604.13 | AG26: 798487.53 | AH26: 1243123.1 | AI26: 1243953.3 | AJ26: 1244880.1 | AK26: 1243156 | AL26: 1243987.4 | AM26: 1344563.5 | AN26: 1345585.8 | AO26: 1543183.9 | AP26: 1543770.5 | AQ26: 1544918.5 | AR26: 1691354.8 | AS26: 1692858.9 | AT26: 1694604.5 | AU26: 1850971.1 | AV26: 1852904.2 | AW26: 1954783.7 | AX26: 2050883.4 | BF26: 1304 | BG26: Disponibles para la venta del estado o de entidade | BH26: 1243123.1 | BI26: 1304 | BJ26: Disponibles para la venta del estado o de entidade | BK26: 1243953.3
B27: 130405 | C27: De 1 a 30 días | D27: 413105.51 | E27: 641724.91 | F27: 500231.41 | G27: 313551.54 | H27: 610924.96 | I27: 390716.89 | J27: 145763.67 | K27: 630985.08 | L27: 169881.12 | M27: 145773.33 | N27: 801294.8 | O27: 209836.68 | Y27: 109768.59 | AA27: 119864.07 | AD27: 119906.67 | AE27: 99894.01 | AF27: 99889.73 | AG27: 219795.27 | AH27: 279830.46 | AI27: 300834.71 | AJ27: 666144.12 | AK27: 279852.86 | AL27: 300856.04 | AM27: 284766.08 | AN27: 662003 | AO27: 401072.72 | AP27: 284743.29 | AQ27: 861728.33 | AR27: 401013.1 | AS27: 284688.81 | AT27: 1011504.5 | AU27: 401015.27 | AV27: 284715.8 | AW27: 1171879.3 | AX27: 401046.15 | BF27: 130405 | BG27: De 1 a 30 días | BH27: 279830.46 | BI27: 130405 | BJ27: De 1 a 30 días | BK27: 300834.71
B28: 130410 | C28: De 31 a 90 días | D28: 899090.65 | E28: 571456.1 | F28: 921553.14 | G28: 999106.02 | H28: 535169.31 | I28: 774147.99 | J28: 969042.2 | K28: 485033.36 | L28: 774195.56 | M28: 1008920.1 | N28: 209486.71 | W28: 109225.67 | X28: 213991.71 | Y28: 224016.85 | Z28: 119572.78 | AB28: 119506.7 | AC28: 219183.41 | AD28: 199116.27 | AE28: 318391.23 | AF28: 497714.4 | AG28: 578692.26 | AH28: 963292.63 | AI28: 943118.62 | AJ28: 578736.01 | AK28: 583570.62 | AL28: 943131.34 | AM28: 1059797.5 | AN28: 683582.81 | AO28: 1142111.2 | AP28: 1259027.2 | AQ28: 683190.2 | AR28: 1091187.6 | AS28: 1408170.1 | AT28: 683100 | AU28: 1449955.9 | AV28: 1568188.4 | AW28: 782904.38 | AX28: 1649837.3 | BF28: 130410 | BG28: De 31 a 90 días | BH28: 963292.63 | BI28: 130410 | BJ28: De 31 a 90 días | BK28: 943118.62
B29: 130415 | C29: De 91 a 180 días | E29: 208824.15 | L29: 169631.36 | T29: 459793.53 | U29: 1004114.3 | V29: 892037.29 | W29: 222906.2 | X29: 118980.5 | AC29: 99228.12 | AO29: 0 | AP29: 0 | AQ29: 0 | AR29: 0 | AS29: 0 | AT29: 0 | AU29: 0 | AV29: 0 | AW29: 0 | AX29: 0
B30: 130420 | C30: De 181 a 360 días | N30: 345749.31 | O30: 988510.01 | P30: 1195356.7 | Q30: 1198541.3 | R30: 1201417.8 | S30: 1204602.4 | T30: 747890.73 | U30: 206754.59 | AO30: 0 | AP30: 0 | AQ30: 0 | AR30: 0 | AS30: 0 | AT30: 0 | AU30: 0 | AV30: 0 | AW30: 0 | AX30: 0
B31: 1305 | C31: Mantenidas hasta el vencimiento de entidades sector privado | AO31: 0 | AP31: 0 | AQ31: 0 | AR31: 0 | AS31: 0 | AT31: 0 | AU31: 0 | AV31: 0 | AW31: 0 | AX31: 0
B32: 130505 | C32: De 1 a 30 días | AO32: 0 | AP32: 0 | AQ32: 0 | AR32: 0 | AS32: 0 | AT32: 0 | AU32: 0 | AV32: 0 | AW32: 0 | AX32: 0
B33: 130510 | C33: De 31 a 90 días | AO33: 0 | AP33: 0 | AQ33: 0 | AR33: 0 | AS33: 0 | AT33: 0 | AU33: 0 | AV33: 0 | AW33: 0 | AX33: 0
B34: 1306 | C34: Mantenidas hasta el vencimiento del estado o de en | D34: 1760226.9 | E34: 1849267.3 | F34: 1940708.2 | G34: 1982968.5 | H34: 2013310.3 | I34: 2044499.8 | J34: 2046019.1 | K34: 2036968.3 | L34: 2043124.9 | M34: 2052346.3 | N34: 2119538.8 | O34: 2135986.1 | P34: 2138249.7 | Q34: 2159492 | R34: 2168711.6 | S34: 2155819.4 | T34: 2147356.4 | U34: 2132310.9 | V34: 2100873.6 | W34: 2070535.1 | X34: 2053825.3 | Y34: 2041836.7 | Z34: 2020960.4 | AA34: 2045810.9 | AB34: 2059964.6 | AC34: 2071498 | AD34: 2076291.9 | AE34: 2064132.7 | AF34: 2073272.3 | AG34: 2093541.4 | AH34: 2157982 | AI34: 2319675.4 | AJ34: 2110208.1 | AK34: 2272338.3 | AL34: 2266118.2 | AM34: 2304228.7 | AN34: 2344713.5 | AO34: 2468593.4 | AP34: 2530921.2 | AQ34: 2595033.4 | AR34: 2716377.8 | AS34: 2778364.8 | AT34: 2771651.3 | AU34: 2839311.9 | AV34: 2944406.9 | AW34: 3030921.8 | AX34: 3086341.5 | BF34: 1306 | BG34: Mantenidas hasta el vencimiento del estado o de en | BH34: 2157982 | BI34: 1306 | BJ34: Mantenidas hasta el vencimiento del estado o de en | BK34: 2319675.4
B35: 130615 | C35: De 91 a 180 días | D35: 1760226.9 | E35: 1849267.3 | F35: 1940708.2 | G35: 1982968.5 | H35: 2013310.3 | I35: 2044499.8 | J35: 2046019.1 | K35: 2036968.3 | L35: 2043124.9 | M35: 2052346.3 | N35: 2119538.8 | O35: 2135986.1 | P35: 2138249.7 | Q35: 2159492 | R35: 2168711.6 | S35: 2155819.4 | T35: 2147356.4 | U35: 2132310.9 | V35: 2100873.6 | W35: 2070535.1 | X35: 2053825.3 | Y35: 2041836.7 | Z35: 2020960.4 | AA35: 2045810.9 | AB35: 2059964.6 | AC35: 2071498 | AD35: 2076291.9 | AE35: 2064132.7 | AF35: 2073272.3 | AG35: 2093541.4 | AH35: 2157982 | AI35: 2319675.4 | AJ35: 2110208.1 | AK35: 2272338.3 | AL35: 2266118.2 | AM35: 2304228.7 | AN35: 2344713.5 | AO35: 2468593.4 | AP35: 2530921.2 | AQ35: 2595033.4 | AR35: 2716377.8 | AS35: 2778364.8 | AT35: 2771651.3 | AU35: 2839311.9 | AV35: 2944406.9 | AW35: 3030921.8 | AX35: 3086341.5 | BF35: 130615 | BG35: De 91 a 180 días | BH35: 2157982 | BI35: 130615 | BJ35: De 91 a 180 días | BK35: 2319675.4
B36: 1307 | C36: De disponibilidad restringida | D36: 362654.49 | E36: 362654.49 | F36: 362614.21 | G36: 362634.35 | H36: 362614.21 | I36: 362634.35 | J36: 362634.35 | K36: 362634.35 | L36: 362654.49 | M36: 362654.49 | N36: 362654.49 | O36: 362654.49 | P36: 362674.63 | Q36: 362674.63 | R36: 362614.21 | S36: 362594.07 | T36: 362594.07 | U36: 362553.8 | V36: 362553.8 | W36: 362573.93 | X36: 362573.93 | Y36: 363097.54 | AN36: 10033.54 | AO36: 10083.06 | AP36: 10127.78 | AQ36: 10177.29 | AR36: 10225.21 | AS36: 10274.72 | AT36: 10322.64 | AU36: 10372.15 | AV36: 10421.67 | AW36: 10469.58 | AX36: 438165.38
B37: 130710 | C37: Depósitos sujetos a restricción | D37: 362654.49 | E37: 362654.49 | F37: 362614.21 | G37: 362634.35 | H37: 362614.21 | I37: 362634.35 | J37: 362634.35 | K37: 362634.35 | L37: 362654.49 | M37: 362654.49 | N37: 362654.49 | O37: 362654.49 | P37: 362674.63 | Q37: 362674.63 | R37: 362614.21 | S37: 362594.07 | T37: 362594.07 | U37: 362553.8 | V37: 362553.8 | W37: 362573.93 | X37: 362573.93 | Y37: 363097.54 | AN37: 10033.54 | AO37: 10083.06 | AP37: 10127.78 | AQ37: 10177.29 | AR37: 10225.21 | AS37: 10274.72 | AT37: 10322.64 | AU37: 10372.15 | AV37: 10421.67 | AW37: 10469.58 | AX37: 10519.1
B38: 14 | C38: CARTERA DE CREDITOS | D38: 16941057 | E38: 17465919 | F38: 18395321 | G38: 19854931 | H38: 20338206 | I38: 21390769 | J38: 21843896 | K38: 22248486 | L38: 22403326 | M38: 22142781 | N38: 22483243 | O38: 22912017 | P38: 23772499 | Q38: 23269792 | R38: 24359372 | S38: 24821532 | T38: 24750622 | U38: 24906664 | V38: 24123481 | W38: 23259505 | X38: 23029410 | Y38: 22965420 | Z38: 22165634 | AA38: 22203438 | AB38: 19180364 | AC38: 18773966 | AD38: 18008447 | AE38: 18365493 | AF38: 18486105 | AG38: 18109430 | AH38: 24318701 | AI38: 24732960 | AJ38: 24692896 | AK38: 24847676 | AL38: 25536075 | AM38: 24396647 | AN38: 25299258 | AO38: 26164723 | AP38: 27274081 | AQ38: 28308348 | AR38: 31045993 | AS38: 32984678 | AT38: 35797577 | AU38: 36874866 | AV38: 39485583 | AW38: 41678361 | AX38: 45825231 | BF38: 14 | BG38: CARTERA DE CREDITOS | BH38: 24318701 | BI38: 14 | BJ38: CARTERA DE CREDITOS | BK38: 24732960
C39: CARTERA DE CREDITOS BRUTA | D39: =SUM(D40:D49) -> 18527280 | E39: =SUM(E40:E49) -> 19008396 | F39: =SUM(F40:F49) -> 19834142 | G39: =SUM(G40:G49) -> 21296414 | H39: =SUM(H40:H49) -> 21815268 | I39: =SUM(I40:I49) -> 22899243 | J39: =SUM(J40:J49) -> 23375519 | K39: =SUM(K40:K49) -> 23771584 | ... AX39: =SUM(AX40:AX49) -> 46916087
C40: PRODUCTIVO | D40: =D53+D95+D137 -> 640031.74 | E40: =E53+E95+E137 -> 589612 | F40: =F53+F95+F137 -> 921670.45 | G40: =G53+G95+G137 -> 1491384.3 | H40: =H53+H95+H137 -> 1543212.4 | I40: =I53+I95+I137 -> 1836803.3 | J40: =J53+J95+J137 -> 1779345 | K40: =K53+K95+K137 -> 1782985.1 | ... AX40: =AX53+AX95+AX137 -> 643955.82
C41: CONSUMO | D41: =D59+D101+D142 -> 16264033 | E41: =E59+E101+E142 -> 16837435 | F41: =F59+F101+F142 -> 17370633 | G41: =G59+G101+G142 -> 18166881 | H41: =H59+H101+H142 -> 18064599 | I41: =I59+I101+I142 -> 18222559 | J41: =J59+J101+J142 -> 18291762 | K41: =K59+K101+K142 -> 18330823 | ... AX41: =AX59+AX101+AX142 -> 29829805
C42: MICROCREDITO | D42: =D65+D107+D154 -> 952625.16 | E42: =E65+E107+E154 -> 932387.96 | F42: =F65+F107+F154 -> 931119.11 | G42: =G65+G107+G154 -> 1069863 | H42: =H65+H107+H154 -> 1655469.8 | I42: =I65+I107+I154 -> 2319299.5 | J42: =J65+J107+J154 -> 2805629.9 | K42: =K65+K107+K154 -> 3174634.3 | ... AX42: =AX65+AX107+AX154 -> 15825819
C43: INMOBILIARIO | D43: =D148 -> 1 | E43: =E148 -> 1 | F43: =F148 -> 1 | G43: =G148 -> 1 | H43: =H148 -> 1 | I43: =I148 -> 1 | J43: =J148 -> 1 | K43: =K148 -> 1 | ... AX43: =AX148 -> 0
C44: CONSUMO REFINANCIADO | D44: =D71+D113+D160 -> 0 | E44: =E71+E113+E160 -> 0 | F44: =F71+F113+F160 -> 0 | G44: =G71+G113+G160 -> 0 | H44: =H71+H113+H160 -> 0 | I44: =I71+I113+I160 -> 0 | J44: =J71+J113+J160 -> 13549.05 | K44: =K71+K113+K160 -> 13549.05 | ... AX44: =AX71+AX113+AX160 -> 260130
C45: MICROCREDITO REFINANCIADO | U45: =U77+U119+U165 -> 0 | V45: =V77+V119+V165 -> 0 | W45: =W77+W119+W165 -> 30942.94 | X45: =X77+X119+X165 -> 56130.02 | Y45: =Y77+Y119+Y165 -> 95559.15 | Z45: =Z77+Z119+Z165 -> 117323.1 | AA45: =AA77+AA119+AA165 -> 117323.1 | AB45: =AB77+AB119+AB165 -> 117962.57 | ... AX45: =AX77+AX119+AX165 -> 89773.94
C46: CONSUMO REESTRUCTURADO | D46: =D83 -> 26201.66 | E46: =E83 -> 25435.53 | F46: =F83 -> 24494.63 | G46: =G83 -> 28579.79 | H46: =H83 -> 27599.36 | I46: =I83 -> 21556.93 | J46: =J83 -> 15979.25 | K46: =K83 -> 15065.3 | ... T46: =T83 -> 6856.37 | U46: =U83+U125+U169 -> 6304.02 | V46: =V83+V125+V169 -> 5744.16 | W46: =W83+W125+W169 -> 20189.48 | X46: =X83+X125+X169 -> 96839.78 | Y46: =Y83+Y125+Y169 -> 126080.62 | Z46: =Z83+Z125+Z169 -> 148107.14 | AA46: =AA83+AA125+AA169 -> 163729.77 | AB46: =AB83+AB125+AB169 -> 170670.1 | ... AX46: =AX83+AX125+AX169 -> 69182.77
C47: MICROCREDITO REESTRUCTURADO | D47: =D131+D174 -> 8017.83 | E47: =E131+E174 -> 7478.27 | F47: =F131+F174 -> 7478.27 | G47: =G131+G174 -> 7478.27 | H47: =H131+H174 -> 7478.27 | I47: =I131+I174 -> 7478.27 | J47: =J131+J174 -> 7478.27 | K47: =K131+K174 -> 7478.27 | ... T47: =T131+T174 -> 6438.29 | U47: =U89+U131+U174 -> 4438.29 | V47: =V89+V131+V174 -> 3538.29 | W47: =W89+W131+W174 -> 2828.6 | X47: =X89+X131+X174 -> 15200.52 | Y47: =Y89+Y131+Y174 -> 35282.42 | Z47: =Z89+Z131+Z174 -> 35131.78 | AA47: =AA89+AA131+AA174 -> 51875.01 | AB47: =AB89+AB131+AB174 -> 109551.42 | ... AX47: =AX89+AX131+AX174 -> 24197.46
C48: REFINANCIADO COVID 19 | D48: =D179+D182+D184 -> 161393.28 | E48: =E179+E182+E184 -> 146507.77 | F48: =F179+F182+F184 -> 143355.83 | G48: =G179+G182+G184 -> 112774.68 | H48: =H179+H182+H184 -> 102745.86 | I48: =I179+I182+I184 -> 89869.48 | J48: =J179+J182+J184 -> 80275.21 | K48: =K179+K182+K184 -> 69832.11 | ... AX48: =AX179+AX182+AX184 -> 115962.57
C49: REESTRUCTURADO COVID 19 | D49: =D186+D189+D192 -> 474975.87 | E49: =E186+E189+E192 -> 469538.17 | F49: =F186+F189+F192 -> 435389.88 | G49: =G186+G189+G192 -> 419451.88 | H49: =H186+H189+H192 -> 414161.7 | I49: =I186+I189+I192 -> 401675.84 | J49: =J186+J189+J192 -> 381499.08 | K49: =K186+K189+K192 -> 377215.65 | ... AX49: =AX186+AX189+AX192 -> 57260.86
C50: PROVISIONES PARA CREDITOS INCOBRABLES | D50: =D195 -> -1586222.2 | E50: =E195 -> -1542477.1 | F50: =F195 -> -1438820.8 | G50: =G195 -> -1441483.1 | H50: =H195 -> -1477061.9 | I50: =I195 -> -1508473.9 | J50: =J195 -> -1531622.9 | K50: =K195 -> -1523097.7 | ... AX50: =AX195 -> -1090856.6
C51: TOTAL CARTERA DE CREDITO POR VENCER | D51: =D53+D59+D65+D71+D83+D179+D186 -> 17581864 | E51: =E53+E59+E65+E71+E83+E179+E186 -> 18111821 | F51: =F53+F59+F65+F71+F83+F179+F186 -> 19126794 | G51: =G53+G59+G65+G71+G83+G179+G186 -> 20639650 | H51: =H53+H59+H65+H71+H83+H179+H186 -> 21050695 | I51: =I53+I59+I65+I71+I83+I179+I186 -> 22155023 | J51: =J53+J59+J65+J71+J83+J179+J186 -> 22572123 | K51: =K53+K59+K65+K71+K83+K179+K186 -> 22900172 | ... T51: =T53+T59+T65+T71+T83+T179+T186 -> 24141086 | U51: =U53+U59+U65+U71+U83+U179+U186+U77+U89 -> 24208873 | V51: =V53+V59+V65+V71+V83+V179+V186+V77+V89 -> 23407312 | W51: =W53+W59+W65+W71+W83+W179+W186+W77+W89 -> 22413044 | X51: =X53+X59+X65+X71+X83+X179+X186+X77+X89 -> 22474107 | Y51: =Y53+Y59+Y65+Y71+Y83+Y179+Y186+Y77+Y89 -> 22432999 | Z51: =Z53+Z59+Z65+Z71+Z83+Z179+Z186+Z77+Z89 -> 19662511 | AA51: =AA53+AA59+AA65+AA71+AA83+AA179+AA186+AA77+AA89 -> 21279535 | AB51: =AB53+AB59+AB65+AB71+AB83+AB179+AB186+AB77+AB89 -> 18221028 | ... AX51: =AX53+AX59+AX65+AX71+AX83+AX179+AX186+AX77+AX89 -> 46080175
C52: TOTAL CARTERA DE CREDITO EN RIESGO | D52: =D95+D101+D107+D113+D131+D137+D142+D148+D154+D160+D174+D182+D184+D189+D192 -> 945415.18 | E52: =E95+E101+E107+E113+E131+E137+E142+E148+E154+E160+E174+E182+E184+E189+E192 -> 896575.1 | F52: =F95+F101+F107+F113+F131+F137+F142+F148+F154+F160+F174+F182+F184+F189+F192 -> 707348.39 | G52: =G95+G101+G107+G113+G131+G137+G142+G148+G154+G160+G174+G182+G184+G189+G192 -> 656763.72 | H52: =H95+H101+H107+H113+H131+H137+H142+H148+H154+H160+H174+H182+H184+H189+H192 -> 764573.23 | I52: =I95+I101+I107+I113+I131+I137+I142+I148+I154+I160+I174+I182+I184+I189+I192 -> 744219.64 | J52: =J95+J101+J107+J113+J131+J137+J142+J148+J154+J160+J174+J182+J184+J189+J192 -> 803396.16 | K52: =K95+K101+K107+K113+K131+K137+K142+K148+K154+K160+K174+K182+K184+K189+K192 -> 871412.16 | ... T52: =T95+T101+T107+T113+T131+T137+T142+T148+T154+T160+T174+T182+T184+T189+T192 -> 2281772.9 | U52: =U95+U101+U107+U113+U131+U137+U142+U148+U154+U160+U174+U182+U184+U189+U192+U119+U125+U165+U169 -> 2506903.9 | V52: =V95+V101+V107+V113+V131+V137+V142+V148+V154+V160+V174+V182+V184+V189+V192+V119+V125+V165+V169 -> 2618395.4 | W52: =W95+W101+W107+W113+W131+W137+W142+W148+W154+W160+W174+W182+W184+W189+W192+W119+W125+W165+W169 -> 2822467.2 | X52: =X95+X101+X107+X113+X131+X137+X142+X148+X154+X160+X174+X182+X184+X189+X192+X119+X125+X165+X169 -> 2541798.7 | Y52: =Y95+Y101+Y107+Y113+Y131+Y137+Y142+Y148+Y154+Y160+Y174+Y182+Y184+Y189+Y192+Y119+Y125+Y165+Y169 -> 2585172.8 | Z52: =Z95+Z101+Z107+Z113+Z131+Z137+Z142+Z148+Z154+Z160+Z174+Z182+Z184+Z189+Z192+Z119+Z125+Z165+Z169 -> 4765363.2 | AA52: =AA95+AA101+AA107+AA113+AA131+AA137+AA142+AA148+AA154+AA160+AA174+AA182+AA184+AA189+AA192+AA119+AA125+AA165+AA169 -> 2967023 | AB52: =AB95+AB101+AB107+AB113+AB131+AB137+AB142+AB148+AB154+AB160+AB174+AB182+AB184+AB189+AB192+AB119+AB125+AB165+AB169 -> 3028981.8 | ... AX52: =AX95+AX101+AX107+AX113+AX131+AX137+AX142+AX148+AX154+AX160+AX174+AX182+AX184+AX189+AX192+AX119+AX125+AX165+AX169 -> 835912.4
B53: 1401 | C53: CARTERA DE CRÉDITOS PRODUCTIVO POR VENCER | D53: 635054.41 | E53: 584634.67 | F53: 916693.12 | G53: 1491292.3 | H53: 1543121.4 | I53: 1836713.3 | J53: 1779255 | K53: 1708782.8 | L53: 1979665.9 | M53: 1545254.8 | N53: 1554192.9 | O53: 1628347.2 | P53: 1734072.3 | Q53: 1080190.8 | R53: 1436040.4 | S53: 1322502.2 | T53: 1174227.7 | U53: 1276341.7 | V53: 1178401.2 | W53: 982762.02 | X53: 1021419.3 | Y53: 835220.01 | Z53: 714034.35 | AA53: 661841.17 | AB53: 639271.61 | AC53: 627114.89 | AD53: 666746.27 | AE53: 795258.68 | AF53: 783862.58 | AG53: 807364.88 | AH53: 726963.57 | AI53: 677485.24 | AJ53: 720768.96 | AK53: 737369.17 | AL53: 723611.95 | AM53: 735372.36 | AN53: 768061.3 | AO53: 685119.83 | AP53: 733823.72 | AQ53: 728836.98 | AR53: 725339.93 | AS53: 733989.78 | AT53: 770989.99 | AU53: 754548.06 | AV53: 775381.5 | AW53: 758312.95 | AX53: 643884.82 | BF53: 1401 | BG53: CARTERA DE CRÉDITOS PRODUCTIVO POR VENCER | BH53: 726963.57 | BI53: 1401 | BJ53: CARTERA DE CRÉDITOS PRODUCTIVO POR VENCER | BK53: 677485.24
B54: 140105 | C54: De 1 a 30 días | D54: 191155.55 | E54: 30531.8 | F54: 41731.82 | G54: 130523.01 | H54: 133328.45 | I54: 87326.54 | J54: 141988.15 | K54: 297143.08 | L54: 653356.01 | M54: 689772.78 | N54: 374921.87 | O54: 73928.35 | P54: 692142.45 | Q54: 22709.81 | R54: 94667.02 | S54: 148960.9 | T54: 12740.63 | U54: 111974.16 | V54: 73592.91 | W54: 21574.38 | X54: 208421.87 | Y54: 120849.36 | Z54: 77952.54 | AA54: 11866.97 | AB54: 12414.08 | AC54: 10957.94 | AD54: 12018.24 | AE54: 17205.63 | AF54: 16104.15 | AG54: 103458.71 | AH54: 29948.39 | AI54: 17548.62 | AJ54: 14331.83 | AK54: 15622.15 | AL54: 17592.64 | AM54: 18761.38 | AN54: 18983.46 | AO54: 16859.83 | AP54: 19137.67 | AQ54: 19925.18 | AR54: 20430.44 | AS54: 18681.48 | AT54: 21401.89 | AU54: 19977.8 | AV54: 29322.19 | AW54: 32373.54 | AX54: 24172.66 | BF54: 140105 | BG54: De 1 a 30 días | BH54: 29948.39 | BI54: 140105 | BJ54: De 1 a 30 días | BK54: 17548.62
B55: 140110 | C55: De 31 a 90 días | D55: 42375.78 | E55: 144168.84 | F55: 159882.06 | G55: 136286.08 | H55: 116367.31 | I55: 318514.83 | J55: 793985.58 | K55: 717418.62 | L55: 603072.62 | M55: 155777.57 | N55: 354803.28 | O55: 681789.73 | P55: 156396.74 | Q55: 261802.64 | R55: 179886.32 | S55: 111858.86 | T55: 170864.96 | U55: 92041.2 | V55: 199654.94 | W55: 281587.99 | X55: 158978.43 | Y55: 64396.45 | Z55: 20599.56 | AA55: 21555.51 | AB55: 21135.61 | AC55: 20975.91 | AD55: 24027.53 | AE55: 63571.52 | AF55: 116865.29 | AG55: 43969.55 | AH55: 33709.65 | AI55: 33184.08 | AJ55: 31462.07 | AK55: 32023.12 | AL55: 32537.08 | AM55: 33202 | AN55: 35251.93 | AO55: 32184.57 | AP55: 35690.43 | AQ55: 35145.63 | AR55: 36832.84 | AS55: 38107.23 | AT55: 39579.89 | AU55: 40650.35 | AV55: 58689.08 | AW55: 59524.04 | AX55: 47950.25 | BF55: 140110 | BG55: De 31 a 90 días | BH55: 33709.65 | BI55: 140110 | BJ55: De 31 a 90 días | BK55: 33184.08
B56: 140115 | C56: De 91 a 180 días | D56: 156842.74 | E56: 81873.46 | F56: 208364.37 | G56: 689312.54 | H56: 742794.25 | I56: 766140.15 | J56: 255677.49 | K56: 289897.38 | L56: 309785.9 | M56: 285032.43 | N56: 225107.69 | O56: 270215.37 | P56: 257802.78 | Q56: 180949.63 | R56: 187718.19 | S56: 266107.42 | T56: 254223.62 | U56: 302160.95 | V56: 150378.83 | W56: 50588.67 | X56: 37586.48 | Y56: 32837.18 | Z56: 31676.49 | AA56: 33607.63 | AB56: 32076.97 | AC56: 43902.09 | AD56: 48596.21 | AE56: 61213.31 | AF56: 46834.51 | AG56: 49914.69 | AH56: 52119.09 | AI56: 50834.72 | AJ56: 49639.75 | AK56: 49760.07 | AL56: 50227.4 | AM56: 51936.56 | AN56: 53686.18 | AO56: 48492.92 | AP56: 54691.98 | AQ56: 54119.46 | AR56: 56441.59 | AS56: 58543.09 | AT56: 61931.89 | AU56: 62312.35 | AV56: 80753.71 | AW56: 73010.91 | AX56: 55094.05 | BF56: 140115 | BG56: De 91 a 180 días | BH56: 52119.09 | BI56: 140115 | BJ56: De 91 a 180 días | BK56: 50834.72
B57: 140120 | C57: De 181 a 360 días | D57: 99952.21 | E57: 191299.54 | F57: 294266.2 | G57: 336904.39 | H57: 308700.07 | I57: 329423.18 | J57: 265318.74 | K57: 138209.88 | L57: 158223.92 | M57: 151671.22 | N57: 248384.06 | O57: 275346.28 | P57: 285323.79 | Q57: 232054.85 | R57: 286383.82 | S57: 124311.73 | T57: 78131.85 | U57: 93943.73 | V57: 94300.13 | W57: 77873.7 | X57: 78570.31 | Y57: 67752.65 | Z57: 65768.29 | AA57: 68972.86 | AB57: 78317.46 | AC57: 67389.99 | AD57: 77226.96 | AE57: 104344.54 | AF57: 97925.31 | AG57: 104508.15 | AH57: 104935.03 | AI57: 99122.64 | AJ57: 101556.43 | AK57: 103001.46 | AL57: 104124.71 | AM57: 107074.66 | AN57: 112134.33 | AO57: 101534.76 | AP57: 113911.71 | AQ57: 113319.16 | AR57: 112088.4 | AS57: 110655.16 | AT57: 108665.54 | AU57: 101449.31 | AV57: 93071.72 | AW57: 85381.3 | AX57: 65751.45 | BF57: 140120 | BG57: De 181 a 360 días | BH57: 104935.03 | BI57: 140120 | BJ57: De 181 a 360 días | BK57: 99122.64
B58: 140125 | C58: De más de 360 días | D58: 144728.13 | E58: 136761.03 | F58: 212448.67 | G58: 198266.24 | H58: 241931.33 | I58: 335308.57 | J58: 322285.08 | K58: 266113.81 | L58: 255227.45 | M58: 263000.75 | N58: 350975.99 | O58: 327067.47 | P58: 342406.55 | Q58: 382673.86 | R58: 687385.09 | S58: 671263.34 | T58: 658266.67 | U58: 676221.64 | V58: 660474.41 | W58: 551137.28 | X58: 537862.18 | Y58: 549384.37 | Z58: 518037.47 | AA58: 525838.2 | AB58: 495327.49 | AC58: 483888.96 | AD58: 504877.33 | AE58: 548923.68 | AF58: 506133.32 | AG58: 505513.78 | AH58: 506251.41 | AI58: 476795.18 | AJ58: 523778.88 | AK58: 536962.37 | AL58: 519130.12 | AM58: 524397.76 | AN58: 548005.4 | AO58: 486047.75 | AP58: 510391.93 | AQ58: 506327.55 | AR58: 499546.66 | AS58: 508002.82 | AT58: 539410.78 | AU58: 530158.25 | AV58: 513544.8 | AW58: 508023.16 | AX58: 450916.41 | BF58: 140125 | BG58: De más de 360 días | BH58: 506251.41 | BI58: 140125 | BJ58: De más de 360 días | BK58: 476795.18
B59: 1402 | C59: CARTERA DE CRÉDITOS CONSUMO POR VENCER | D59: 15709710 | E59: 16304012 | F59: 16976903 | G59: 17767280 | H59: 17572313 | I59: 17680915 | J59: 17712186 | K59: 17772668 | L59: 16495765 | M59: 16400779 | N59: 16146113 | O59: 16031868 | P59: 16240949 | Q59: 15544857 | R59: 15671930 | S59: 15875618 | T59: 15704959 | U59: 15600109 | V59: 15083713 | W59: 14607269 | X59: 14550816 | Y59: 14746901 | Z59: 12338340 | AA59: 14282300 | AB59: 11356754 | AC59: 10967270 | AD59: 10304698 | AE59: 10188544 | AF59: 10790437 | AG59: 10361067 | AH59: 16655883 | AI59: 17200840 | AJ59: 17065000 | AK59: 17640924 | AL59: 18466470 | AM59: 20025988 | AN59: 20757555 | AO59: 21091096 | AP59: 20569155 | AQ59: 20077242 | AR59: 20683092 | AS59: 21564666 | AT59: 23620655 | AU59: 24421931 | AV59: 25935733 | AW59: 27557041 | AX59: 29255983 | BF59: 1402 | BG59: CARTERA DE CRÉDITOS CONSUMO POR VENCER | BH59: 16655883 | BI59: 1402 | BJ59: CARTERA DE CRÉDITOS CONSUMO POR VENCER | BK59: 17200840
B60: 140205 | C60: De 1 a 30 días | D60: 627155.08 | E60: 648340.33 | F60: 625332.63 | G60: 730989.79 | H60: 633890.84 | I60: 691583.11 | J60: 706614.16 | K60: 769813.26 | L60: 619621.53 | M60: 608344.79 | N60: 742751.87 | O60: 655729.38 | P60: 663705.87 | Q60: 658863.82 | R60: 743145.49 | S60: 782738.58 | T60: 660432.16 | U60: 675035.21 | V60: 650302.05 | W60: 764302.54 | X60: 861481.99 | Y60: 938276.26 | Z60: 545663.75 | AA60: 634995.51 | AB60: 340529.59 | AC60: 449652.81 | AD60: 387598.26 | AE60: 351560.35 | AF60: 379079.09 | AG60: 377847.8 | AH60: 684306.16 | AI60: 550346.18 | AJ60: 698753.84 | AK60: 576668.95 | AL60: 524365.55 | AM60: 532415.62 | AN60: 505861.88 | AO60: 533192.51 | AP60: 565918.08 | AQ60: 834102.33 | AR60: 586854.24 | AS60: 531805.65 | AT60: 593405.54 | AU60: 556471.04 | AV60: 559796.6 | AW60: 582394.18 | AX60: 596710.35 | BF60: 140205 | BG60: De 1 a 30 días | BH60: 684306.16 | BI60: 140205 | BJ60: De 1 a 30 días | BK60: 550346.18
B61: 140210 | C61: De 31 a 90 días | D61: 988917.08 | E61: 1063544.7 | F61: 1096153.2 | G61: 1110426.7 | H61: 1170170.6 | I61: 1231019.5 | J61: 1163976.8 | K61: 1049291.4 | L61: 1116759.2 | M61: 1149055.1 | N61: 1043436.7 | O61: 1049749.8 | P61: 1076703 | Q61: 1131881.6 | R61: 1165743.4 | S61: 1199011.6 | T61: 1134088.3 | U61: 1098206 | V61: 1063949.1 | W61: 1080936.1 | X61: 1069288.5 | Y61: 1086382.9 | Z61: 788998.07 | AA61: 1056820.2 | AB61: 713647.05 | AC61: 609344.09 | AD61: 616618.9 | AE61: 551194 | AF61: 899154.39 | AG61: 724638.56 | AH61: 1105808.1 | AI61: 1132925.8 | AJ61: 965037.91 | AK61: 965087.57 | AL61: 1212604.1 | AM61: 1199584.3 | AN61: 1017260.1 | AO61: 1366671.4 | AP61: 1351684.4 | AQ61: 1035022.4 | AR61: 1062227.8 | AS61: 1067920.8 | AT61: 1048196.4 | AU61: 1067210.9 | AV61: 1115026.4 | AW61: 1408687 | AX61: 1463530.9 | BF61: 140210 | BG61: De 31 a 90 días | BH61: 1105808.1 | BI61: 140210 | BJ61: De 31 a 90 días | BK61: 1132925.8
B62: 140215 | C62: De 91 a 180 días | D62: 1468608.6 | E62: 1421307.8 | F62: 1554944 | G62: 1612329.9 | H62: 1543809.7 | I62: 1568027.1 | J62: 1585960.2 | K62: 1624318.7 | L62: 1454460.2 | M62: 1509542.3 | N62: 1489599.9 | O62: 1490811.5 | P62: 1507168 | Q62: 1466445.9 | R62: 1503798.6 | S62: 1540464.6 | T62: 1570135.1 | U62: 1567073 | V62: 1552140.5 | W62: 1618311.1 | X62: 1628994 | Y62: 1673722.4 | Z62: 1174573.8 | AA62: 1454006.2 | AB62: 903434.75 | AC62: 865345.38 | AD62: 844938.17 | AE62: 1169391.7 | AF62: 899206.61 | AG62: 900917.34 | AH62: 1481373.2 | AI62: 1682170.8 | AJ62: 1629086.2 | AK62: 1678617.3 | AL62: 1731295 | AM62: 1779461.2 | AN62: 1812946.5 | AO62: 1538934.3 | AP62: 1510214.2 | AQ62: 1511900.1 | AR62: 1492634.2 | AS62: 1492751.1 | AT62: 1582684.4 | AU62: 1627170.4 | AV62: 1666579.8 | AW62: 1721742.8 | AX62: 1753491.9 | BF62: 140215 | BG62: De 91 a 180 días | BH62: 1481373.2 | BI62: 140215 | BJ62: De 91 a 180 días | BK62: 1682170.8
B63: 140220 | C63: De 181 a 360 días | D63: 2401688.6 | E63: 2450427.8 | F63: 2498328.5 | G63: 2731488.8 | H63: 2790714.3 | I63: 2719665.2 | J63: 2753905.4 | K63: 2832966.1 | L63: 2709869.1 | M63: 2711195.9 | N63: 2728273.3 | O63: 2733456.8 | P63: 2751506.2 | Q63: 2667498.6 | R63: 2639463.8 | S63: 2728971.2 | T63: 2720322.9 | U63: 2760719.4 | V63: 2758524.8 | W63: 2616094.7 | X63: 2609448.5 | Y63: 2541248.5 | Z63: 2052390.2 | AA63: 2462242 | AB63: 1762814.4 | AC63: 1690725.5 | AD63: 1567051.9 | AE63: 1491872.4 | AF63: 1550474.9 | AG63: 1512748.5 | AH63: 2684936.9 | AI63: 2659481.3 | AJ63: 2901750.2 | AK63: 2921036.9 | AL63: 2673610.5 | AM63: 2748342.2 | AN63: 2872026.9 | AO63: 2859001.9 | AP63: 2806555.9 | AQ63: 2768640.2 | AR63: 2826877.5 | AS63: 2889817.5 | AT63: 3015113.1 | AU63: 2999944.7 | AV63: 3083176.6 | AW63: 3133962.6 | AX63: 3260138.3 | BF63: 140220 | BG63: De 181 a 360 días | BH63: 2684936.9 | BI63: 140220 | BJ63: De 181 a 360 días | BK63: 2659481.3
B64: 140225 | C64: De más de 360 días | D64: 10223341 | E64: 10720391 | F64: 11202145 | G64: 11582045 | H64: 11433727 | I64: 11470620 | J64: 11501730 | K64: 11496279 | L64: 10595055 | M64: 10422641 | N64: 10142051 | O64: 10102121 | P64: 10241866 | Q64: 9620167 | R64: 9619778.8 | S64: 9624431.9 | T64: 9619980.9 | U64: 9499075.5 | V64: 9058796.2 | W64: 8527624.9 | X64: 8381603.4 | Y64: 8507270.6 | Z64: 7776713.8 | AA64: 8674235.9 | AB64: 7636328.5 | AC64: 7352201.9 | AD64: 6888491.2 | AE64: 6624525.1 | AF64: 7062521.8 | AG64: 6844914.5 | AH64: 10699458 | AI64: 11175916 | AJ64: 10870372 | AK64: 11499514 | AL64: 12324595 | AM64: 13766184 | AN64: 14549459 | AO64: 14793296 | AP64: 14334782 | AQ64: 13927577 | AR64: 14714499 | AS64: 15582371 | AT64: 17381255 | AU64: 18171134 | AV64: 19511154 | AW64: 20710254 | AX64: 22182112 | BF64: 140225 | BG64: De más de 360 días | BH64: 10699458 | BI64: 140225 | BJ64: De más de 360 días | BK64: 11175916
... B70: 140425 | C70: De más de 360 días | D70: 651130.37 | E70: 645818.46 | F70: 640375.4 | G70: 737699.15 | H70: 1219936.9 | I70: 1795713.3 | J70: 2211542.2 | K70: 2500278.4 | L70: 3243437.4 | M70: 3445342.4 | N70: 3835902.4 | O70: 4237141.2 | P70: 4654121 | Q70: 4754313.1 | R70: 4981263.7 | S70: 5480036.3 | T70: 5673568.9 | U70: 5715610.3 | V70: 5500331 | W70: 5219168.7 | X70: 5158351.2 | Y70: 4971622.6 | Z70: 4736942.7 | AA70: 4515025 | AB70: 4390736 | AC70: 4174116.8 | AD70: 4012147.7 | AE70: 3947560.5 | AF70: 4162049.6 | AG70: 3912328.2 | AH70: 4079815.8 | AI70: 3947650.5 | AJ70: 3566853.2 | AK70: 3577088.6 | AL70: 3490100.7 | AM70: 3492320.4 | AN70: 3693953.5 | AO70: 4255465.2 | AP70: 5573160.6 | AQ70: 6938056.1 | AR70: 8862542.9 | AS70: 9940404.1 | AT70: 10468133 | AU70: 10674600 | AV70: 11635003 | AW70: 12206105 | AX70: 12898789 | BF70: 140425 | BG70: De más de 360 días | BH70: 4079815.8 | BI70: 140425 | BJ70: De más de 360 días | BK70: 3947650.5
B71: 1410 | C71: CARTERA DE CRÉDITOS CONSUMO REFINANCIADA POR VENCER | J71: 13549.05 | K71: 13549.05 | L71: 13248.62 | M71: 13248.62 | N71: 13098.32 | O71: 12785.89 | P71: 12623.84 | Q71: 19365.96 | R71: 19207.27 | S71: 18889.82 | T71: 12125.08 | U71: 25764.24 | V71: 37272.76 | W71: 50938.28 | X71: 83341.37 | Y71: 117623.86 | Z71: 129152.68 | AA71: 148180.08 | AB71: 127243.32 | AC71: 154439.51 | AD71: 136535.48 | AE71: 204425.51 | AF71: 194358.52 | AG71: 170610.21 | AH71: 129004.01 | AI71: 137748.33 | AJ71: 163688.45 | AK71: 140698.19 | AL71: 178471.48 | AM71: 177358.14 | AN71: 174780.34 | AO71: 157355.02 | AP71: 165955.71 | AQ71: 150147.77 | AR71: 175307.56 | AS71: 201133.93 | AT71: 174009.64 | AU71: 228653.24 | AV71: 217587.7 | AW71: 213355.03 | AX71: 260130 | BF71: 1410 | BG71: CARTERA DE CRÉDITOS CONSUMO REFINANCIADA POR VENCER | BH71: 129004.01 | BI71: 1410 | BJ71: CARTERA DE CRÉDITOS CONSUMO REFINANCIADA POR VENCER | BK71: 137748.33
B72: 141005 | C72: DE 1 A 30 DIAS | J72: 152.13 | K72: 300.43 | L72: 150.3 | M72: 308.29 | N72: 312.43 | O72: 162.05 | P72: 158.69 | Q72: 476.14 | R72: 642.27 | S72: 640.1 | T72: 338.18 | U72: 278.38 | V72: 640.34 | W72: 637.91 | X72: 1355.26 | Y72: 1438.91 | Z72: 2518.01 | AA72: 2774.48 | AB72: 2691.92 | AC72: 4292.77 | AD72: 4450.99 | AE72: 5024.73 | AF72: 5341.44 | AG72: 4250.32 | AH72: 4287.74 | AI72: 4125.39 | AJ72: 5641.83 | AK72: 3874.8 | AL72: 4245.62 | AM72: 4130.85 | AN72: 9170.13 | AO72: 4459.68 | AP72: 4896.94 | AQ72: 3616.17 | AR72: 4454.15 | AS72: 5144.18 | AT72: 4223.46 | AU72: 5334.95 | AV72: 6029.68 | AW72: 7345.77 | AX72: 6934.8 | BF72: 141005 | BG72: DE 1 A 30 DIAS | BH72: 4287.74 | BI72: 141005 | BJ72: DE 1 A 30 DIAS | BK72: 4125.39
B73: 141010 | C73: DE 31 A 90 DIAS | J73: 148.3 | K73: 150.3 | L73: 157.99 | M73: 154.44 | N73: 162.05 | O73: 330.31 | P73: 340.07 | Q73: 640.1 | R73: 469.91 | S73: 481.4 | T73: 169.93 | U73: 579.22 | V73: 750.56 | W73: 1199.06 | X73: 1601.78 | Y73: 4072.22 | Z73: 4124.03 | AA73: 4579.2 | AB73: 4800.09 | AC73: 4501.57 | AD73: 5389.27 | AE73: 6545.86 | AF73: 6950.97 | AG73: 6328.06 | AH73: 5679.23 | AI73: 5744.9 | AJ73: 5992.32 | AK73: 4924.47 | AL73: 10855.37 | AM73: 11419.11 | AN73: 6418.05 | AO73: 6286.9 | AP73: 6215.55 | AQ73: 5896.69 | AR73: 6954.66 | AS73: 7202.67 | AT73: 6777.01 | AU73: 9053.2 | AV73: 9852.13 | AW73: 9740.25 | AX73: 10468.79 | BF73: 141010 | BG73: DE 31 A 90 DIAS | BH73: 5679.23 | BI73: 141010 | BJ73: DE 31 A 90 DIAS | BK73: 5744.9
B74: 141015 | C74: DE 91 A 180 DIAS | J74: 462.73 | K74: 474.48 | L74: 475.18 | M74: 492.36 | N74: 498.76 | O74: 333.84 | P74: 338.18 | Q74: 987.22 | R74: 990.77 | S74: 998.91 | T74: 528.79 | U74: 892.25 | V74: 1457.49 | W74: 2131.29 | X74: 3201.17 | Y74: 6827.97 | Z74: 7300.23 | AA74: 7810.8 | AB74: 7136.2 | AC74: 8354.81 | AD74: 8636.31 | AE74: 11347.17 | AF74: 11046.39 | AG74: 9607.83 | AH74: 7813.25 | AI74: 7417.03 | AJ74: 8551.29 | AK74: 8249.13 | AL74: 9580.03 | AM74: 9454.95 | AN74: 9472.8 | AO74: 9326.69 | AP74: 9960.57 | AQ74: 10094.18 | AR74: 11448.48 | AS74: 13170.96 | AT74: 13179.14 | AU74: 16495.36 | AV74: 16415.11 | AW74: 16781.68 | AX74: 18912.66 | BF74: 141015 | BG74: DE 91 A 180 DIAS | BH74: 7813.25 | BI74: 141015 | BJ74: DE 91 A 180 DIAS | BK74: 7417.03
B75: 141020 | C75: DE 181 A 360 DIAS | J75: 998.99 | K75: 1006.87 | L75: 1025.43 | M75: 1028.41 | N75: 1036.9 | O75: 1055.63 | P75: 1064.63 | Q75: 1892.62 | R75: 1921.21 | S75: 2129.27 | T75: 1131.6 | U75: 1914.64 | V75: 3091.53 | W75: 4550.6 | X75: 6863.38 | Y75: 14407.41 | Z75: 15418.69 | AA75: 15162.41 | AB75: 14247.51 | AC75: 16356.89 | AD75: 15250.94 | AE75: 20700.25 | AF75: 19283.76 | AG75: 18134.43 | AH75: 15541.19 | AI75: 16245.77 | AJ75: 18187.93 | AK75: 17295.27 | AL75: 20109.71 | AM75: 20351.64 | AN75: 20193.55 | AO75: 19283.27 | AP75: 19531.46 | AQ75: 20419.88 | AR75: 23046.93 | AS75: 28800.4 | AT75: 27511.57 | AU75: 35197.89 | AV75: 35072.71 | AW75: 35226.54 | AX75: 39374.36 | BF75: 141020 | BG75: DE 181 A 360 DIAS | BH75: 15541.19 | BI75: 141020 | BJ75: DE 181 A 360 DIAS | BK75: 16245.77
B76: 141025 | C76: DE MAS DE 360 DIAS | J76: 11786.9 | K76: 11616.97 | L76: 11439.72 | M76: 11265.12 | N76: 11088.18 | O76: 10904.06 | P76: 10722.27 | Q76: 15369.88 | R76: 15183.11 | S76: 14640.14 | T76: 9956.58 | U76: 22099.75 | V76: 31332.84 | W76: 42419.42 | X76: 70319.78 | Y76: 90877.35 | Z76: 99791.72 | AA76: 117853.19 | AB76: 98367.6 | AC76: 120933.47 | AD76: 102807.97 | AE76: 160807.5 | AF76: 151735.96 | AG76: 132289.57 | AH76: 95682.6 | AI76: 104215.24 | AJ76: 125315.08 | AK76: 106354.52 | AL76: 133680.75 | AM76: 132001.59 | AN76: 129525.81 | AO76: 117998.48 | AP76: 125351.19 | AQ76: 110120.85 | AR76: 129403.34 | AS76: 146815.72 | AT76: 122318.46 | AU76: 162571.84 | AV76: 150218.07 | AW76: 144260.79 | AX76: 184439.39 | BF76: 141025 | BG76: DE MAS DE 360 DIAS | BH76: 95682.6 | BI76: 141025 | BJ76: DE MAS DE 360 DIAS | BK76: 104215.24
B77: 1412 | C77: CARTERA DE MICROCRÉDITO REFINANCIADA POR VENCER | W77: 30942.94 | X77: 56130.02 | Y77: 95559.15 | Z77: 117323.1 | AA77: 78308.7 | AB77: 66919.58 | AC77: 59660.07 | AD77: 72663.12 | AE77: 75490.88 | AF77: 77339.77 | AG77: 92582.58 | AH77: 79069.27 | AI77: 92524.83 | AJ77: 110455.11 | AK77: 89751.13 | AL77: 83678.12 | AM77: 164462.17 | AN77: 100463.39 | AO77: 99773.41 | AP77: 99366.86 | AQ77: 84676.29 | AR77: 96007.14 | AS77: 95129.66 | AT77: 81766.93 | AU77: 80596.92 | AV77: 79582.5 | AW77: 78771.93 | AX77: 77541.86 | BF77: 1412 | BG77: CARTERA DE MICROCRÉDITO REFINANCIADA POR VENCER | BH77: 79069.27 | BI77: 1412 | BJ77: CARTERA DE MICROCRÉDITO REFINANCIADA POR VENCER | BK77: 92524.83
B78: 141205 | C78: De 1 a 30 días | W78: 231.1 | X78: 529.98 | Y78: 658.08 | Z78: 769.19 | AA78: 680.39 | AB78: 313.39 | AC78: 222.2 | AD78: 830.17 | AE78: 876.45 | AF78: 607.33 | AG78: 1085.39 | AH78: 907.72 | AI78: 1115.72 | AJ78: 913 | AK78: 879.71 | AL78: 1004.54 | AM78: 1199.09 | AN78: 1285.47 | AO78: 1708.63 | AP78: 2412.87 | AQ78: 1693.84 | AR78: 1919.62 | AS78: 2012.2 | AT78: 1564.31 | AU78: 1402.77 | AV78: 1416.08 | AW78: 1680.69 | AX78: 1684.23 | BF78: 141205 | BG78: De 1 a 30 días | BH78: 907.72 | BI78: 141205 | BJ78: De 1 a 30 días | BK78: 1115.72
B79: 141210 | C79: De 31 a 90 días | W79: 488.25 | X79: 869.57 | Y79: 1321.39 | Z79: 1920.92 | AA79: 1465.14 | AB79: 942.1 | AC79: 972.58 | AD79: 1223.74 | AE79: 1200.65 | AF79: 1286.27 | AG79: 1790.67 | AH79: 1540.16 | AI79: 1668.64 | AJ79: 2179.49 | AK79: 2168.57 | AL79: 2086.41 | AM79: 3145.19 | AN79: 2752.99 | AO79: 2790.96 | AP79: 2742.45 | AQ79: 2278.53 | AR79: 2645.44 | AS79: 2681.96 | AT79: 2383.79 | AU79: 2449.79 | AV79: 2483.38 | AW79: 2516.34 | AX79: 2550.85 | BF79: 141210 | BG79: De 31 a 90 días | BH79: 1540.16 | BI79: 141210 | BJ79: De 31 a 90 días | BK79: 1668.64
B80: 141215 | C80: De 91 a 180 días | W80: 753.3 | X80: 1405.79 | Y80: 2655.07 | Z80: 3341.7 | AA80: 2387.18 | AB80: 1766.53 | AC80: 1541.81 | AD80: 1886.65 | AE80: 2116.92 | AF80: 2239.94 | AG80: 2757.25 | AH80: 2457.41 | AI80: 2848.54 | AJ80: 3865.23 | AK80: 3420.32 | AL80: 3602.13 | AM80: 6136.96 | AN80: 4121.42 | AO80: 4218.64 | AP80: 4017.5 | AQ80: 3585.99 | AR80: 4084.43 | AS80: 4140.87 | AT80: 3766.11 | AU80: 3784.46 | AV80: 3836.36 | AW80: 3948.29 | AX80: 4002.43 | BF80: 141215 | BG80: De 91 a 180 días | BH80: 2457.41 | BI80: 141215 | BJ80: De 91 a 180 días | BK80: 2848.54
B81: 141220 | C81: De 181 a 360 días | W81: 1354.78 | X81: 2777.03 | Y81: 5305.1 | Z81: 6778.48 | AA81: 4944.66 | AB81: 3803.41 | AC81: 3234.34 | AD81: 4029.19 | AE81: 4609.12 | AF81: 4828.43 | AG81: 5976.79 | AH81: 5217.69 | AI81: 6172.86 | AJ81: 8360.95 | AK81: 7124.56 | AL81: 7320.96 | AM81: 12200.98 | AN81: 8568.2 | AO81: 8650.66 | AP81: 8801.05 | AQ81: 7714.4 | AR81: 8759.05 | AS81: 8913.95 | AT81: 7999.43 | AU81: 8137.22 | AV81: 8248.8 | AW81: 8270.41 | AX81: 8410.06 | BF81: 141220 | BG81: De 181 a 360 días | BH81: 5217.69 | BI81: 141220 | BJ81: De 181 a 360 días | BK81: 6172.86
B82: 141225 | C82: De más de 360 días | W82: 28115.51 | X82: 50547.65 | Y82: 85619.51 | Z82: 104512.81 | AA82: 68831.33 | AB82: 60094.15 | AC82: 53689.14 | AD82: 64693.37 | AE82: 66687.74 | AF82: 68377.8 | AG82: 80972.48 | AH82: 68946.29 | AI82: 80719.07 | AJ82: 95136.44 | AK82: 76157.97 | AL82: 69664.08 | AM82: 141779.95 | AN82: 83735.31 | AO82: 82404.52 | AP82: 81392.99 | AQ82: 69403.53 | AR82: 78598.6 | AS82: 77380.68 | AT82: 66053.29 | AU82: 64822.68 | AV82: 63597.88 | AW82: 62356.2 | AX82: 60894.29 | BF82: 141225 | BG82: De más de 360 días | BH82: 68946.29 | BI82: 141225 | BJ82: De más de 360 días | BK82: 80719.07
B83: 1418 | C83: CARTERA DE CRÉDITOS CONSUMO REESTRUCTURADA POR VENCER | D83: 26201.66 | E83: 25435.53 | F83: 24494.63 | G83: 28579.79 | H83: 27599.36 | I83: 21556.93 | J83: 15979.25 | K83: 15065.3 | L83: 14223.34 | M83: 13290.81 | N83: 12342.43 | O83: 11381.63 | P83: 10049.69 | Q83: 9166.07 | R83: 8247.42 | S83: 7231.35 | T83: 6856.37 | U83: 6304.02 | V83: 5744.16 | W83: 20189.48 | X83: 96839.78 | Y83: 126080.62 | Z83: 144531.66 | AA83: 142105.08 | AB83: 132810.86 | AC83: 101408.8 | AD83: 81016.33 | AE83: 115232.46 | AF83: 128355.74 | AG83: 96505.46 | AH83: 95511.67 | AI83: 87312.87 | AJ83: 99309.76 | AK83: 83344.78 | AL83: 118472.19 | AM83: 103611.84 | AN83: 92990.63 | AO83: 101710.24 | AP83: 98503.35 | AQ83: 97754.1 | AR83: 105139.16 | AS83: 98287.52 | AT83: 113920.12 | AU83: 79105.12 | AV83: 68014.56 | AW83: 66408.22 | AX83: 56238.4 | BF83: 1418 | BG83: CARTERA DE CRÉDITOS CONSUMO REESTRUCTURADA POR VENCER | BH83: 95511.67 | BI83: 1418 | BJ83: CARTERA DE CRÉDITOS CONSUMO REESTRUCTURADA POR VENCER | BK83: 87312.87
B84: 141805 | C84: De 1 a 30 días | D84: 1165.2 | E84: 1502.45 | F84: 1395.97 | G84: 1941.37 | H84: 1804.84 | I84: 1582.98 | J84: 1168.06 | K84: 1178.66 | L84: 1435.63 | M84: 1297 | N84: 1477.5 | O84: 1331.94 | P84: 989.67 | Q84: 1285.62 | R84: 1218.26 | S84: 927.33 | T84: 934.91 | U84: 1127.3 | V84: 662.3 | W84: 594.55 | X84: 1169.97 | Y84: 1960.84 | Z84: 2432.33 | AA84: 2873.22 | AB84: 3016.83 | AC84: 1805.41 | AD84: 1111.9 | AE84: 1649.86 | AF84: 2340.84 | AG84: 2050.59 | AH84: 2462.26 | AI84: 2373.68 | AJ84: 1768.31 | AK84: 1080.25 | AL84: 1920.85 | AM84: 2613.22 | AN84: 1905.42 | AO84: 2347.75 | AP84: 2293.13 | AQ84: 2039.32 | AR84: 2972.36 | AS84: 2255.67 | AT84: 2872.1 | AU84: 2189.2 | AV84: 2579.04 | AW84: 2499.3 | AX84: 1910.89 | BF84: 141805 | BG84: De 1 a 30 días | BH84: 2462.26 | BI84: 141805 | BJ84: De 1 a 30 días | BK84: 2373.68
B85: 141810 | C85: De 31 a 90 días | D85: 2085.78 | E85: 1959.44 | F85: 1721.46 | G85: 1990.47 | H85: 2567.1 | I85: 1637.97 | J85: 1602.03 | K85: 1628.42 | L85: 1490.03 | M85: 1672.6 | N85: 1530.51 | O85: 2169.24 | P85: 2203.65 | Q85: 1576.43 | R85: 817.52 | S85: 652.37 | T85: 839.6 | U85: 371.88 | V85: 557.7 | W85: 1027.69 | X85: 2332.46 | Y85: 3198.77 | Z85: 3662.62 | AA85: 4485.82 | AB85: 4336.86 | AC85: 3100.4 | AD85: 2820 | AE85: 3384.41 | AF85: 4206.06 | AG85: 3104.47 | AH85: 3420.79 | AI85: 3288.57 | AJ85: 2827.76 | AK85: 2934.51 | AL85: 3614.47 | AM85: 3785.38 | AN85: 3633.23 | AO85: 3798.91 | AP85: 3462.28 | AQ85: 3614.83 | AR85: 3856.23 | AS85: 3570.63 | AT85: 4186.15 | AU85: 3673.97 | AV85: 3205.4 | AW85: 3085.09 | AX85: 2808.07 | BF85: 141810 | BG85: De 31 a 90 días | BH85: 3420.79 | BI85: 141810 | BJ85: De 31 a 90 días | BK85: 3288.57
B86: 141815 | C86: De 91 a 180 días | D86: 2571.65 | E86: 2866.23 | F86: 3041.22 | G86: 4302.82 | H86: 4359.87 | I86: 3164.71 | J86: 2887.95 | K86: 2923.8 | L86: 2962.66 | M86: 3009.48 | N86: 2568.04 | O86: 1668.81 | P86: 1204.72 | Q86: 1222.16 | R86: 1406.8 | S86: 1127.49 | T86: 844.05 | U86: 855.22 | V86: 868.25 | W86: 1350.71 | X86: 3799.32 | Y86: 5538.3 | Z86: 6437.37 | AA86: 7148.32 | AB86: 6775.32 | AC86: 5259.71 | AD86: 4543.07 | AE86: 5753.33 | AF86: 6375.92 | AG86: 5160.64 | AH86: 5261.92 | AI86: 5022.64 | AJ86: 4739.71 | AK86: 4605.13 | AL86: 6237.31 | AM86: 5952.15 | AN86: 5291.76 | AO86: 5709.22 | AP86: 5531.74 | AQ86: 5762.04 | AR86: 6136.47 | AS86: 5612.01 | AT86: 7059.09 | AU86: 5859.23 | AV86: 5363.05 | AW86: 5619.68 | AX86: 4720.91 | BF86: 141815 | BG86: De 91 a 180 días | BH86: 5261.92 | BI86: 141815 | BJ86: De 91 a 180 días | BK86: 5022.64
B87: 141820 | C87: De 181 a 360 días | D87: 6294.84 | E87: 6120.43 | F87: 6460.34 | G87: 9158.5 | H87: 8793.9 | I87: 5770.55 | J87: 4669.56 | K87: 4252.56 | L87: 3530.18 | M87: 2787.57 | N87: 2528.57 | O87: 2262.02 | P87: 1995.74 | Q87: 1721.84 | R87: 1744.62 | S87: 1770.36 | T87: 1791.84 | U87: 1816.61 | V87: 1838.95 | W87: 3359.87 | X87: 8529.6 | Y87: 11283.9 | Z87: 13212.78 | AA87: 14662.17 | AB87: 14034.53 | AC87: 10524.09 | AD87: 9390.95 | AE87: 12371.21 | AF87: 13706.97 | AG87: 11115.02 | AH87: 11239.79 | AI87: 10815 | AJ87: 10233.9 | AK87: 9461.4 | AL87: 12754.93 | AM87: 12467.23 | AN87: 11168.27 | AO87: 11163.29 | AP87: 11156.36 | AQ87: 11561.54 | AR87: 12204.59 | AS87: 11415.14 | AT87: 14736.63 | AU87: 12564.83 | AV87: 11523.34 | AW87: 11470.7 | AX87: 9574.96 | BF87: 141820 | BG87: De 181 a 360 días | BH87: 11239.79 | BI87: 141820 | BJ87: De 181 a 360 días | BK87: 10815
B88: 141825 | C88: De más de 360 días | D88: 14084.19 | E88: 12986.98 | F88: 11875.64 | G88: 11186.63 | H88: 10073.65 | I88: 9400.72 | J88: 5651.65 | K88: 5081.86 | L88: 4804.84 | M88: 4524.16 | N88: 4237.81 | O88: 3949.62 | P88: 3655.91 | Q88: 3360.02 | R88: 3060.22 | S88: 2753.8 | T88: 2445.97 | U88: 2133.01 | V88: 1816.96 | W88: 13856.66 | X88: 81008.43 | Y88: 104098.81 | Z88: 118786.56 | AA88: 112935.55 | AB88: 104647.32 | AC88: 80719.19 | AD88: 63150.41 | AE88: 92073.65 | AF88: 101725.95 | AG88: 75074.74 | AH88: 73126.91 | AI88: 65812.98 | AJ88: 79740.08 | AK88: 65263.49 | AL88: 93944.63 | AM88: 78793.86 | AN88: 70991.95 | AO88: 78691.07 | AP88: 76059.84 | AQ88: 74776.37 | AR88: 79969.51 | AS88: 75434.07 | AT88: 85066.15 | AU88: 54817.89 | AV88: 45343.73 | AW88: 43733.45 | AX88: 37223.57 | BF88: 141825 | BG88: De más de 360 días | BH88: 73126.91 | BI88: 141825 | BJ88: De más de 360 días | BK88: 65812.98
B89: 1420 | C89: CARTERA DE MICROCRÉDITO REESTRUCTURADA POR VENCER | X89: 13747.92 | Y89: 33930.45 | Z89: 33900.54 | AA89: 37038.19 | AB89: 94865.44 | AC89: 129942.19 | AD89: 153677.07 | AE89: 100932.02 | AF89: 102908.48 | AG89: 114241.05 | AH89: 113714.14 | AI89: 56568.43 | AJ89: 97631.58 | AK89: 73219.25 | AL89: 119937.59 | AM89: 92995.09 | AN89: 76810.63 | AO89: 78018.2 | AP89: 107902.06 | AQ89: 94486.22 | AR89: 45461.35 | AS89: 25926.7 | AT89: 36182.68 | AU89: 35653.36 | AV89: 34776.33 | AW89: 34573.33 | AX89: 22485.73 | BF89: 1420 | BG89: CARTERA DE MICROCRÉDITO REESTRUCTURADA POR VENCER | BH89: 113714.14 | BI89: 1420 | BJ89: CARTERA DE MICROCRÉDITO REESTRUCTURADA POR VENCER | BK89: 56568.43
B90: 142005 | C90: DE 1 A 30 DIAS | X90: 142.34 | Y90: 180.75 | Z90: 297.47 | AA90: 159.88 | AB90: 264.32 | AC90: 739.13 | AD90: 1975.3 | AE90: 1268.31 | AF90: 1551.33 | AG90: 1777.05 | AH90: 2571.08 | AI90: 1412.84 | AJ90: 1049.51 | AK90: 770.81 | AL90: 1046.4 | AM90: 850.11 | AN90: 1189.34 | AO90: 1560.87 | AP90: 2403.18 | AQ90: 2194.49 | AR90: 1849.17 | AS90: 944.79 | AT90: 1017.6 | AU90: 1023.57 | AV90: 694.56 | AW90: 1211.32 | AX90: 562.91 | BF90: 142005 | BG90: DE 1 A 30 DIAS | BH90: 2571.08 | BI90: 142005 | BJ90: DE 1 A 30 DIAS | BK90: 1412.84
B91: 142010 | C91: DE 31 A 90 DIAS | X91: 297.47 | Y91: 461.57 | Z91: 617.77 | AA91: 739.13 | AB91: 1718.4 | AC91: 2699.8 | AD91: 3495.11 | AE91: 2140.87 | AF91: 2237.54 | AG91: 2608.69 | AH91: 2594.35 | AI91: 1452.84 | AJ91: 1979.77 | AK91: 2092.46 | AL91: 2021.68 | AM91: 1989.49 | AN91: 1762.86 | AO91: 2314.81 | AP91: 2522.37 | AQ91: 3295.15 | AR91: 2027.05 | AS91: 972.63 | AT91: 1378.98 | AU91: 1414.32 | AV91: 1435.25 | AW91: 1455.81 | AX91: 1161.69 | BF91: 142010 | BG91: DE 31 A 90 DIAS | BH91: 2594.35 | BI91: 142010 | BJ91: DE 31 A 90 DIAS | BK91: 1452.84
B92: 142015 | C92: DE 91 A 180 DIAS | X92: 459.36 | Y92: 955.72 | Z92: 970.54 | AA92: 1646.66 | AB92: 3494.66 | AC92: 4744.79 | AD92: 5545.9 | AE92: 3308.94 | AF92: 3455.1 | AG92: 4028.89 | AH92: 4137.24 | AI92: 2246.28 | AJ92: 3922.57 | AK92: 3308.24 | AL92: 4055.68 | AM92: 2932.4 | AN92: 2359.27 | AO92: 3508.78 | AP92: 4322.27 | AQ92: 5206.1 | AR92: 3146.51 | AS92: 1507.35 | AT92: 2175.57 | AU92: 2192.85 | AV92: 2225.32 | AW92: 2283.58 | AX92: 1821.99 | BF92: 142015 | BG92: DE 91 A 180 DIAS | BH92: 4137.24 | BI92: 142015 | BJ92: DE 91 A 180 DIAS | BK92: 2246.28
B93: 142020 | C93: DE 181 A 360 DIAS | X93: 992.88 | Y93: 2014.97 | Z93: 2061.58 | AA93: 3040.88 | AB93: 7206.13 | AC93: 9717.58 | AD93: 10303.42 | AE93: 7208.05 | AF93: 7144.64 | AG93: 8744.71 | AH93: 8495.91 | AI93: 4863.75 | AJ93: 8528.52 | AK93: 6604.42 | AL93: 8477.8 | AM93: 6264.45 | AN93: 5594.43 | AO93: 7440.02 | AP93: 8237.93 | AQ93: 11251.04 | AR93: 6387.53 | AS93: 3248.88 | AT93: 4248.66 | AU93: 4723.59 | AV93: 4793.53 | AW93: 4411.77 | AX93: 3868.14 | BF93: 142020 | BG93: DE 181 A 360 DIAS | BH93: 8495.91 | BI93: 142020 | BJ93: DE 181 A 360 DIAS | BK93: 4863.75
B94: 142025 | C94: DE MAS DE 360 DIAS | X94: 11855.87 | Y94: 30317.44 | Z94: 29953.18 | AA94: 31451.64 | AB94: 82181.93 | AC94: 112040.89 | AD94: 132357.34 | AE94: 87005.85 | AF94: 88519.87 | AG94: 97081.71 | AH94: 95915.56 | AI94: 46592.72 | AJ94: 82151.21 | AK94: 60443.32 | AL94: 104336.03 | AM94: 80958.64 | AN94: 65904.73 | AO94: 63193.72 | AP94: 90416.31 | AQ94: 72539.44 | AR94: 32051.09 | AS94: 19253.05 | AT94: 27361.87 | AU94: 26299.03 | AV94: 25627.67 | AW94: 25210.85 | AX94: 15071 | BF94: 142025 | BG94: DE MAS DE 360 DIAS | BH94: 95915.56 | BI94: 142025 | BJ94: DE MAS DE 360 DIAS | BK94: 46592.72
B95: 1425 | C95: CARTERA DE CRÉDITOS PRODUCTIVO QUE NO DEVENGA INTERESES | K95: 71995.58 | L95: 69881.13 | M95: 120662.9 | N95: 65579.67 | O95: 111206.1 | P95: 61207.52 | Q95: 56762.77 | R95: 56762.77 | S95: 52229.42 | T95: 49934.69 | U95: 47634.83 | V95: 45302.73 | W95: 42963.94 | X95: 40593.85 | Y95: 38215.49 | Z95: 60992.55 | AA95: 33388.92 | AB95: 55185.63 | AC95: 52245.08 | AD95: 28482.21 | AE95: 46284.39 | AF95: 83840.65 | AG95: 51341.6 | AH95: 26695.99 | AI95: 44647.41 | AJ95: 51366.04 | AK95: 28326.03 | AL95: 24645.21 | AM95: 0 | AN95: 0 | AO95: 67647.22 | AP95: 0 | AQ95: 9254.51 | AR95: 0 | AS95: 0 | AT95: 0 | AU95: 0 | AV95: 9272.61 | AW95: 0 | AX95: 0 | BF95: 1425 | BG95: CARTERA DE CRÉDITOS PRODUCTIVO QUE NO DEVENGA INTERESES | BH95: 26695.99 | BI95: 1425 | BJ95: CARTERA DE CRÉDITOS PRODUCTIVO QUE NO DEVENGA INTERESES | BK95: 44647.41
B96: 142505 | C96: De 1 a 30 días | K96: 6415.91 | L96: 6469.83 | M96: 14279.5 | N96: 6577.26 | O96: 14562.12 | P96: 6687.22 | Q96: 4533.35 | R96: 6828.08 | S96: 4594.59 | T96: 4631.96 | U96: 4670.89 | V96: 4708.88 | W96: 4748.45 | X96: 4776.71 | Y96: 4826.57 | Z96: 5806.92 | AA96: 4906.71 | AB96: 5420.7 | AC96: 5960.69 | AD96: 7516.65 | AE96: 6055.09 | AF96: 8309.82 | AG96: 6694.19 | AH96: 5739.1 | AI96: 6291.61 | AJ96: 7134.37 | AK96: 6356.65 | AL96: 6420.02 | AM96: 0 | AN96: 0 | AO96: 3477.9 | AP96: 0 | AQ96: 1164.32 | AR96: 0 | AS96: 0 | AT96: 0 | AU96: 0 | AV96: 279.3 | AW96: 0 | AX96: 0 | BF96: 142505 | BG96: De 1 a 30 días | BH96: 5739.1 | BI96: 142505 | BJ96: De 1 a 30 días | BK96: 6291.61
B97: 142510 | C97: De 31 a 90 días | K97: 2168.37 | L97: 2203.78 | M97: 7499.78 | N97: 2239.64 | O97: 9913.55 | P97: 4585.61 | Q97: 4594.59 | R97: 2299.86 | S97: 2332.1 | T97: 2338.79 | U97: 2370.09 | V97: 2378.36 | W97: 2398.35 | X97: 2428.22 | Y97: 2438.91 | Z97: 2940.55 | AA97: 2480.15 | AB97: 6008.99 | AC97: 6055.09 | AD97: 2543.33 | AE97: 3064.87 | AF97: 5840.27 | AG97: 3661.63 | AH97: 3177.24 | AI97: 4235.11 | AJ97: 4039.12 | AK97: 3744.19 | AL97: 528.23 | AM97: 0 | AN97: 0 | AO97: 3611.75 | AP97: 0 | AQ97: 1180.75 | AR97: 0 | AS97: 0 | AT97: 0 | AU97: 0 | AV97: 287.93 | AW97: 0 | AX97: 0 | BF97: 142510 | BG97: De 31 a 90 días | BH97: 3177.24 | BI97: 142510 | BJ97: De 31 a 90 días | BK97: 4235.11
B98: 142515 | C98: De 91 a 180 días | K98: 6648.53 | L98: 6687.22 | M98: 14911.42 | N98: 6828.08 | O98: 12892.6 | P98: 4631.96 | Q98: 7040.98 | R98: 7040.98 | S98: 7087.24 | T98: 7146.8 | U98: 7204.93 | V98: 7265.48 | W98: 7334.93 | X98: 7386.86 | Y98: 7456 | Z98: 8975.23 | AA98: 7579.83 | AB98: 6591.51 | AC98: 6157.25 | AD98: 7767.63 | AE98: 9347.47 | AF98: 12875.96 | AG98: 10338.74 | AH98: 8867.39 | AI98: 7795.32 | AJ98: 5580.34 | AK98: 1614.7 | AL98: 1629.61 | AM98: 0 | AN98: 0 | AO98: 5498.65 | AP98: 0 | AQ98: 1812.64 | AR98: 0 | AS98: 0 | AT98: 0 | AU98: 0 | AV98: 441.31 | AW98: 0 | AX98: 0 | BF98: 142515 | BG98: De 91 a 180 días | BH98: 8867.39 | BI98: 142515 | BJ98: De 91 a 180 días | BK98: 7795.32
B99: 142520 | C99: De 181 a 360 días | K99: 13798.83 | L99: 13926.45 | M99: 30933.1 | N99: 14117.55 | O99: 31474.72 | P99: 14352.72 | Q99: 12111.64 | R99: 14591.79 | S99: 14721.48 | T99: 14851.58 | U99: 14966.69 | V99: 15097.48 | W99: 15215.98 | X99: 15347.46 | Y99: 15469.39 | Z99: 18624.64 | AA99: 15725.53 | AB99: 18939.24 | AC99: 16375.09 | AD99: 10654.6 | AE99: 11206.47 | AF99: 15773.34 | AG99: 7671.7 | AH99: 1747.02 | AI99: 5061.77 | AJ99: 6039.85 | AK99: 3344.47 | AL99: 3379.29 | AM99: 0 | AN99: 0 | AO99: 11461.32 | AP99: 0 | AQ99: 3786.41 | AR99: 0 | AS99: 0 | AT99: 0 | AU99: 0 | AV99: 931.31 | AW99: 0 | AX99: 0 | BF99: 142520 | BG99: De 181 a 360 días | BH99: 1747.02 | BI99: 142520 | BJ99: De 181 a 360 días | BK99: 5061.77
B100: 142525 | C100: De más de 360 días | K100: 42963.94 | L100: 40593.85 | M100: 53039.1 | N100: 35817.14 | O100: 42363.11 | P100: 30950.01 | Q100: 28482.21 | R100: 26002.06 | S100: 23494.01 | T100: 20965.56 | U100: 18422.23 | V100: 15852.53 | W100: 13266.23 | X100: 10654.6 | Y100: 8024.62 | Z100: 24645.21 | AA100: 2696.7 | AB100: 18225.19 | AC100: 17696.96 | AE100: 16610.49 | AF100: 41041.26 | AG100: 22975.34 | AH100: 7165.24 | AI100: 21263.6 | AJ100: 28572.36 | AK100: 13266.02 | AL100: 12688.06 | AM100: 0 | AN100: 0 | AO100: 43597.6 | AP100: 0 | AQ100: 1310.39 | AR100: 0 | AS100: 0 | AT100: 0 | AU100: 0 | AV100: 7332.76 | AW100: 0 | AX100: 0 | BF100: 142525 | BG100: De más de 360 días | BH100: 7165.24 | BI100: 142525 | BJ100: De más de 360 días | BK100: 21263.6
B101: 1426 | C101: CARTERA DE CRÉDITOS CONSUMO QUE NO DEVENGA INTERESES | D101: 189630.16 | E101: 208610.96 | F101: 170644.88 | G101: 198369.93 | H101: 295190.45 | I101: 345086.15 | J101: 389150.87 | K101: 404101.41 | L101: 527609.94 | M101: 574711.52 | N101: 735583.98 | O101: 743351.67 | P101: 720126.37 | Q101: 1263864 | R101: 1417129.9 | S101: 1317581.8 | T101: 1257748 | U101: 1334641.1 | V101: 1325151.6 | W101: 1337626.4 | X101: 1175593.8 | Y101: 1239264.6 | Z101: 3107586.6 | AA101: 1292095.9 | AB101: 1257856.4 | AC101: 1267284.4 | AD101: 1402547.2 | AE101: 1558335.4 | AF101: 1033212.3 | AG101: 1179102.3 | AH101: 1244410.8 | AI101: 1105785.1 | AJ101: 1364010.3 | AK101: 1266527 | AL101: 1429252.6 | AM101: 637091.72 | AN101: 354003.72 | AO101: 253248.33 | AP101: 374599.78 | AQ101: 346967.77 | AR101: 406888.42 | AS101: 301091.19 | AT101: 301560.53 | AU101: 342591.59 | AV101: 309941.43 | AW101: 326390.56 | AX101: 525323.29 | BF101: 1426 | BG101: CARTERA DE CRÉDITOS CONSUMO QUE NO DEVENGA INTERESES | BH101: 1244410.8 | BI101: 1426 | BJ101: CARTERA DE CRÉDITOS CONSUMO QUE NO DEVENGA INTERESES | BK101: 1105785.1
B102: 142605 | C102: De 1 a 30 días | D102: 43695.87 | E102: 41810.27 | F102: 35394.6 | G102: 33264.4 | H102: 38853.02 | I102: 34284.77 | J102: 36328.42 | K102: 32357.27 | L102: 46622.51 | M102: 51231.74 | N102: 63042.53 | O102: 66471.74 | P102: 63274.95 | Q102: 71441.48 | R102: 87516.91 | S102: 84111.9 | T102: 80091.21 | U102: 87220.41 | V102: 91939.99 | W102: 100219.75 | X102: 95006.42 | Y102: 102285.26 | Z102: 430947.7 | AA102: 104766.45 | AB102: 104285.95 | AC102: 107358.22 | AD102: 125540.34 | AE102: 132522.9 | AF102: 116894.65 | AG102: 121935.92 | AH102: 132859.17 | AI102: 132147.16 | AJ102: 143183.84 | AK102: 134557.92 | AL102: 133931.14 | AM102: 43890.06 | AN102: 30517.15 | AO102: 20227.5 | AP102: 21127.86 | AQ102: 19916.51 | AR102: 24704.72 | AS102: 20713.74 | AT102: 23624.64 | AU102: 19962.2 | AV102: 22893.38 | AW102: 19864.47 | AX102: 24275.49 | BF102: 142605 | BG102: De 1 a 30 días | BH102: 132859.17 | BI102: 142605 | BJ102: De 1 a 30 días | BK102: 132147.16
B103: 142610 | C103: De 31 a 90 días | D103: 26432.09 | E103: 21794.59 | F103: 14886.38 | G103: 14607.85 | H103: 19001.8 | I103: 16546.74 | J103: 19209.63 | K103: 19191.51 | L103: 28516.29 | M103: 32828.85 | N103: 38692.1 | O103: 43208.96 | P103: 44806.72 | Q103: 72186.12 | R103: 86155.53 | S103: 84892.98 | T103: 80853.86 | U103: 85942.02 | V103: 88108.71 | W103: 98337.59 | X103: 90651.25 | Y103: 99538.18 | Z103: 381100.1 | AA103: 99406.41 | AB103: 107201.22 | AC103: 107631.45 | AD103: 120051.97 | AE103: 126019.24 | AF103: 115578.69 | AG103: 116845.72 | AH103: 122589.75 | AI103: 121512.26 | AJ103: 124046.42 | AK103: 116993.05 | AL103: 108790.7 | AM103: 36348.71 | AN103: 24085.65 | AO103: 16175.84 | AP103: 18511.03 | AQ103: 17944.32 | AR103: 24186.84 | AS103: 19667.56 | AT103: 21539.22 | AU103: 19176.27 | AV103: 21507.81 | AW103: 17388.62 | AX103: 23231.32 | BF103: 142610 | BG103: De 31 a 90 días | BH103: 122589.75 | BI103: 142610 | BJ103: De 31 a 90 días | BK103: 121512.26
B104: 142615 | C104: De 91 a 180 días | D104: 22166.78 | E104: 19751.44 | F104: 14462.39 | G104: 15044.52 | H104: 23115.94 | I104: 23758.45 | J104: 29404.69 | K104: 30158.97 | L104: 40250.56 | M104: 48424.56 | N104: 61681.59 | O104: 65233.43 | P104: 66076.85 | Q104: 111327.33 | R104: 129611.74 | S104: 126935.56 | T104: 119469.08 | U104: 130509.87 | V104: 138870.67 | W104: 147197.22 | X104: 135111.89 | Y104: 145442.02 | Z104: 496804.82 | AA104: 156390.64 | AB104: 156496.41 | AC104: 159180.87 | AD104: 178650.61 | AE104: 192429.22 | AF104: 162173.86 | AG104: 164047.3 | AH104: 163359.97 | AI104: 150612.87 | AJ104: 150261.23 | AK104: 137290.52 | AL104: 133448.17 | AM104: 48294.12 | AN104: 32635.93 | AO104: 22635.58 | AP104: 28825.47 | AQ104: 28170.27 | AR104: 34294.41 | AS104: 27321.8 | AT104: 29922.75 | AU104: 24787.65 | AV104: 27120.23 | AW104: 25245.66 | AX104: 33294.84 | BF104: 142615 | BG104: De 91 a 180 días | BH104: 163359.97 | BI104: 142615 | BJ104: De 91 a 180 días | BK104: 150612.87
B105: 142620 | C105: De 181 a 360 días | D105: 18495.55 | E105: 22195.91 | F105: 20875.32 | G105: 27861.97 | H105: 43962.34 | I105: 50281.98 | J105: 61371.04 | K105: 64432.96 | L105: 85830.87 | M105: 97680.04 | N105: 125806.99 | O105: 133213 | P105: 137617.92 | Q105: 221340.37 | R105: 261837.2 | S105: 260490.85 | T105: 245236.06 | U105: 267808.62 | V105: 274933.66 | W105: 293577.68 | X105: 275156.52 | Y105: 275318.57 | Z105: 746271.27 | AA105: 296028.58 | AB105: 292460.76 | AC105: 281208.63 | AD105: 301898.56 | AE105: 300756.29 | AF105: 221084.28 | AG105: 217922.07 | AH105: 217478.75 | AI105: 196199.68 | AJ105: 217497.47 | AK105: 205608.79 | AL105: 230750.26 | AM105: 89361.99 | AN105: 56049.25 | AO105: 42501.18 | AP105: 57391.33 | AQ105: 55508.77 | AR105: 61712.3 | AS105: 42745.86 | AT105: 49041.83 | AU105: 46697.35 | AV105: 47434.64 | AW105: 41996.52 | AX105: 60998.38 | BF105: 142620 | BG105: De 181 a 360 días | BH105: 217478.75 | BI105: 142620 | BJ105: De 181 a 360 días | BK105: 196199.68
...

Sheet BGhoriz
B1: =Premisas!A1 -> BANCO CAPITAL S.A.
B2: PRESUPUESTOS 2024 | D2: EJECUTADO | E2: EJECUTADO | F2: EJECUTADO | G2: EJECUTADO | H2: EJECUTADO | I2: EJECUTADO | J2: EJECUTADO | K2: EJECUTADO | L2: EJECUTADO | M2: EJECUTADO | N2: EJECUTADO | O2: EJECUTADO | P2: EJECUTADO | Q2: EJECUTADO | R2: EJECUTADO | S2: EJECUTADO | T2: EJECUTADO | U2: EJECUTADO | V2: EJECUTADO | W2: EJECUTADO | X2: EJECUTADO | Y2: EJECUTADO | Z2: EJECUTADO | AA2: EJECUTADO | AB2: EJECUTADO | AC2: EJECUTADO | AD2: EJECUTADO | AE2: EJECUTADO | AF2: EJECUTADO | AG2: EJECUTADO | AH2: EJECUTADO | AI2: EJECUTADO | AJ2: EJECUTADO | AK2: EJECUTADO | AL2: EJECUTADO | AM2: PRESUPUESTO | AN2: PRESUPUESTO | AO2: PRESUPUESTO | AP2: PRESUPUESTO | AQ2: PRESUPUESTO | AR2: PRESUPUESTO | AS2: PRESUPUESTO | AT2: PRESUPUESTO | AU2: PRESUPUESTO | AV2: PRESUPUESTO | AW2: PRESUPUESTO | AX2: PRESUPUESTO | BA2: ANÁLISIS VERTICAL | BB2: ANÁLISIS VERTICAL
D3: =EEFFun!P2 -> 12 | E3: =EEFFun!Q2 -> 1 | F3: =EEFFun!R2 -> 2 | G3: =EEFFun!S2 -> 3 | H3: =EEFFun!T2 -> 4 | I3: 5 | J3: 6 | K3: 7 | L3: 8 | M3: 9 | N3: 10 | O3: 11 | P3: 12 | Q3: 1 | R3: 2 | S3: 3 | T3: 4 | U3: 5 | V3: 6 | W3: 7 | X3: 8 | Y3: 0 | Z3: 10 | AA3: 11 | AB3: 12 | AC3: 1 | AD3: 2 | AE3: 3 | AF3: 4 | AG3: 5 | AH3: 6 | AI3: 7 | AJ3: 8 | AK3: 9 | AL3: 10 | AM3: 1 | AN3: 2 | AO3: 3 | AP3: 4 | AQ3: 5 | AR3: 6 | AS3: 7 | AT3: 8 | AU3: 9 | AV3: 10 | AW3: 11 | AX3: 12 | AY3: 202406-202412 | AZ3: 202312-202412 | BA3: 2023 | BB3: 2024
A4: D | B4: BALANCE GENERAL - PRESUPUESTO MENSUAL | D4: =EEFFun!P3 -> 44926 | E4: =EEFFun!Q3 -> 44957 | F4: =EEFFun!R3 -> 44985 | G4: =EEFFun!S3 -> 45016 | H4: =EEFFun!T3 -> 45046 | I4: =EEFFun!U3 -> 45077 | J4: =EEFFun!V3 -> 45107 | K4: =EEFFun!W3 -> 45138 | ... AB4: =EEFFun!AN3 -> 45657 | AC4: 2025-1 | AD4: 2025-2 | AE4: 2025-3 | AF4: 2025-4 | AG4: 2025-5 | AH4: 2025-6 | AI4: 2025-7 | AJ4: 2025-8 | AK4: 2025-9 | AL4: 2025-10 | AM4: 45688 | AN4: 45716 | AO4: 45747 | AP4: 45777 | AQ4: 45808 | AR4: 45838 | AS4: 45869 | AT4: 45900 | AU4: 45930 | AV4: 45961 | AW4: 45991 | AX4: 46022 | AY4: Comportam | AZ4: Comportam | BA4: % | BB4: %
A5: 1 | B5: =EEFFun!B4 -> 1 | C5: =EEFFun!C4 -> ACTIVOS | D5: =EEFFun!P4 -> 41871995 | E5: =EEFFun!Q4 -> 41428485 | F5: =EEFFun!R4 -> 41342572 | G5: =EEFFun!S4 -> 41608837 | H5: =EEFFun!T4 -> 41402927 | I5: =EEFFun!U4 -> 40814797 | J5: =EEFFun!V4 -> 39918747 | K5: =EEFFun!W4 -> 38859684 | ... AL5: =EEFFun!AX4 -> 72243574 | AM5: =AM6+AM20+AM39+AM102+AM112+AM122+AM134 -> 76988041 | AN5: =AN6+AN20+AN39+AN102+AN112+AN122+AN134 -> 82087921 | AO5: =AO6+AO20+AO39+AO102+AO112+AO122+AO134 -> 87307824 | AP5: =AP6+AP20+AP39+AP102+AP112+AP122+AP134 -> 92258595 | AQ5: =AQ6+AQ20+AQ39+AQ102+AQ112+AQ122+AQ134 -> 97129483 | AR5: =AR6+AR20+AR39+AR102+AR112+AR122+AR134 -> 1.022545e+08 | AS5: =AS6+AS20+AS39+AS102+AS112+AS122+AS134 -> 1.0838113e+08 | AT5: =AT6+AT20+AT39+AT102+AT112+AT122+AT134 -> 1.1345952e+08 | ... AX5: =AX6+AX20+AX39+AX102+AX112+AX122+AX134 -> 1.3374238e+08 | AY5: =AX5-V5 -> 86679839 | AZ5: =AX5-P5 -> 95578761 | BA5: =BA6+BA20+BA39+BA102+BA112+BA122+BA134 -> 1 | BB5: =BB6+BB20+BB39+BB102+BB112+BB122+BB134 -> 1 | BC5: =AT5-W5 -> 66346180
A6: 2 | B6: =EEFFun!B5 -> 11 | C6: =EEFFun!C5 -> FONDOS DISPONIBLES | D6: =EEFFun!P5 -> 1875049.3 | E6: =EEFFun!Q5 -> 2157721.8 | F6: =EEFFun!R5 -> 1067075.5 | G6: =EEFFun!S5 -> 1371077.2 | H6: =EEFFun!T5 -> 1367417.2 | I6: =EEFFun!U5 -> 639585.39 | J6: =EEFFun!V5 -> 1015149.9 | K6: =EEFFun!W5 -> 1439298.4 | ... AL6: =EEFFun!AX5 -> 4340169 | AM6: =AM7+AM12+AM14+AM17 -> 4832852.9 | AN6: =AN7+AN12+AN14+AN17 -> 5768827.1 | AO6: =AO7+AO12+AO14+AO17 -> 5905297.6 | AP6: =AP7+AP12+AP14+AP17 -> 5932709.8 | AQ6: =AQ7+AQ12+AQ14+AQ17 -> 6786992.6 | AR6: =AR7+AR12+AR14+AR17 -> 6451153.8 | AS6: =AS7+AS12+AS14+AS17 -> 6515681.2 | AT6: =AT7+AT12+AT14+AT17 -> 6227035.7 | ... AX6: =AX7+AX12+AX14+AX17 -> 8116267.4 | AY6: =AX6-V6 -> 3861730.8 | AZ6: =AX6-P6 -> 6085400.3 | BA6: =P6/$P$5 -> 0.053214742 | BB6: =AX6/$AX$5 -> 0.060685831 | BC6: =AT6-W6 -> 2127739.7
A7: 4 | B7: =EEFFun!B6 -> 1101 | C7: =EEFFun!C6 -> Caja | D7: =EEFFun!P6 -> 214026.13 | E7: =EEFFun!Q6 -> 277847.72 | F7: =EEFFun!R6 -> 286876.51 | G7: =EEFFun!S6 -> 204150.86 | H7: =EEFFun!T6 -> 160152.06 | I7: =EEFFun!U6 -> 131044.46 | J7: =EEFFun!V6 -> 176055.54 | K7: =EEFFun!W6 -> 198561.99 | ... AL7: =EEFFun!AX6 -> 163888.03 | AM7: =AM8+AM11 -> 245580.43 | AN7: =AN8+AN11 -> 240150.73 | AO7: =AO8+AO11 -> 240117.8 | AP7: =AP8+AP11 -> 239530.73 | AQ7: =AQ8+AQ11 -> 241889.72 | AR7: =AR8+AR11 -> 242864.75 | AS7: =AS8+AS11 -> 239774.44 | AT7: =AT8+AT11 -> 237796.84 | ... AX7: =AX8+AX11 -> 238504.6 | AY7: =AX7-V7 -> -72346.942 | AZ7: =AX7-P7 -> 30339.698 | BA7: =P7/$P$5 -> 0.0054545379 | BB7: =AX7/$AX$5 -> 0.0017833136 | BC7: =AT7-W7 -> -45484.825
A8: 6 | B8: =EEFFun!B7 -> 110105 | C8: =EEFFun!C7 -> Efectivo | D8: =EEFFun!P7 -> 213326.13 | E8: =EEFFun!Q7 -> 277147.72 | F8: =EEFFun!R7 -> 286476.51 | G8: =EEFFun!S7 -> 203550.86 | H8: =EEFFun!T7 -> 159552.06 | I8: =EEFFun!U7 -> 130444.46 | J8: =EEFFun!V7 -> 175455.54 | K8: =EEFFun!W7 -> 197961.99 | ... AL8: =EEFFun!AX7 -> 163238.03 | AM8: =SUM(AM9:AM10) -> 244980.43 | AN8: =SUM(AN9:AN10) -> 239550.73 | AO8: =SUM(AO9:AO10) -> 239517.8 | AP8: =SUM(AP9:AP10) -> 238930.73 | AQ8: =SUM(AQ9:AQ10) -> 241289.72 | AR8: =SUM(AR9:AR10) -> 242264.75 | AS8: =SUM(AS9:AS10) -> 239174.44 | AT8: =SUM(AT9:AT10) -> 237196.84 | ... AX8: =SUM(AX9:AX10) -> 237854.6 | AY8: =AX8-V8 -> -72396.942 | AZ8: =AX8-P8 -> 30289.698 | BA8: =P8/$P$5 -> 0.0054388161 | BB8: =AX8/$AX$5 -> 0.0017784535 | BC8: =AT8-W8 -> -45484.825
A9: 8 | B9: =EEFFun!B8 -> 11010505 | C9: =EEFFun!C8 -> EFECTIVO CAJEROS | D9: =EEFFun!P8 -> 213326.13 | E9: =EEFFun!Q8 -> 277147.72 | F9: =EEFFun!R8 -> 286476.51 | G9: =EEFFun!S8 -> 203550.86 | H9: =EEFFun!T8 -> 159552.06 | I9: =EEFFun!U8 -> 130444.46 | J9: =EEFFun!V8 -> 175455.54 | K9: =EEFFun!W8 -> 197961.99 | ... AL9: =EEFFun!AX8 -> 163238.03 | AM9: =AVERAGE(Q9:AB9) -> 244980.43 | AN9: =AVERAGE(R9:AM9) -> 239550.73 | AO9: =AVERAGE(S9:AN9) -> 239517.8 | AP9: =AVERAGE(T9:AO9) -> 238930.73 | AQ9: =AVERAGE(U9:AP9) -> 241289.72 | AR9: =AVERAGE(V9:AQ9) -> 242264.75 | AS9: =AVERAGE(W9:AR9) -> 239174.44 | AT9: =AVERAGE(X9:AS9) -> 237196.84 | AU9: =AVERAGE(Y9:AT9) -> 238937.84 | ... AX9: =AVERAGE(AB9:AW9) -> 237854.6 | AY9: =AX9-V9 -> -72396.942 | AZ9: =AX9-P9 -> 30289.698 | BA9: =P9/$P$5 -> 0.0054388161 | BB9: =AX9/$AX$5 -> 0.0017784535 | BC9: =AT9-W9 -> -45484.825
A10: 8 | B10: =EEFFun!B9 -> 11010510 | C10: =EEFFun!C9 -> EFECTIVO SERVIPAGOS | D10: =EEFFun!P9 -> 0 | E10: =EEFFun!Q9 -> 0 | F10: =EEFFun!R9 -> 0 | G10: =EEFFun!S9 -> 0 | H10: =EEFFun!T9 -> 0 | I10: =EEFFun!U9 -> 0 | J10: =EEFFun!V9 -> 0 | K10: =EEFFun!W9 -> 0 | ... AL10: =EEFFun!AX9 -> 0 | AM10: =Q10 -> 0 | AN10: =R10 -> 0 | AO10: =S10 -> 0 | AP10: =T10 -> 0 | AQ10: =U10 -> 0 | AR10: =V10 -> 0 | AS10: =W10 -> 0 | AT10: =X10 -> 0 | ... AX10: =AB10 -> 0 | AY10: =AX10-V10 -> 0 | AZ10: =AX10-P10 -> 0 | BA10: =P10/$P$5 -> 0 | BB10: =AX10/$AX$5 -> 0 | BC10: =AT10-W10 -> 0
A11: 6 | B11: =EEFFun!B10 -> 110110 | C11: =EEFFun!C10 -> Caja chica | D11: =EEFFun!P10 -> 700 | E11: =EEFFun!Q10 -> 700 | F11: =EEFFun!R10 -> 400 | G11: =EEFFun!S10 -> 600 | H11: =EEFFun!T10 -> 600 | I11: =EEFFun!U10 -> 600 | J11: =EEFFun!V10 -> 600 | K11: =EEFFun!W10 -> 600 | ... AL11: =EEFFun!AX10 -> 650 | AM11: =Q11 -> 600 | AN11: =R11 -> 600 | AO11: =S11 -> 600 | AP11: =T11 -> 600 | AQ11: =U11 -> 600 | AR11: =V11 -> 600 | AS11: =W11 -> 600 | AT11: =X11 -> 600 | ... AX11: =AB11 -> 650 | AY11: =AX11-V11 -> 50 | AZ11: =AX11-P11 -> 50 | BA11: =P11/$P$5 -> 1.572178e-05 | BB11: =AX11/$AX$5 -> 4.86009e-06 | BC11: =AT11-W11 -> 0
A12: 4 | B12: =EEFFun!B11 -> 1102 | C12: =EEFFun!C11 -> Depósitos para encaje | D12: =EEFFun!P11 -> 1458459.1 | E12: =EEFFun!Q11 -> 1655874.6 | F12: =EEFFun!R11 -> 696024.36 | G12: =EEFFun!S11 -> 729617.53 | H12: =EEFFun!T11 -> 914088.16 | I12: =EEFFun!U11 -> 395720.74 | J12: =EEFFun!V11 -> 661246.05 | K12: =EEFFun!W11 -> 905886.15 | ... AL12: =EEFFun!AX11 -> 1771523.1 | AM12: =AM13 -> 2311231.9 | AN12: =AN13 -> 3205437.2 | AO12: =AO13 -> 3341132 | AP12: =AP13 -> 3501797.4 | AQ12: =AQ13 -> 4287844.4 | AR12: =AR13 -> 3888320.4 | AS12: =AS13 -> 3929571.3 | AT12: =AT13 -> 3769054.6 | ... AX12: =AX13 -> 5593793.8 | AY12: =AX12-V12 -> 2450042.8 | AZ12: =AX12-P12 -> 4188047 | BA12: =P12/$P$5 -> 0.036834735 | BB12: =AX12/$AX$5 -> 0.041825141 | BC12: =AT12-W12 -> 962550.58
A13: 6 | B13: =EEFFun!B12 -> 110205 | C13: =EEFFun!C12 -> Banco Central del Ecuador | D13: =EEFFun!P12 -> 1458459.1 | E13: =EEFFun!Q12 -> 1655874.6 | F13: =EEFFun!R12 -> 696024.36 | G13: =EEFFun!S12 -> 729617.53 | H13: =EEFFun!T12 -> 914088.16 | I13: =EEFFun!U12 -> 395720.74 | J13: =EEFFun!V12 -> 661246.05 | K13: =EEFFun!W12 -> 905886.15 | ... AL13: =EEFFun!AX12 -> 1771523.1 | AM13: 2311231.9 | AN13: 3205437.2 | AO13: 3341132 | AP13: 3501797.4 | AQ13: 4287844.4 | AR13: 3888320.4 | AS13: 3929571.3 | AT13: 3769054.6 | AU13: 3827145.9 | AV13: 4040969.4 | AW13: 4924504.9 | AX13: 5593793.8 | AY13: =AX13-V13 -> 2450042.8 | AZ13: =AX13-P13 -> 4188047 | BA13: =P13/$P$5 -> 0.036834735 | BB13: =AX13/$AX$5 -> 0.041825141 | BC13: =AT13-W13 -> 962550.58
A14: 4 | B14: =EEFFun!B13 -> 1103 | C14: =EEFFun!C13 -> Bancos y otras instituciones financieras | D14: =EEFFun!P13 -> 158169.61 | E14: =EEFFun!Q13 -> 195182.12 | F14: =EEFFun!R13 -> 71708.75 | G14: =EEFFun!S13 -> 422965.87 | H14: =EEFFun!T13 -> 281591.29 | I14: =EEFFun!U13 -> 98347.3 | J14: =EEFFun!V13 -> 169766.14 | K14: =EEFFun!W13 -> 318895.57 | ... AL14: =EEFFun!AX13 -> 2378842.1 | AM14: =SUM(AM15:AM16) -> 2258922.5 | AN14: =SUM(AN15:AN16) -> 2278578.4 | AO14: =SUM(AO15:AO16) -> 2280062.1 | AP14: =SUM(AP15:AP16) -> 2145955.8 | AQ14: =SUM(AQ15:AQ16) -> 2210156.5 | AR14: =SUM(AR15:AR16) -> 2272108.6 | AS14: =SUM(AS15:AS16) -> 2297209.1 | AT14: =SUM(AT15:AT16) -> 2168933 | ... AX14: =SUM(AX15:AX16) -> 2224130.3 | AY14: =AX14-V14 -> 1444196.2 | AZ14: =AX14-P14 -> 1980081.3 | BA14: =P14/$P$5 -> 0.006394808 | BB14: =AX14/$AX$5 -> 0.016629959 | BC14: =AT14-W14 -> 1161801.8
A15: 6 | B15: =EEFFun!B14 -> 110310 | C15: =EEFFun!C14 -> Bancos e instituciones financieras locales | D15: =EEFFun!P14 -> 149402.61 | E15: =EEFFun!Q14 -> 186391.8 | F15: =EEFFun!R14 -> 62918.43 | G15: =EEFFun!S14 -> 414175.55 | H15: =EEFFun!T14 -> 272800.97 | I15: =EEFFun!U14 -> 89556.98 | J15: =EEFFun!V14 -> 160975.82 | K15: =EEFFun!W14 -> 310105.25 | ... AL15: =EEFFun!AX14 -> 2369967.9 | AM15: =AVERAGE(AC15:AL15) -> 2250048.3 | AN15: =AVERAGE(AD15:AM15) -> 2269704.2 | AO15: =AVERAGE(AE15:AN15) -> 2271187.9 | AP15: =AVERAGE(AF15:AO15) -> 2137081.6 | AQ15: =AVERAGE(AG15:AP15) -> 2201282.2 | AR15: =AVERAGE(AH15:AQ15) -> 2263234.3 | AS15: =AVERAGE(AI15:AR15) -> 2288334.8 | AT15: =AVERAGE(AJ15:AS15) -> 2160058.7 | ... AX15: =AVERAGE(AN15:AW15) -> 2215256 | AY15: =AX15-V15 -> 1444196.2 | AZ15: =AX15-P15 -> 1980081.3 | BA15: =P15/$P$5 -> 0.0061622756 | BB15: =AX15/$AX$5 -> 0.016563605 | BC15: =AT15-W15 -> 1161801.8
A16: 6 | B16: =EEFFun!B15 -> 110315 | C16: =EEFFun!C15 -> Bancos e instituciones financieras del exterior | D16: =EEFFun!P15 -> 8767 | E16: =EEFFun!Q15 -> 8790.32 | F16: =EEFFun!R15 -> 8790.32 | G16: =EEFFun!S15 -> 8790.32 | H16: =EEFFun!T15 -> 8790.32 | I16: =EEFFun!U15 -> 8790.32 | J16: =EEFFun!V15 -> 8790.32 | K16: =EEFFun!W15 -> 8790.32 | ... AL16: =EEFFun!AX15 -> 8874.28 | AM16: =Q16 -> 8874.28 | AN16: =R16 -> 8874.28 | AO16: =S16 -> 8874.28 | AP16: =T16 -> 8874.28 | AQ16: =U16 -> 8874.28 | AR16: =V16 -> 8874.28 | AS16: =W16 -> 8874.28 | AT16: =X16 -> 8874.28 | ... AX16: =AB16 -> 8874.28 | AY16: =AX16-V16 -> 0 | AZ16: =AX16-P16 -> 0 | BA16: =P16/$P$5 -> 0.00023253246 | BB16: =AX16/$AX$5 -> 6.6353538e-05 | BC16: =AT16-W16 -> 0
A17: 4 | B17: =EEFFun!B16 -> 1104 | C17: =EEFFun!C16 -> Efectos de cobro inmediato | D17: =EEFFun!P16 -> 44394.42 | E17: =EEFFun!Q16 -> 28817.37 | F17: =EEFFun!R16 -> 12465.85 | G17: =EEFFun!S16 -> 14342.96 | H17: =EEFFun!T16 -> 11585.67 | I17: =EEFFun!U16 -> 14472.89 | J17: =EEFFun!V16 -> 8082.17 | K17: =EEFFun!W16 -> 15954.67 | ... AL17: =EEFFun!AX16 -> 25915.8 | AM17: =AM18+AM19 -> 17117.974 | AN17: =AN18+AN19 -> 44660.699 | AO17: =AO18+AO19 -> 43985.572 | AP17: =AP18+AP19 -> 45425.825 | AQ17: =AQ18+AQ19 -> 47101.999 | AR17: =AR18+AR19 -> 47860.062 | AS17: =AS18+AS19 -> 49126.429 | AT17: =AT18+AT19 -> 51251.305 | ... AX17: =AX18+AX19 -> 59838.733 | AY17: =AX17-V17 -> 39838.733 | AZ17: =AX17-P17 -> -113067.7 | BA17: =P17/$P$5 -> 0.0045306614 | BB17: =AX17/$AX$5 -> 0.00044741789 | BC17: =AT17-W17 -> 48872.155
A18: 6 | B18: =EEFFun!B17 -> 110405 | C18: =EEFFun!C17 -> EFECTOS INGRESADOS A CAJA | D18: =EEFFun!P17 -> 0 | E18: =EEFFun!Q17 -> 0 | F18: =EEFFun!R17 -> 0 | G18: =EEFFun!S17 -> 0 | H18: =EEFFun!T17 -> 0 | I18: =EEFFun!U17 -> 0 | J18: =EEFFun!V17 -> 0 | K18: =EEFFun!W17 -> 0 | ... AL18: =EEFFun!AX17 -> 0 | AY18: =AX18-V18 -> 0 | AZ18: =AX18-P18 -> 0 | BA18: =P18/$P$5 -> 0 | BB18: =AX18/$AX$5 -> 0 | BC18: =AT18-W18 -> 0
A19: 6 | B19: =EEFFun!B18 -> 110410 | C19: =EEFFun!C18 -> VALORES ENVIADOS A CÁMARA DE COMPENSACIÓN | D19: =EEFFun!P18 -> 44394.42 | E19: =EEFFun!Q18 -> 28817.37 | F19: =EEFFun!R18 -> 12465.85 | G19: =EEFFun!S18 -> 14342.96 | H19: =EEFFun!T18 -> 11585.67 | I19: =EEFFun!U18 -> 14472.89 | J19: =EEFFun!V18 -> 8082.17 | K19: =EEFFun!W18 -> 15954.67 | ... AL19: =EEFFun!AX18 -> 25915.8 | AM19: =AVERAGE(Q19:AB19) -> 17117.974 | AN19: =AVERAGE(R19:AM19) -> 44660.699 | AO19: =AVERAGE(S19:AN19) -> 43985.572 | AP19: =AVERAGE(T19:AO19) -> 45425.825 | AQ19: =AVERAGE(U19:AP19) -> 47101.999 | AR19: =AVERAGE(V19:AQ19) -> 47860.062 | AS19: =AVERAGE(W19:AR19) -> 49126.429 | AT19: =AVERAGE(X19:AS19) -> 51251.305 | AU19: =AVERAGE(Y19:AT19) -> 53563.179 | ... AX19: =AVERAGE(AB19:AW19) -> 59838.733 | AY19: =AX19-V19 -> 39838.733 | AZ19: =AX19-P19 -> -113067.7 | BA19: =P19/$P$5 -> 0.0045306614 | BB19: =AX19/$AX$5 -> 0.00044741789 | BC19: =AT19-W19 -> 48872.155
A20: 2 | B20: =EEFFun!B19 -> 13 | C20: =EEFFun!C19 -> INVERSIONES | D20: =EEFFun!P19 -> 4569816.5 | E20: =EEFFun!Q19 -> 4396213.9 | F20: =EEFFun!R19 -> 4304281.3 | G20: =EEFFun!S19 -> 3882342.1 | H20: =EEFFun!T19 -> 3717634.7 | I20: =EEFFun!U19 -> 3705733.6 | J20: =EEFFun!V19 -> 3355464.7 | K20: =EEFFun!W19 -> 2765240.9 | ... AL20: =EEFFun!AX19 -> 6909362.7 | AM20: =AM21+AM27+AM32+AM35+AM37 -> 6212324.5 | AN20: =AN21+AN27+AN32+AN35+AN37 -> 5602025.5 | AO20: =AO21+AO27+AO32+AO35+AO37 -> 6026932.9 | AP20: =AP21+AP27+AP32+AP35+AP37 -> 6838671.8 | AQ20: =AQ21+AQ27+AQ32+AQ35+AQ37 -> 6223039 | AR20: =AR21+AR27+AR32+AR35+AR37 -> 7237293.6 | AS20: =AS21+AS27+AS32+AS35+AS37 -> 8925517.5 | AT20: =AT21+AT27+AT32+AT35+AT37 -> 9941448.2 | ... AX20: =AX21+AX27+AX32+AX35+AX37 -> 11119798 | AY20: =AX20-V20 -> 4216831.2 | AZ20: =AX20-P20 -> 5646839 | BA20: =P20/$P$5 -> 0.14340777 | BB20: =AX20/$AX$5 -> 0.083143417 | BC20: =AT20-W20 -> 3447191.8
A21: 4 | B21: =EEFFun!B20 -> 1303 | C21: =EEFFun!C20 -> Disponibles para la venta de entidades del sector privado | D21: =EEFFun!P20 -> 873535.46 | E21: =EEFFun!Q20 -> 675506.01 | F21: =EEFFun!R20 -> 571537.73 | G21: =EEFFun!S20 -> 159326.22 | H21: =EEFFun!T20 -> 0 | I21: =EEFFun!U20 -> 0 | J21: =EEFFun!V20 -> 0 | K21: =EEFFun!W20 -> 0 | ... AL21: =EEFFun!AX20 -> 1333972.4 | AM21: =SUM(AM22:AM26) -> 1290464.2 | AN21: =SUM(AN22:AN26) -> 2617206.1 | AO21: =SUM(AO22:AO26) -> 2476803.7 | AP21: =SUM(AP22:AP26) -> 3719868 | AQ21: =SUM(AQ22:AQ26) -> 3641540.7 | AR21: =SUM(AR22:AR26) -> 4160715.2 | AS21: =SUM(AS22:AS26) -> 4024862.3 | AT21: =SUM(AT22:AT26) -> 6133715.4 | ... AX21: =SUM(AX22:AX26) -> 6434978.9 | AY21: =AX21-V21 -> 2933116.8 | AZ21: =AX21-P21 -> 3141490.9 | BA21: =P21/$P$5 -> 0.086299155 | BB21: =AX21/$AX$5 -> 0.048114733 | BC21: =AT21-W21 -> 3203087.7
A22: 6 | B22: =EEFFun!B21 -> 130305 | C22: =EEFFun!C21 -> De 1 a 30 días | D22: =EEFFun!P21 -> 202034.17 | E22: =EEFFun!Q21 -> 107021.85 | F22: =EEFFun!R21 -> 413146.67 | G22: =EEFFun!S21 -> 159326.22 | H22: =EEFFun!T21 -> 0 | I22: =EEFFun!U21 -> 0 | J22: =EEFFun!V21 -> 0 | K22: =EEFFun!W21 -> 0 | ... AL22: =EEFFun!AX21 -> 823359.35 | AM22: =AC22-INV!B16+INV!C16+900000-200000 -> 880958.11 | AN22: =AD22-INV!C16+INV!D16+600000-200000 -> 938713.65 | AO22: =AE22-INV!D16+INV!E16-500000+700000-200000 -> 1184575.4 | AP22: =AF22-INV!E16+INV!F16+700000-290000 -> 1199389 | AQ22: =AG22-INV!F16+INV!G16+600000-490000 -> 946215.76 | AR22: =AH22-INV!G16+INV!H16+400000-760000 -> 407890.25 | AS22: =AI22-INV!H16+INV!I16 -> 393345.64 | AT22: =AJ22-INV!I16+INV!J16 -> 1356503.6 | AU22: =AK22-INV!J16+INV!K16+600000 -> 2021996.4 | AV22: =AL22-INV!K16+INV!L16+1000000 -> 1823359.4 | AW22: =AM22-INV!L16+INV!M16 -> 880958.11 | AX22: =AN22-INV!M16+INV!N16 -> 938713.65 | AY22: =AX22-V22 -> 389605.53 | AZ22: =AX22-P22 -> 845684.48 | BA22: =P22/$P$5 -> 0.0024376402 | BB22: =AX22/$AX$5 -> 0.0070188198 | BC22: =AT22-W22 -> 1356503.6
A23: 6 | B23: =EEFFun!B22 -> 130310 | C23: =EEFFun!C22 -> De 31 a 90 días | D23: =EEFFun!P22 -> 514890.08 | E23: =EEFFun!Q22 -> 568484.16 | F23: =EEFFun!R22 -> 158391.06 | G23: =EEFFun!S22 -> 0 | H23: =EEFFun!T22 -> 0 | I23: =EEFFun!U22 -> 0 | J23: =EEFFun!V22 -> 0 | K23: =EEFFun!W22 -> 0 | ... AL23: =EEFFun!AX22 -> 0 | AM23: =AC23-INV!B17+INV!C17 -> 0 | AN23: =R23-INV!C16+INV!D16+INV!$N$16/12 -> 93446.72 | AO23: =S23-INV!D16+INV!E16+INV!$N$16/12 -> 145324.17 | AP23: =T23-INV!E16+INV!F16+INV!$N$16/12 -> 389401.73 | AQ23: =U23-INV!F16+INV!G16+INV!$N$16/12 -> 545416.85 | AR23: =V23-INV!G16+INV!H16+INV!$N$16/12+800000 -> 844624.19 | AS23: =W23-INV!H16+INV!I16+INV!$N$16/12+800000 -> 937818.79 | AT23: 1865632 | AU23: 2535411 | AV23: =3221436-800000 -> 2421436 | AW23: =3811625-2000000 -> 1811625 | AX23: =4365877-1000000-2000000 -> 1365877 | AY23: =AX23-V23 -> 1321252.8 | AZ23: =AX23-P23 -> 1321401.1 | BA23: =P23/$P$5 -> 0.0011653997 | BB23: =AX23/$AX$5 -> 0.010212746 | BC23: =AT23-W23 -> 1727813.2
A24: 6 | B24: =EEFFun!B23 -> 130315 | C24: =EEFFun!C23 -> De 91 a 180 días | D24: =EEFFun!P23 -> 156611.21 | E24: =EEFFun!Q23 -> 0 | F24: =EEFFun!R23 -> 0 | G24: =EEFFun!S23 -> 0 | H24: =EEFFun!T23 -> 0 | I24: =EEFFun!U23 -> 0 | J24: =EEFFun!V23 -> 0 | K24: =EEFFun!W23 -> 0 | ... AL24: =EEFFun!AX23 -> 0 | AM24: =AC24-INV!B18+INV!C18 -> 0 | AN24: =Q24-INV!G16-INV!E16+400000 -> 537670.47 | AO24: =R24-INV!H16-INV!F16 -> 138587.64 | AP24: =S24-INV!I16-INV!G16 -> 138718.81 | AQ24: =T24-INV!J16-INV!H16 -> 137798.26 | AR24: =U24-INV!K16-INV!I16 -> 138778.69 | AS24: =V24-INV!L16-INV!J16 -> 138707.72 | AT24: =W24-INV!M16-INV!K16 -> 137818.79 | AU24: =AT24 -> 137818.79 | AV24: =AU24-INV!M16+INV!K16+600000 -> 737818.79 | AW24: =AV24 -> 737818.79 | AX24: =AW24 -> 737818.79 | AY24: =AX24-V24 -> 599111.07 | AZ24: =AX24-P24 -> 587859.96 | BA24: =P24/$P$5 -> 0.0039293662 | BB24: =AX24/$AX$5 -> 0.0055167165 | BC24: =AT24-W24 -> 0
A25: 6 | B25: =EEFFun!B24 -> 130320 | C25: =EEFFun!C24 -> De 181 a 360 días | D25: =EEFFun!P24 -> 0 | E25: =EEFFun!Q24 -> 0 | F25: =EEFFun!R24 -> 0 | G25: =EEFFun!S24 -> 0 | H25: =EEFFun!T24 -> 0 | I25: =EEFFun!U24 -> 0 | J25: =EEFFun!V24 -> 0 | K25: =EEFFun!W24 -> 0 | ... AL25: =EEFFun!AX24 -> 0 | AM25: =AC25-INV!B19+INV!C19 -> 275659.74 | AN25: =R25+INV!$N$16/12 -> 277175.29 | AO25: =S25+INV!$N$16/12 -> 277437.62 | AP25: =T25+INV!$N$16/12 -> 275596.52 | AQ25: =U25+INV!$N$16/12 -> 277557.38 | AR25: =V25+INV!$N$16/12 -> 277415.43 | AS25: =W25+INV!$N$16/12 -> 275637.57 | AT25: =X25+INV!$N$16/12 -> 277598.41 | AU25: =Y25+INV!$N$16/12+500000 -> 777461.81 | AV25: =Z25+INV!$N$16/12+600000 -> 875649.22 | AW25: =AA25+INV!$N$16/12 -> 277552.97 | AX25: =AB25+INV!$N$16/12+900000 -> 1177478.7 | AY25: =AX25-V25 -> 900063.25 | AZ25: =AX25-P25 -> 914922.36 | BA25: =P25/$P$5 -> 0.0068797544 | BB25: =AX25/$AX$5 -> 0.0088040806 | BC25: =AT25-W25 -> 1960.84
A26: 6 | B26: =EEFFun!B25 -> 130325 | C26: =EEFFun!C25 -> De más de 360 días | D26: =EEFFun!P25 -> 0 | E26: =EEFFun!Q25 -> 0 | F26: =EEFFun!R25 -> 0 | G26: =EEFFun!S25 -> 0 | H26: =EEFFun!T25 -> 0 | I26: =EEFFun!U25 -> 0 | J26: =EEFFun!V25 -> 0 | K26: =EEFFun!W25 -> 0 | ... AL26: =EEFFun!AX25 -> 0 | AM26: =AC26-INV!B20+INV!C20-1400000-570000 -> 133846.34 | AN26: =R26-INV!$N$16/12-INV!C17-1900000 -> 770199.93 | AO26: =S26-INV!$N$16/12-INV!D17-1900000 -> 730878.84 | AP26: =T26-INV!$N$16/12-INV!E17-1800000+1000000 -> 1716762 | AQ26: =U26-INV!$N$16/12-INV!F17-1800000+1000000 -> 1734552.4 | AR26: =V26-INV!$N$16/12-INV!G17 -> 2492006.6 | AS26: =W26-INV!$N$16/12-INV!H17+1000000-1100000 -> 2279352.6 | AT26: =X26-INV!$N$16/12-INV!I17+1500000-600000 -> 2496162.7 | AU26: =Y26-INV!$N$16/12-INV!J17 -> 1553721.6 | AV26: =Z26-INV!$N$16/12-INV!K17+1000000 -> 3241608.2 | AW26: =AA26-INV!$N$16/12-INV!L17 -> 2256966.2 | AX26: =AB26-INV!$N$16/12-INV!M17 -> 2215090.7 | AY26: =AX26-V26 -> -276915.86 | AZ26: =AX26-P26 -> -528377.06 | BA26: =P26/$P$5 -> 0.071886995 | BB26: =AX26/$AX$5 -> 0.01656237 | BC26: =AT26-W26 -> 116810.05
A27: 4 | B27: =EEFFun!B26 -> 1304 | C27: =EEFFun!C26 -> Disponibles para la venta del estado o de entidades sector público | D27: =EEFFun!P26 -> 1195356.7 | E27: =EEFFun!Q26 -> 1198541.3 | F27: =EEFFun!R26 -> 1201417.8 | G27: =EEFFun!S26 -> 1204602.4 | H27: =EEFFun!T26 -> 1207684.3 | I27: =EEFFun!U26 -> 1210868.9 | J27: =EEFFun!V26 -> 892037.29 | K27: =EEFFun!W26 -> 332131.87 | ... AL27: =EEFFun!AX26 -> 2050883.4 | AM27: =SUM(AM28:AM31) -> 1543183.9 | AN27: =SUM(AN28:AN31) -> 1543770.5 | AO27: =SUM(AO28:AO31) -> 2544918.5 | AP27: =SUM(AP28:AP31) -> 2492200.7 | AQ27: =SUM(AQ28:AQ31) -> 2292858.9 | AR27: =SUM(AR28:AR31) -> 1694604.5 | AS27: =SUM(AS28:AS31) -> 2050971.1 | AT27: =SUM(AT28:AT31) -> 2352904.2 | ... AX27: =SUM(AX28:AX31) -> 3243770.5 | AY27: =AX27-V27 -> 2000647.4 | AZ27: =AX27-P27 -> 3124263.8 | BA27: =P27/$P$5 -> 0.00313143 | BB27: =AX27/$AX$5 -> 0.024253872 | BC27: =AT27-W27 -> 1108950.9
A28: 6 | B28: =EEFFun!B27 -> 130405 | C28: =EEFFun!C27 -> De 1 a 30 días | D28: =EEFFun!P27 -> 0 | E28: =EEFFun!Q27 -> 0 | F28: =EEFFun!R27 -> 0 | G28: =EEFFun!S27 -> 0 | H28: =EEFFun!T27 -> 0 | I28: =EEFFun!U27 -> 0 | J28: =EEFFun!V27 -> 0 | K28: =EEFFun!W27 -> 0 | ... AL28: =EEFFun!AX27 -> 401046.15 | AM28: =AC28-INV!B22+INV!C22 -> 401072.72 | AN28: =AD28-INV!C22+INV!D22 -> 284743.29 | AO28: =AE28-INV!D22+INV!E22 -> 861728.33 | AP28: =AF28-INV!E22+INV!F22 -> 401013.1 | AQ28: =AG28-INV!F22+INV!G22+500000 -> 784688.81 | AR28: =AH28-INV!G22+INV!H22 -> 1011504.5 | AS28: =AI28-INV!H22+INV!I22+1000000 -> 1401015.3 | AT28: =AJ28-INV!I22+INV!J22+1500000 -> 1784715.8 | AU28: =AK28-INV!J22+INV!K22 -> 1171879.3 | AV28: =AL28-INV!K22+INV!L22 -> 401046.15 | AW28: =AM28-INV!L22+INV!M22+2000000-500000 -> 1901072.7 | AX28: =AN28-INV!M22+INV!N22+2500000-1000000 -> 1784743.3 | AY28: =AX28-V28 -> 1504912.8 | AZ28: =AX28-P28 -> 1784743.3 | BA28: =P28/$P$5 -> 0 | BB28: =AX28/$AX$5 -> 0.013344635 | BC28: =AT28-W28 -> 1483881.1
A29: 6 | B29: =EEFFun!B28 -> 130410 | C29: =EEFFun!C28 -> De 31 a 90 días | D29: =EEFFun!P28 -> 0 | E29: =EEFFun!Q28 -> 0 | F29: =EEFFun!R28 -> 0 | G29: =EEFFun!S28 -> 0 | H29: =EEFFun!T28 -> 0 | I29: =EEFFun!U28 -> 0 | J29: =EEFFun!V28 -> 0 | K29: =EEFFun!W28 -> 109225.67 | ... AL29: =EEFFun!AX28 -> 1649837.3 | AM29: =AC29-INV!B23+INV!C23 -> 1142111.2 | AN29: =AD29-INV!C23+INV!D23 -> 1259027.2 | AO29: =AE29-INV!D23+INV!E23+1000000 -> 1683190.2 | AP29: =AF29-INV!E23+INV!F23+1000000 -> 2091187.6 | AQ29: =AG29-INV!F23+INV!G23+100000 -> 1508170.1 | AR29: =AH29-INV!G23+INV!H23 -> 683100 | AS29: =AI29-INV!H23+INV!I23-800000 -> 649955.85 | AT29: =AJ29-INV!I23+INV!J23-1000000 -> 568188.4 | AU29: =AK29-INV!J23+INV!K23 -> 782904.38 | AV29: =AL29-INV!K23+INV!L23-1000000 -> 649837.29 | AW29: =AM29-INV!L23+INV!M23 -> 1142111.2 | AX29: =AN29-INV!M23+INV!N23+2000000-1800000 -> 1459027.2 | AY29: =AX29-V29 -> 495734.6 | AZ29: =AX29-P29 -> 1339520.5 | BA29: =P29/$P$5 -> 0.00313143 | BB29: =AX29/$AX$5 -> 0.010909236 | BC29: =AT29-W29 -> -374930.22
A30: 6 | B30: =EEFFun!B29 -> 130415 | C30: =EEFFun!C29 -> De 91 a 180 días | D30: =EEFFun!P29 -> 0 | E30: =EEFFun!Q29 -> 0 | F30: =EEFFun!R29 -> 0 | G30: =EEFFun!S29 -> 0 | H30: =EEFFun!T29 -> 459793.53 | I30: =EEFFun!U29 -> 1004114.3 | J30: =EEFFun!V29 -> 892037.29 | K30: =EEFFun!W29 -> 222906.2 | ... AL30: =EEFFun!AX29 -> 0 | AM30: =AC30-INV!B24+INV!C24 -> 0 | AN30: =AD30-INV!C24+INV!D24 -> 0 | AO30: =AE30-INV!D24+INV!E24 -> 0 | AP30: =AF30-INV!E24+INV!F24 -> 0 | AQ30: =AG30-INV!F24+INV!G24 -> 0 | AR30: =AH30-INV!G24+INV!H24 -> 0 | AS30: =AI30-INV!H24+INV!I24 -> 0 | AT30: =AJ30-INV!I24+INV!J24 -> 0 | ... AX30: =AN30-INV!M24+INV!N24 -> 0 | AY30: =AX30-V30 -> 0 | AZ30: =AX30-P30 -> 0 | BA30: =P30/$P$5 -> 0 | BB30: =AX30/$AX$5 -> 0 | BC30: =AT30-W30 -> 0
A31: 6 | B31: =EEFFun!B30 -> 130420 | C31: =EEFFun!C30 -> De 181 a 360 días | D31: =EEFFun!P30 -> 1195356.7 | E31: =EEFFun!Q30 -> 1198541.3 | F31: =EEFFun!R30 -> 1201417.8 | G31: =EEFFun!S30 -> 1204602.4 | H31: =EEFFun!T30 -> 747890.73 | I31: =EEFFun!U30 -> 206754.59 | J31: =EEFFun!V30 -> 0 | K31: =EEFFun!W30 -> 0 | ... AL31: =EEFFun!AX30 -> 0 | AM31: =AC31-INV!B25+INV!C25 -> 0 | AN31: =AD31-INV!C25+INV!D25 -> 0 | AO31: =AE31-INV!D25+INV!E25 -> 0 | AP31: =AF31-INV!E25+INV!F25 -> 0 | AQ31: =AG31-INV!F25+INV!G25 -> 0 | AR31: =AH31-INV!G25+INV!H25 -> 0 | AS31: =AI31-INV!H25+INV!I25 -> 0 | AT31: =AJ31-INV!I25+INV!J25 -> 0 | ... AX31: =AN31-INV!M25+INV!N25 -> 0 | AY31: =AX31-V31 -> 0 | AZ31: =AX31-P31 -> 0 | BA31: =P31/$P$5 -> 0 | BB31: =AX31/$AX$5 -> 0 | BC31: =AT31-W31 -> 0
A32: 4 | B32: =EEFFun!B31 -> 1305 | C32: =EEFFun!C31 -> Mantenidas hasta el vencimiento de entidades sector privado | D32: =EEFFun!P31 -> 0 | E32: =EEFFun!Q31 -> 0 | F32: =EEFFun!R31 -> 0 | G32: =EEFFun!S31 -> 0 | H32: =EEFFun!T31 -> 0 | I32: =EEFFun!U31 -> 0 | J32: =EEFFun!V31 -> 0 | K32: =EEFFun!W31 -> 0 | ... AL32: =EEFFun!AX31 -> 0 | AM32: =AM33+AM34 -> 0 | AN32: =AN33+AN34 -> 0 | AO32: =AO33+AO34 -> 0 | AP32: =AP33+AP34 -> 0 | AQ32: =AQ33+AQ34 -> 0 | AR32: =AR33+AR34 -> 0 | AS32: =AS33+AS34 -> 0 | AT32: =AT33+AT34 -> 0 | ... AX32: =AX33+AX34 -> 0 | AY32: =AX32-V32 -> 0 | AZ32: =AX32-P32 -> 0 | BA32: =P32/$P$5 -> 0 | BB32: =AX32/$AX$5 -> 0 | BC32: =AT32-W32 -> 0
A33: 6 | B33: =EEFFun!B32 -> 130505 | C33: =EEFFun!C32 -> De 1 a 30 días | D33: =EEFFun!P32 -> 0 | E33: =EEFFun!Q32 -> 0 | F33: =EEFFun!R32 -> 0 | G33: =EEFFun!S32 -> 0 | H33: =EEFFun!T32 -> 0 | I33: =EEFFun!U32 -> 0 | J33: =EEFFun!V32 -> 0 | K33: =EEFFun!W32 -> 0 | ... AL33: =EEFFun!AX32 -> 0 | AM33: =AC33-INV!B27+INV!C27 -> 0 | AN33: =AD33-INV!C27+INV!D27 -> 0 | AO33: =AE33-INV!D27+INV!E27 -> 0 | AP33: =AF33-INV!E27+INV!F27 -> 0 | AQ33: =AG33-INV!F27+INV!G27 -> 0 | AR33: =AH33-INV!G27+INV!H27 -> 0 | AS33: =AI33-INV!H27+INV!I27 -> 0 | AT33: =AJ33-INV!I27+INV!J27 -> 0 | ... AX33: =AN33-INV!M27+INV!N27 -> 0 | AY33: =AX33-V33 -> 0 | AZ33: 0 | BA33: =P33/$P$5 -> 0 | BB33: =AX33/$AX$5 -> 0 | BC33: =AT33-W33 -> 0
A34: 6 | B34: =EEFFun!B33 -> 130510 | C34: =EEFFun!C33 -> De 31 a 90 días | D34: =EEFFun!P33 -> 0 | E34: =EEFFun!Q33 -> 0 | F34: =EEFFun!R33 -> 0 | G34: =EEFFun!S33 -> 0 | H34: =EEFFun!T33 -> 0 | I34: =EEFFun!U33 -> 0 | J34: =EEFFun!V33 -> 0 | K34: =EEFFun!W33 -> 0 | ... AL34: =EEFFun!AX33 -> 0 | AM34: =AC34-INV!B28+INV!C28 -> 0 | AN34: =AD34-INV!C28+INV!D28 -> 0 | AO34: =AE34-INV!D28+INV!E28 -> 0 | AP34: =AF34-INV!E28+INV!F28 -> 0 | AQ34: =AG34-INV!F28+INV!G28 -> 0 | AR34: =AH34-INV!G28+INV!H28 -> 0 | AS34: =AI34-INV!H28+INV!I28 -> 0 | AT34: =AJ34-INV!I28+INV!J28 -> 0 | ... AX34: =AN34-INV!M28+INV!N28 -> 0 | AY34: =AX34-V34 -> 0 | AZ34: 0 | BA34: =P34/$P$5 -> 0 | BB34: =AX34/$AX$5 -> 0 | BC34: =AT34-W34 -> 0
A35: 4 | B35: =EEFFun!B34 -> 1306 | C35: =EEFFun!C34 -> Mantenidas hasta el vencimiento del estado o de en | D35: =EEFFun!P34 -> 2138249.7 | E35: =EEFFun!Q34 -> 2159492 | F35: =EEFFun!R34 -> 2168711.6 | G35: =EEFFun!S34 -> 2155819.4 | H35: =EEFFun!T34 -> 2147356.4 | I35: =EEFFun!U34 -> 2132310.9 | J35: =EEFFun!V34 -> 2100873.6 | K35: =EEFFun!W34 -> 2070535.1 | ... AL35: =EEFFun!AX34 -> 3086341.5 | AM35: =AM36 -> 3368593.4 | AN35: =AN36 -> 1430921.2 | AO35: =AO36 -> 995033.39 | AP35: =AP36 -> 616377.83 | AQ35: =AQ36 -> 278364.78 | AR35: =AR36 -> 1371651.3 | AS35: =AS36 -> 2839311.9 | AT35: =AT36 -> 1444406.9 | ... AX35: =AX36 -> 1430921.2 | AY35: =AX35-V35 -> -727060.84 | AZ35: =AX35-P35 -> -629043.42 | BA35: =P35/$P$5 -> 0.053977183 | BB35: =AX35/$AX$5 -> 0.010699086 | BC35: =AT35-W35 -> -875268.46
A36: 6 | B36: =EEFFun!B35 -> 130615 | C36: =EEFFun!C35 -> De 91 a 180 días | D36: =EEFFun!P35 -> 2138249.7 | E36: =EEFFun!Q35 -> 2159492 | F36: =EEFFun!R35 -> 2168711.6 | G36: =EEFFun!S35 -> 2155819.4 | H36: =EEFFun!T35 -> 2147356.4 | I36: =EEFFun!U35 -> 2132310.9 | J36: =EEFFun!V35 -> 2100873.6 | K36: =EEFFun!W35 -> 2070535.1 | ... AL36: =EEFFun!AX35 -> 3086341.5 | AM36: =AC36-INV!B30+INV!C30+900000 -> 3368593.4 | AN36: =AD36-INV!C30+INV!D30-1100000 -> 1430921.2 | AO36: =AE36-INV!D30+INV!E30-1600000 -> 995033.39 | AP36: =AF36-INV!E30+INV!F30-2100000 -> 616377.83 | AQ36: =AG36-INV!F30+INV!G30-2500000 -> 278364.78 | AR36: =AH36-INV!G30+INV!H30-1400000 -> 1371651.3 | AS36: =AI36-INV!H30+INV!I30 -> 2839311.9 | AT36: =AJ36-INV!I30+INV!J30-1500000 -> 1444406.9 | AU36: =AK36-INV!J30+INV!K30+360000-2100000 -> 1290921.8 | AV36: =AL36-INV!K30+INV!L30-2000000 -> 1086341.5 | AW36: =AM36-INV!L30+INV!M30+1200000-1500000 -> 3068593.4 | AX36: =AN36-INV!M30+INV!N30 -> 1430921.2 | AY36: =AX36-V36 -> -727060.84 | AZ36: =AX36-P36 -> -629043.42 | BA36: =P36/$P$5 -> 0.053977183 | BB36: =AX36/$AX$5 -> 0.010699086 | BC36: =AT36-W36 -> -875268.46
A37: 4 | B37: =EEFFun!B36 -> 1307 | C37: =EEFFun!C36 -> De disponibilidad restringida | D37: =EEFFun!P36 -> 362674.63 | E37: =EEFFun!Q36 -> 362674.63 | F37: =EEFFun!R36 -> 362614.21 | G37: =EEFFun!S36 -> 362594.07 | H37: =EEFFun!T36 -> 362594.07 | I37: =EEFFun!U36 -> 362553.8 | J37: =EEFFun!V36 -> 362553.8 | K37: =EEFFun!W36 -> 362573.93 | ... AL37: =EEFFun!AX36 -> 438165.38 | AM37: =AM38 -> 10083.06 | AN37: =AN38 -> 10127.78 | AO37: =AO38 -> 10177.29 | AP37: =AP38 -> 10225.21 | AQ37: =AQ38 -> 10274.72 | AR37: =AR38 -> 10322.64 | AS37: =AS38 -> 10372.15 | AT37: =AT38 -> 10421.67 | ... AX37: =AX38 -> 10127.78 | AY37: =AX37-V37 -> 10127.78 | AZ37: =AX37-P37 -> 10127.78 | BA37: =P37/$P$5 -> 0 | BB37: =AX37/$AX$5 -> 7.5726035e-05 | BC37: =AT37-W37 -> 10421.67
A38: 6 | B38: =EEFFun!B37 -> 130710 | C38: =EEFFun!C37 -> Depósitos sujetos a restricción | D38: =EEFFun!P37 -> 362674.63 | E38: =EEFFun!Q37 -> 362674.63 | F38: =EEFFun!R37 -> 362614.21 | G38: =EEFFun!S37 -> 362594.07 | H38: =EEFFun!T37 -> 362594.07 | I38: =EEFFun!U37 -> 362553.8 | J38: =EEFFun!V37 -> 362553.8 | K38: =EEFFun!W37 -> 362573.93 | ... AL38: =EEFFun!AX37 -> 10519.1 | AM38: =AC38-INV!B32+INV!C32 -> 10083.06 | AN38: =AD38-INV!C32+INV!D32 -> 10127.78 | AO38: =AE38-INV!D32+INV!E32 -> 10177.29 | AP38: =AF38-INV!E32+INV!F32 -> 10225.21 | AQ38: =AG38-INV!F32+INV!G32 -> 10274.72 | AR38: =AH38-INV!G32+INV!H32 -> 10322.64 | AS38: =AI38-INV!H32+INV!I32 -> 10372.15 | AT38: =AJ38-INV!I32+INV!J32 -> 10421.67 | ... AX38: =AN38-INV!M32+INV!N32 -> 10127.78 | AY38: =AX38-V38 -> 10127.78 | AZ38: =AX38-P38 -> 10127.78 | BA38: =P38/$P$5 -> 0 | BB38: =AX38/$AX$5 -> 7.5726035e-05 | BC38: =AT38-W38 -> 10421.67
A39: 2 | B39: =EEFFun!B38 -> 14 | C39: =EEFFun!C38 -> CARTERA DE CREDITOS | D39: =EEFFun!P38 -> 23772499 | E39: =EEFFun!Q38 -> 23269792 | F39: =EEFFun!R38 -> 24359372 | G39: =EEFFun!S38 -> 24821532 | H39: =EEFFun!T38 -> 24750622 | I39: =EEFFun!U38 -> 24906664 | J39: =EEFFun!V38 -> 24123481 | K39: =EEFFun!W38 -> 23259505 | ... AL39: =EEFFun!AX38 -> 45825231 | AM39: =SUM(AM54:AM76)+AM78+AM80+AM82+AM85+AM88+AM91 -> 50802087 | AN39: =SUM(AN54:AN76)+AN78+AN80+AN82+AN85+AN88+AN91 -> 55681480 | AO39: =SUM(AO54:AO76)+AO78+AO80+AO82+AO85+AO88+AO91 -> 60406923 | AP39: =SUM(AP54:AP76)+AP78+AP80+AP82+AP85+AP88+AP91 -> 64774643 | AQ39: =SUM(AQ54:AQ76)+AQ78+AQ80+AQ82+AQ85+AQ88+AQ91 -> 69317335 | AR39: =SUM(AR54:AR76)+AR78+AR80+AR82+AR85+AR88+AR91+10000 -> 73811842 | AS39: =SUM(AS54:AS76)+AS78+AS80+AS82+AS85+AS88+AS91 -> 78194902 | AT39: =SUM(AT54:AT76)+AT78+AT80+AT82+AT85+AT88+AT91 -> 82524914 | AU39: =SUM(AU54:AU76)+AU78+AU80+AU82+AU85+AU88+AU91 -> 86762780 | AV39: =SUM(AV54:AV76)+AV78+AV80+AV82+AV85+AV88+AV91 -> 90875197 | AW39: =SUM(AW54:AW76)+AW78+AW80+AW82+AW85+AW88+AW91 -> 94966949 | AX39: =SUM(AX54:AX76)+AX78+AX80+AX82+AX85+AX88+AX91 -> 98467818 | AY39: =AX39-V39 -> 74149117 | AZ39: =AX39-P39 -> 79287454 | BA39: =P39/$P$5 -> 0.50258243 | BB39: =AX39/$AX$5 -> 0.73624994 | BC39: =AT39-W39 -> 57791954 | BD39: =AU39-AT39 -> 4237865.8
C40: =EEFFun!C39 -> CARTERA DE CREDITOS BRUTA | D40: =EEFFun!P39 -> 25387754 | E40: =EEFFun!Q39 -> 24883898 | F40: =EEFFun!R39 -> 25969717 | G40: =EEFFun!S39 -> 26459545 | H40: =EEFFun!T39 -> 26422858 | I40: =EEFFun!U39 -> 26715776 | J40: =EEFFun!V39 -> 26025707 | K40: =EEFFun!W39 -> 25235511 | ... AL40: =EEFFun!AX39 -> 46916087 | AM40: =SUM(AM41:AM50) -> 51974511 | AN40: =SUM(AN41:AN50) -> 56934852 | AO40: =SUM(AO41:AO50) -> 61738504 | AP40: =SUM(AP41:AP50) -> 66178237 | AQ40: =SUM(AQ41:AQ50) -> 70796026 | AR40: =SUM(AR41:AR50) -> 75354644 | AS40: =SUM(AS41:AS50) -> 79820223 | AT40: =SUM(AT41:AT50) -> 84194324 | ... AX40: =SUM(AX41:AX50) -> 1.0064969e+08 | AY40: =AX40-V40 -> 73956470 | AZ40: =AX40-P40 -> 79399678 | BA40: =P40/$P$5 -> 0.55681329 | BB40: =AX40/$AX$5 -> 0.75256391 | BC40: =AT40-W40 -> 57200640
C41: =EEFFun!C40 -> PRODUCTIVO | D41: =EEFFun!P40 -> 1808274.6 | E41: =EEFFun!Q40 -> 1154393.1 | F41: =EEFFun!R40 -> 1510242.8 | G41: =EEFFun!S40 -> 1396704.6 | H41: =EEFFun!T40 -> 1248430.1 | I41: =EEFFun!U40 -> 1350544 | J41: =EEFFun!V40 -> 1252603.6 | K41: =EEFFun!W40 -> 1056963.3 | ... AL41: =EEFFun!AX40 -> 643955.82 | AM41: =AM54+AM61+AM68 -> 643194.08 | AN41: =AN54+AN61+AN68 -> 643154.42 | AO41: =AO54+AO61+AO68 -> 642332.14 | AP41: =AP54+AP61+AP68 -> 641480.9 | AQ41: =AQ54+AQ61+AQ68 -> 641124.91 | AR41: =AR54+AR61+AR68 -> 640669.32 | AS41: =AS54+AS61+AS68 -> 641216.75 | AT41: =AT54+AT61+AT68 -> 641650.54 | ... AX41: =AX54+AX61+AX68 -> 643955.82 | AY41: =AX41-V41 -> -168851.84 | AZ41: =AX41-P41 -> -94227.46 | BA41: =P41/$P$5 -> 0.019342592 | BB41: =AX41/$AX$5 -> 0.0048148973 | BC41: =AT41-W41 -> -142459.23
C42: =EEFFun!C41 -> CONSUMO | D42: =EEFFun!P41 -> 17111511 | E42: =EEFFun!Q41 -> 17008134 | F42: =EEFFun!R41 -> 17312780 | G42: =EEFFun!S41 -> 17437064 | H42: =EEFFun!T41 -> 17221201 | I42: =EEFFun!U41 -> 17219408 | J42: =EEFFun!V41 -> 16723703 | K42: =EEFFun!W41 -> 16286806 | ... AL42: =EEFFun!AX41 -> 29829805 | AM42: =AM55+AM62+AM69 -> 33314860 | AN42: =AN55+AN62+AN69 -> 36722583 | AO42: =AO55+AO62+AO69 -> 40003360 | AP42: =AP55+AP62+AP69 -> 42937957 | AQ42: =AQ55+AQ62+AQ69 -> 46072759 | AR42: =AR55+AR62+AR69 -> 49156966 | AS42: =AS55+AS62+AS69 -> 52170308 | AT42: =AT55+AT62+AT69 -> 55112000 | ... AX42: =AX55+AX62+AX69 -> 66067405 | AY42: =AX42-V42 -> 47524831 | AZ42: =AX42-P42 -> 53002871 | BA42: =P42/$P$5 -> 0.34232955 | BB42: =AX42/$AX$5 -> 0.49399005 | BC42: =AT42-W42 -> 36135206
C43: =EEFFun!C42 -> MICROCREDITO | D43: =EEFFun!P42 -> 6046285.6 | E43: =EEFFun!Q42 -> 6299039.6 | F43: =EEFFun!R42 -> 6730983.6 | G43: =EEFFun!S42 -> 7226511.7 | H43: =EEFFun!T42 -> 7560747.3 | I43: =EEFFun!U42 -> 7747403.8 | J43: =EEFFun!V42 -> 7658867.7 | K43: =EEFFun!W42 -> 7447687.6 | ... AL43: =EEFFun!AX42 -> 15825819 | AM43: =AM56+AM63+AM71 -> 17399300 | AN43: =AN56+AN63+AN71 -> 18948694 | AO43: =AO56+AO63+AO71 -> 20471660 | AP43: =AP56+AP63+AP71 -> 21976222 | AQ43: =AQ56+AQ63+AQ71 -> 23459035 | AR43: =AR56+AR63+AR71 -> 24933319 | AS43: =AS56+AS63+AS71 -> 26385311 | AT43: =AT56+AT63+AT71 -> 27817886 | ... AX43: =AX56+AX63+AX71 -> 33321819 | AY43: =AX43-V43 -> 26972982 | AZ43: =AX43-P43 -> 26757344 | BA43: =P43/$P$5 -> 0.17200872 | BB43: =AX43/$AX$5 -> 0.24914929 | BC43: =AT43-W43 -> 21603904
C44: =EEFFun!C43 -> INMOBILIARIO | D44: =EEFFun!P43 -> 1 | E44: =EEFFun!Q43 -> 1 | F44: =EEFFun!R43 -> 1 | G44: =EEFFun!S43 -> 1 | H44: =EEFFun!T43 -> 1 | I44: =EEFFun!U43 -> 1 | J44: =EEFFun!V43 -> 1 | K44: =EEFFun!W43 -> 1 | ... AL44: =EEFFun!AX43 -> 0 | AM44: =AM70 -> 0 | AN44: =AN70 -> 0 | AO44: =AO70 -> 0 | AP44: =AP70 -> 0 | AQ44: =AQ70 -> 0 | AR44: =AR70 -> 0 | AS44: =AS70 -> 0 | AT44: =AT70 -> 0 | ... AX44: =AX70 -> 0 | AY44: =AX44-V44 -> 0 | AZ44: =AX44-P44 -> -1 | BA44: =P44/$P$5 -> 2.6202966e-08 | BB44: =AX44/$AX$5 -> 0 | BC44: =AT44-W44 -> 0
C45: =EEFFun!C44 -> CONSUMO REFINANCIADO | D45: =EEFFun!P44 -> 12623.84 | E45: =EEFFun!Q44 -> 19365.96 | F45: =EEFFun!R44 -> 19207.27 | G45: =EEFFun!S44 -> 18889.82 | H45: =EEFFun!T44 -> 18721.37 | I45: =EEFFun!U44 -> 44485.61 | J45: =EEFFun!V44 -> 43869.05 | K45: =EEFFun!W44 -> 57534.57 | ... AL45: =EEFFun!AX44 -> 260130 | AM45: =AM57+AM64+AM72 -> 288906.61 | AN45: =AN57+AN64+AN72 -> 289954.69 | AO45: =AO57+AO64+AO72 -> 290165.45 | AP45: =AP57+AP64+AP72 -> 290778.32 | AQ45: =AQ57+AQ64+AQ72 -> 291135.82 | AR45: =AR57+AR64+AR72 -> 291443.35 | AS45: =AS57+AS64+AS72 -> 291498.02 | AT45: =AT57+AT64+AT72 -> 291496.59 | ... AX45: =AX57+AX64+AX72 -> 290024.13 | AY45: =AX45-V45 -> 15461.879 | AZ45: =AX45-P45 -> 91802.249 | BA45: =P45/$P$5 -> 0.0051940013 | BB45: =AX45/$AX$5 -> 0.0021685283 | BC45: =AT45-W45 -> -13604.535
C46: =EEFFun!C45 -> MICROCREDITO REFINANCIADO | D46: =EEFFun!P45 -> 0 | E46: =EEFFun!Q45 -> 0 | F46: =EEFFun!R45 -> 0 | G46: =EEFFun!S45 -> 0 | H46: =EEFFun!T45 -> 0 | I46: =EEFFun!U45 -> 0 | J46: =EEFFun!V45 -> 0 | K46: =EEFFun!W45 -> 30942.94 | ... AL46: =EEFFun!AX45 -> 89773.94 | AM46: =AM58+AM65+AM73 -> 152554.66 | AN46: =AN58+AN65+AN73 -> 153108.09 | AO46: =AO58+AO65+AO73 -> 153219.38 | AP46: =AP58+AP65+AP73 -> 153543 | AQ46: =AQ58+AQ65+AQ73 -> 153731.77 | AR46: =AR58+AR65+AR73 -> 153894.16 | AS46: =AS58+AS65+AS73 -> 153923.03 | AT46: =AT58+AT65+AT73 -> 153922.27 | ... AX46: =AX58+AX65+AX73 -> 153144.75 | AY46: =AX46-V46 -> 13160.304 | BC46: =AT46-W46 -> -7183.7578
C47: =EEFFun!C46 -> CONSUMO REESTRUCTURADO | D47: =EEFFun!P46 -> 10049.69 | E47: =EEFFun!Q46 -> 9166.07 | F47: =EEFFun!R46 -> 8247.42 | G47: =EEFFun!S46 -> 7231.35 | H47: =EEFFun!T46 -> 6856.37 | I47: =EEFFun!U46 -> 6304.02 | J47: =EEFFun!V46 -> 5744.16 | K47: =EEFFun!W46 -> 20189.48 | ... AL47: =EEFFun!AX46 -> 69182.77 | AM47: =AM59+AM66+AM74 -> 49065.575 | AN47: =AN59+AN66+AN74 -> 49571.901 | AO47: =AO59+AO66+AO74 -> 49698.169 | AP47: =AP59+AP66+AP74 -> 49839.154 | AQ47: =AQ59+AQ66+AQ74 -> 49824.954 | AR47: =AR59+AR66+AR74 -> 49853.705 | AS47: =AS59+AS66+AS74 -> 49728.813 | AT47: =AT59+AT66+AT74 -> 49537.194 | ... AX47: =AX59+AX66+AX74 -> 48282.223 | AY47: =AX47-V47 -> -136379.73 | AZ47: =AX47-P47 -> -122387.88 | BA47: =P47/$P$5 -> 0.0044720629 | BB47: =AX47/$AX$5 -> 0.00036100915 | BC47: =AT47-W47 -> -119921.93
C48: =EEFFun!C47 -> MICROCREDITO REESTRUCTURADO | D48: =EEFFun!P47 -> 7478.27 | E48: =EEFFun!Q47 -> 7478.27 | F48: =EEFFun!R47 -> 7436.58 | G48: =EEFFun!S47 -> 7236.58 | H48: =EEFFun!T47 -> 6438.29 | I48: =EEFFun!U47 -> 4438.29 | J48: =EEFFun!V47 -> 3538.29 | K48: =EEFFun!W47 -> 2828.6 | ... AL48: =EEFFun!AX47 -> 24197.46 | AM48: =AM60+AM67+AM75 -> 42974.665 | AN48: =AN60+AN67+AN75 -> 43418.138 | AO48: =AO60+AO67+AO75 -> 43528.731 | AP48: =AP60+AP67+AP75 -> 43652.214 | AQ48: =AQ60+AQ67+AQ75 -> 43639.777 | AR48: =AR60+AR67+AR75 -> 43664.959 | AS48: =AS60+AS67+AS75 -> 43555.571 | AT48: =AT60+AT67+AT75 -> 43387.738 | ... AX48: =AX60+AX67+AX75 -> 42288.558 | AY48: =AX48-V48 -> -107184.46 | AZ48: =AX48-P48 -> -67262.862 | BA48: =P48/$P$5 -> 0.0028705722 | BB48: =AX48/$AX$5 -> 0.00031619415 | BC48: =AT48-W48 -> -105035.04
C49: =EEFFun!C48 -> REFINANCIADO COVID 19 | D49: =EEFFun!P48 -> 40716.68 | E49: =EEFFun!Q48 -> 39926.21 | F49: =EEFFun!R48 -> 39124.81 | G49: =EEFFun!S48 -> 38268.98 | H49: =EEFFun!T48 -> 37725.43 | I49: =EEFFun!U48 -> 36595.24 | J49: =EEFFun!V48 -> 35896.22 | K49: =EEFFun!W48 -> 34734.54 | ... AL49: =EEFFun!AX48 -> 115962.57 | AM49: =AM76+AM78+AM80 -> 22610.169 | AN49: =AN76+AN78+AN80 -> 22692.193 | AO49: =AO76+AO78+AO80 -> 22708.687 | AP49: =AP76+AP78+AP80 -> 22756.651 | AQ49: =AQ76+AQ78+AQ80 -> 22784.629 | AR49: =AR76+AR78+AR80 -> 22808.697 | AS49: =AS76+AS78+AS80 -> 22812.975 | AT49: =AT76+AT78+AT80 -> 22812.863 | ... AX49: =AX76+AX78+AX80 -> 22697.627 | AY49: =AX49-V49 -> -2024.7229 | AZ49: =AX49-P49 -> -7146.8029 | BA49: =P49/$P$5 -> 0.0007820126 | BB49: =AX49/$AX$5 -> 0.00016971156 | BC49: =AT49-W49 -> -1064.7068
C50: =EEFFun!C49 -> REESTRUCTURADO COVID 19 | D50: =EEFFun!P49 -> 350812.91 | E50: =EEFFun!Q49 -> 346393.86 | F50: =EEFFun!R49 -> 341693.07 | G50: =EEFFun!S49 -> 327637.04 | H50: =EEFFun!T49 -> 322737.73 | I50: =EEFFun!U49 -> 306596.56 | J50: =EEFFun!V49 -> 301484.79 | K50: =EEFFun!W49 -> 297822.98 | ... AL50: =EEFFun!AX49 -> 57260.86 | AM50: =AM82+AM85+AM88 -> 61044.916 | AN50: =AN82+AN85+AN88 -> 61674.862 | AO50: =AO82+AO85+AO88 -> 61831.958 | AP50: =AP82+AP85+AP88 -> 62007.365 | AQ50: =AQ82+AQ85+AQ88 -> 61989.697 | AR50: =AR82+AR85+AR88 -> 62025.469 | AS50: =AS82+AS85+AS88 -> 61870.084 | AT50: =AT82+AT85+AT88 -> 61631.681 | ... AX50: =AX82+AX85+AX88 -> 60070.309 | AY50: =AX50-V50 -> -155524.03 | AZ50: =AX50-P50 -> -196495.44 | BA50: =P50/$P$5 -> 0.0067227837 | BB50: =AX50/$AX$5 -> 0.0004491494 | BC50: =AT50-W50 -> -149200.82
C51: =EEFFun!C50 -> PROVISIONES PARA CREDITOS INCOBRABLES | D51: =EEFFun!P50 -> -1615254.5 | E51: =EEFFun!Q50 -> -1614105.4 | F51: =EEFFun!R50 -> -1610345.1 | G51: =EEFFun!S50 -> -1638012.4 | H51: =EEFFun!T50 -> -1672236.3 | I51: =EEFFun!U50 -> -1809112.8 | J51: =EEFFun!V50 -> -1902226.8 | K51: =EEFFun!W50 -> -1976006.1 | ... AL51: =EEFFun!AX50 -> -1090856.6 | AM51: =AM91 -> -1172423.5 | AN51: =AN91 -> -1253371.7 | AO51: =AO91 -> -1331581 | AP51: =AP91 -> -1403594.3 | AQ51: =AQ91 -> -1478691 | AR51: =AR91 -> -1552802.5 | AS51: =AS91 -> -1625320.9 | AT51: =AT91 -> -1669410.1 | ... AX51: =AX91 -> -2181868.9 | AY51: =AX51-V51 -> 192647.37 | AZ51: =AX51-P51 -> -112223.29 | BA51: =P51/$P$5 -> -0.054230854 | BB51: =AX51/$AX$5 -> -0.016313968 | BC51: =AT51-W51 -> 591314.01
C52: =EEFFun!C51 -> TOTAL CARTERA DE CREDITO POR VENCER | D52: =EEFFun!P51 -> 24150369 | E52: =EEFFun!Q51 -> 22833546 | F52: =EEFFun!R51 -> 23612210 | G52: =EEFFun!S51 -> 24251602 | H52: =EEFFun!T51 -> 24141086 | I52: =EEFFun!U51 -> 24208873 | J52: =EEFFun!V51 -> 23407312 | K52: =EEFFun!W51 -> 22413044 | ... AL52: =EEFFun!AX51 -> 46080175 | AM52: =AM54+AM55+AM56+AM57+AM58+AM59+AM60+AM76+AM82 -> 50627998 | AN52: =AN54+AN55+AN56+AN57+AN58+AN59+AN60+AN76+AN82 -> 55487465 | AO52: =AO54+AO55+AO56+AO57+AO58+AO59+AO60+AO76+AO82 -> 60194668 | AP52: =AP54+AP55+AP56+AP57+AP58+AP59+AP60+AP76+AP82 -> 64544892 | AQ52: =AQ54+AQ55+AQ56+AQ57+AQ58+AQ59+AQ60+AQ76+AQ82 -> 69070072 | AR52: =AR54+AR55+AR56+AR57+AR58+AR59+AR60+AR76+AR82 -> 73537230 | AS52: =AS54+AS55+AS56+AS57+AS58+AS59+AS60+AS76+AS82 -> 77913666 | AT52: =AT54+AT55+AT56+AT57+AT58+AT59+AT60+AT76+AT82 -> 82200609 | ... AX52: =AX54+AX55+AX56+AX57+AX58+AX59+AX60+AX76+AX82 -> 98330123 | AY52: =AX52-V52 -> 75046231 | AZ52: =AX52-P52 -> 80109095 | BA52: =P52/$P$5 -> 0.47744498 | BB52: =AX52/$AX$5 -> 0.73522039 | BC52: =AT52-W52 -> 58648373
C53: =EEFFun!C52 -> TOTAL CARTERA DE CREDITO EN RIESGO | D53: =EEFFun!P52 -> 1237384.5 | E53: =EEFFun!Q52 -> 2050351.3 | F53: =EEFFun!R52 -> 2357507.2 | G53: =EEFFun!S52 -> 2207942.7 | H53: =EEFFun!T52 -> 2281772.9 | I53: =EEFFun!U52 -> 2506903.9 | J53: =EEFFun!V52 -> 2618395.4 | K53: =EEFFun!W52 -> 2822467.2 | ... AL53: =EEFFun!AX52 -> 835912.4 | AM53: =AM61+AM62+AM63+AM64+AM65+AM66+AM67+AM68+AM69+AM70+AM71+AM72+AM73+AM74+AM75+AM78+AM80+AM85+AM88 -> 1346513.1 | AN53: =AN61+AN62+AN63+AN64+AN65+AN66+AN67+AN68+AN69+AN70+AN71+AN72+AN73+AN74+AN75+AN78+AN80+AN85+AN88 -> 1447387.1 | AO53: =AO61+AO62+AO63+AO64+AO65+AO66+AO67+AO68+AO69+AO70+AO71+AO72+AO73+AO74+AO75+AO78+AO80+AO85+AO88 -> 1543836.6 | AP53: =AP61+AP62+AP63+AP64+AP65+AP66+AP67+AP68+AP69+AP70+AP71+AP72+AP73+AP74+AP75+AP78+AP80+AP85+AP88 -> 1633344.8 | AQ53: =AQ61+AQ62+AQ63+AQ64+AQ65+AQ66+AQ67+AQ68+AQ69+AQ70+AQ71+AQ72+AQ73+AQ74+AQ75+AQ78+AQ80+AQ85+AQ88 -> 1725954.2 | AR53: =AR61+AR62+AR63+AR64+AR65+AR66+AR67+AR68+AR69+AR70+AR71+AR72+AR73+AR74+AR75+AR78+AR80+AR85+AR88 -> 1817413.8 | AS53: =AS61+AS62+AS63+AS64+AS65+AS66+AS67+AS68+AS69+AS70+AS71+AS72+AS73+AS74+AS75+AS78+AS80+AS85+AS88 -> 1906557.3 | AT53: =AT61+AT62+AT63+AT64+AT65+AT66+AT67+AT68+AT69+AT70+AT71+AT72+AT73+AT74+AT75+AT78+AT80+AT85+AT88 -> 1993715.2 | ... AX53: =AX61+AX62+AX63+AX64+AX65+AX66+AX67+AX68+AX69+AX70+AX71+AX72+AX73+AX74+AX75+AX78+AX80+AX85+AX88 -> 2319563.9 | AY53: =AX53-V53 -> -1089760.8 | AZ53: =AX53-P53 -> -709417.87 | BA53: =P53/$P$5 -> 0.079368308 | BB53: =AX53/$AX$5 -> 0.017343522 | BC53: =AT53-W53 -> -1447733.3
A54: 4 | B54: =EEFFun!B53 -> 1401 | C54: =EEFFun!C53 -> CARTERA DE CRÉDITOS PRODUCTIVO POR VENCER | D54: =EEFFun!P53 -> 1734072.3 | E54: =EEFFun!Q53 -> 1080190.8 | F54: =EEFFun!R53 -> 1436040.4 | G54: =EEFFun!S53 -> 1322502.2 | H54: =EEFFun!T53 -> 1174227.7 | I54: =EEFFun!U53 -> 1276341.7 | J54: =EEFFun!V53 -> 1178401.2 | K54: =EEFFun!W53 -> 982762.02 | ... AL54: =EEFFun!AX53 -> 643884.82 | AM54: =CalcIntCart!E6-CalcIntCart!E7 -> 630330.2 | AN54: =CalcIntCart!F6-CalcIntCart!F7 -> 630291.33 | AO54: =CalcIntCart!G6-CalcIntCart!G7 -> 629485.5 | AP54: =CalcIntCart!H6-CalcIntCart!H7 -> 628651.28 | AQ54: =CalcIntCart!I6-CalcIntCart!I7 -> 628302.41 | AR54: =CalcIntCart!J6-CalcIntCart!J7 -> 627855.93 | AS54: =CalcIntCart!K6-CalcIntCart!K7 -> 628392.42 | AT54: =CalcIntCart!L6-CalcIntCart!L7 -> 628817.53 | ... AX54: =CalcIntCart!P6-CalcIntCart!P7 -> 631076.7 | AY54: =AX54-V54 -> -95886.866 | AZ54: =AX54-P54 -> -8194.9064 | BA54: =P54/$P$5 -> 0.016750813 | BB54: =AX54/$AX$5 -> 0.0047185994 | BC54: =AT54-W54 -> -48667.714
A55: 4 | B55: =EEFFun!B59 -> 1402 | C55: =EEFFun!C59 -> CARTERA DE CRÉDITOS CONSUMO POR VENCER | D55: =EEFFun!P59 -> 16240949 | E55: =EEFFun!Q59 -> 15544857 | F55: =EEFFun!R59 -> 15671930 | G55: =EEFFun!S59 -> 15875618 | H55: =EEFFun!T59 -> 15704959 | I55: =EEFFun!U59 -> 15600109 | J55: =EEFFun!V59 -> 15083713 | K55: =EEFFun!W59 -> 14607269 | ... AL55: =EEFFun!AX59 -> 29255983 | AM55: =CalcIntCart!E12-CalcIntCart!E13 -> 32648563 | AN55: =CalcIntCart!F12-CalcIntCart!F13 -> 35988132 | AO55: =CalcIntCart!G12-CalcIntCart!G13 -> 39203293 | AP55: =CalcIntCart!H12-CalcIntCart!H13 -> 42079198 | AQ55: =CalcIntCart!I12-CalcIntCart!I13 -> 45151304 | AR55: =CalcIntCart!J12-CalcIntCart!J13 -> 48173827 | AS55: =CalcIntCart!K12-CalcIntCart!K13 -> 51126901 | AT55: =CalcIntCart!L12-CalcIntCart!L13 -> 54009760 | ... AX55: =CalcIntCart!P12-CalcIntCart!P13 -> 64746057 | AY55: =AX55-V55 -> 48090174 | AZ55: =AX55-P55 -> 53389302 | BA55: =P55/$P$5 -> 0.29758065 | BB55: =AX55/$AX$5 -> 0.48411025 | BC55: =AT55-W55 -> 36808920
A56: 4 | B56: =EEFFun!B65 -> 1404 | C56: =EEFFun!C65 -> CARTERA DE MICROCRÉDITO POR VENCER | D56: =EEFFun!P65 -> 5885580.8 | E56: =EEFFun!Q65 -> 5973834 | F56: =EEFFun!R65 -> 6248944.4 | G56: =EEFFun!S65 -> 6834974.1 | H56: =EEFFun!T65 -> 7019536.5 | I56: =EEFFun!U65 -> 7111801.1 | J56: =EEFFun!V65 -> 6876552 | K56: =EEFFun!W65 -> 6528684.9 | ... AL56: =EEFFun!AX65 -> 15623788 | AM56: =CalcIntCart!E18-CalcIntCart!E19 -> 17051314 | AN56: =CalcIntCart!F18-CalcIntCart!F19 -> 18569720 | AO56: =CalcIntCart!G18-CalcIntCart!G19 -> 20062227 | AP56: =CalcIntCart!H18-CalcIntCart!H19 -> 21536698 | AQ56: =CalcIntCart!I18-CalcIntCart!I19 -> 22989854 | AR56: =CalcIntCart!J18-CalcIntCart!J19 -> 24434652 | AS56: =CalcIntCart!K18-CalcIntCart!K19 -> 25857604 | AT56: =CalcIntCart!L18-CalcIntCart!L19 -> 27261528 | ... AX56: =CalcIntCart!P18-CalcIntCart!P19 -> 32655383 | AY56: =AX56-V56 -> 27308197 | AZ56: =AX56-P56 -> 27003167 | BA56: =P56/$P$5 -> 0.14810482 | BB56: =AX56/$AX$5 -> 0.24416631 | BC56: =AT56-W56 -> 22063516
A57: 4 | B57: =EEFFun!B71 -> 1410 | C57: =EEFFun!C71 -> CARTERA DE CRÉDITOS CONSUMO REFINANCIADA POR VENCER | D57: =EEFFun!P71 -> 12623.84 | E57: =EEFFun!Q71 -> 19365.96 | F57: =EEFFun!R71 -> 19207.27 | G57: =EEFFun!S71 -> 18889.82 | H57: =EEFFun!T71 -> 12125.08 | I57: =EEFFun!U71 -> 25764.24 | J57: =EEFFun!V71 -> 37272.76 | K57: =EEFFun!W71 -> 50938.28 | ... AL57: =EEFFun!AX71 -> 260130 | AM57: =($W$57/($W$45+$W$46+$W$49)*CalcIntCart!E24) -> 130436.76 | AN57: =($W$57/($W$45+$W$46+$W$49)*CalcIntCart!F24) -> 130909.96 | AO57: =($W$57/($W$45+$W$46+$W$49)*CalcIntCart!G24) -> 131005.11 | AP57: =($W$57/($W$45+$W$46+$W$49)*CalcIntCart!H24) -> 131281.81 | AQ57: =($W$57/($W$45+$W$46+$W$49)*CalcIntCart!I24) -> 131443.22 | AR57: =($W$57/($W$45+$W$46+$W$49)*CalcIntCart!J24) -> 131582.06 | AS57: =($W$57/($W$45+$W$46+$W$49)*CalcIntCart!K24) -> 131606.74 | AT57: =($W$57/($W$45+$W$46+$W$49)*CalcIntCart!L24) -> 131606.1 | ... AX57: =($W$57/($W$45+$W$46+$W$49)*CalcIntCart!P24) -> 130941.31 | AY57: =AX57-V57 -> 1937.297 | AZ57: =AX57-P57 -> 3697.987 | BA57: =P57/$P$5 -> 0.0033341524 | BB57: =AX57/$AX$5 -> 0.00097905621 | BC57: =AT57-W57 -> -6142.2322
A58: 4 | B58: =EEFFun!B77 -> 1412 | C58: =EEFFun!C77 -> CARTERA DE MICROCRÉDITO REFINANCIADA POR VENCER | D58: =EEFFun!P77 -> 0 | E58: =EEFFun!Q77 -> 0 | F58: =EEFFun!R77 -> 0 | G58: =EEFFun!S77 -> 0 | H58: =EEFFun!T77 -> 0 | I58: =EEFFun!U77 -> 0 | J58: =EEFFun!V77 -> 0 | K58: =EEFFun!W77 -> 30942.94 | ... AL58: =EEFFun!AX77 -> 77541.86 | AM58: =($W$58/($W$45+$W$46+$W$49)*CalcIntCart!E24) -> 87613.69 | AN58: =($W$58/($W$45+$W$46+$W$49)*CalcIntCart!F24) -> 87931.53 | AO58: =($W$58/($W$45+$W$46+$W$49)*CalcIntCart!G24) -> 87995.446 | AP58: =($W$58/($W$45+$W$46+$W$49)*CalcIntCart!H24) -> 88181.304 | AQ58: =($W$58/($W$45+$W$46+$W$49)*CalcIntCart!I24) -> 88289.719 | AR58: =($W$58/($W$45+$W$46+$W$49)*CalcIntCart!J24) -> 88382.98 | AS58: =($W$58/($W$45+$W$46+$W$49)*CalcIntCart!K24) -> 88399.559 | AT58: =($W$58/($W$45+$W$46+$W$49)*CalcIntCart!L24) -> 88399.125 | ... AX58: =($W$58/($W$45+$W$46+$W$49)*CalcIntCart!P24) -> 87952.588 | AY58: =AX58-V58 -> 8883.3184 | BC58: =AT58-W58 -> -4125.7051
A59: 4 | B59: =EEFFun!B83 -> 1418 | C59: =EEFFun!C83 -> CARTERA DE CRÉDITOS CONSUMO REESTRUCTURADA POR VENCER | D59: =EEFFun!P83 -> 10049.69 | E59: =EEFFun!Q83 -> 9166.07 | F59: =EEFFun!R83 -> 8247.42 | G59: =EEFFun!S83 -> 7231.35 | H59: =EEFFun!T83 -> 6856.37 | I59: =EEFFun!U83 -> 6304.02 | J59: =EEFFun!V83 -> 5744.16 | K59: =EEFFun!W83 -> 20189.48 | ... AL59: =EEFFun!AX83 -> 56238.4 | AM59: =($W$59/($W$47+$W$48+$W$50)*CalcIntCart!E30) -> 25280.765 | AN59: =($W$59/($W$47+$W$48+$W$50)*CalcIntCart!F30) -> 25541.647 | AO59: =($W$59/($W$47+$W$48+$W$50)*CalcIntCart!G30) -> 25606.705 | AP59: =($W$59/($W$47+$W$48+$W$50)*CalcIntCart!H30) -> 25679.347 | AQ59: =($W$59/($W$47+$W$48+$W$50)*CalcIntCart!I30) -> 25672.031 | AR59: =($W$59/($W$47+$W$48+$W$50)*CalcIntCart!J30) -> 25686.845 | AS59: =($W$59/($W$47+$W$48+$W$50)*CalcIntCart!K30) -> 25622.495 | AT59: =($W$59/($W$47+$W$48+$W$50)*CalcIntCart!L30) -> 25523.764 | ... AX59: =($W$59/($W$47+$W$48+$W$50)*CalcIntCart!P30) -> 24877.147 | AY59: =AX59-V59 -> -70634.523 | AZ59: =AX59-P59 -> -107933.71 | BA59: =P59/$P$5 -> 0.0034800385 | BB59: =AX59/$AX$5 -> 0.00018600796 | BC59: =AT59-W59 -> -61789.106
A60: 4 | B60: =EEFFun!B89 -> 1420 | C60: =EEFFun!C89 -> CARTERA DE MICROCRÉDITO REESTRUCTURADA POR VENCER | D60: =EEFFun!P89 -> 0 | E60: =EEFFun!Q89 -> 0 | F60: =EEFFun!R89 -> 0 | G60: =EEFFun!S89 -> 0 | H60: =EEFFun!T89 -> 0 | I60: =EEFFun!U89 -> 0 | J60: =EEFFun!V89 -> 0 | K60: =EEFFun!W89 -> 0 | ... AL60: =EEFFun!AX89 -> 22485.73 | AM60: =($W$60/($W$47+$W$48+$W$50)*CalcIntCart!E30) -> 16378.95 | AN60: =($W$60/($W$47+$W$48+$W$50)*CalcIntCart!F30) -> 16547.971 | AO60: =($W$60/($W$47+$W$48+$W$50)*CalcIntCart!G30) -> 16590.121 | AP60: =($W$60/($W$47+$W$48+$W$50)*CalcIntCart!H30) -> 16637.185 | AQ60: =($W$60/($W$47+$W$48+$W$50)*CalcIntCart!I30) -> 16632.445 | AR60: =($W$60/($W$47+$W$48+$W$50)*CalcIntCart!J30) -> 16642.042 | AS60: =($W$60/($W$47+$W$48+$W$50)*CalcIntCart!K30) -> 16600.351 | AT60: =($W$60/($W$47+$W$48+$W$50)*CalcIntCart!L30) -> 16536.385 | ... AX60: =($W$60/($W$47+$W$48+$W$50)*CalcIntCart!P30) -> 16117.454 | AY60: =AX60-V60 -> -97596.686 | BC60: =AT60-W60 -> -40032.045
A61: 4 | B61: =EEFFun!B95 -> 1425 | C61: =EEFFun!C95 -> CARTERA DE CRÉDITOS PRODUCTIVO QUE NO DEVENGA INTERESES | D61: =EEFFun!P95 -> 61207.52 | E61: =EEFFun!Q95 -> 56762.77 | F61: =EEFFun!R95 -> 56762.77 | G61: =EEFFun!S95 -> 52229.42 | H61: =EEFFun!T95 -> 49934.69 | I61: =EEFFun!U95 -> 47634.83 | J61: =EEFFun!V95 -> 45302.73 | K61: =EEFFun!W95 -> 42963.94 | ... AL61: =EEFFun!AX95 -> 0 | AM61: =($W$61/($W$61+$W$68))*CalcIntCart!E7 -> 5386.556 | AN61: =($W$61/($W$61+$W$68))*CalcIntCart!F7 -> 5386.2238 | AO61: =($W$61/($W$61+$W$68))*CalcIntCart!G7 -> 5379.3375 | AP61: =($W$61/($W$61+$W$68))*CalcIntCart!H7 -> 5372.2086 | AQ61: =($W$61/($W$61+$W$68))*CalcIntCart!I7 -> 5369.2273 | AR61: =($W$61/($W$61+$W$68))*CalcIntCart!J7 -> 5365.4119 | AS61: =($W$61/($W$61+$W$68))*CalcIntCart!K7 -> 5369.9964 | AT61: =($W$61/($W$61+$W$68))*CalcIntCart!L7 -> 5373.6292 | ... AX61: =($W$61/($W$61+$W$68))*CalcIntCart!P7 -> 5392.9353 | AY61: =AX61-V61 -> -21303.055 | AZ61: =AX61-P61 -> -49792.695 | BA61: =P61/$P$5 -> 0.0014460272 | BB61: =AX61/$AX$5 -> 4.0323309e-05 | BC61: =AT61-W61 -> -39273.781
A62: 4 | B62: =EEFFun!B101 -> 1426 | C62: =EEFFun!C101 -> CARTERA DE CRÉDITOS CONSUMO QUE NO DEVENGA INTERESES | D62: =EEFFun!P101 -> 720126.37 | E62: =EEFFun!Q101 -> 1263864 | F62: =EEFFun!R101 -> 1417129.9 | G62: =EEFFun!S101 -> 1317581.8 | H62: =EEFFun!T101 -> 1257748 | I62: =EEFFun!U101 -> 1334641.1 | J62: =EEFFun!V101 -> 1325151.6 | K62: =EEFFun!W101 -> 1337626.4 | ... AL62: =EEFFun!AX101 -> 525323.29 | AM62: =($W$62/($W$62+$W$69))*CalcIntCart!E13 -> 414865.4 | AN62: =($W$62/($W$62+$W$69))*CalcIntCart!F13 -> 457301.31 | AO62: =($W$62/($W$62+$W$69))*CalcIntCart!G13 -> 498156.37 | AP62: =($W$62/($W$62+$W$69))*CalcIntCart!H13 -> 534700.51 | AQ62: =($W$62/($W$62+$W$69))*CalcIntCart!I13 -> 573737.77 | AR62: =($W$62/($W$62+$W$69))*CalcIntCart!J13 -> 612144.98 | AS62: =($W$62/($W$62+$W$69))*CalcIntCart!K13 -> 649669.71 | AT62: =($W$62/($W$62+$W$69))*CalcIntCart!L13 -> 686302.2 | ... AX62: =($W$62/($W$62+$W$69))*CalcIntCart!P13 -> 822728.36 | AY62: =AX62-V62 -> -421682.45 | AZ62: =AX62-P62 -> -435128.07 | BA62: =P62/$P$5 -> 0.03295957 | BB62: =AX62/$AX$5 -> 0.0061515906 | BC62: =AT62-W62 -> -419482.88
A63: 4 | B63: =EEFFun!B107 -> 1428 | C63: =EEFFun!C107 -> CARTERA DE MICROCRÉDITO QUE NO DEVENGA INTERESES | D63: =EEFFun!P107 -> 129973.64 | E63: =EEFFun!Q107 -> 286430.26 | F63: =EEFFun!R107 -> 441081.7 | G63: =EEFFun!S107 -> 347559.75 | H63: =EEFFun!T107 -> 491274.13 | I63: =EEFFun!U107 -> 579062.61 | J63: =EEFFun!V107 -> 716437.08 | K63: =EEFFun!W107 -> 839452.84 | ... AL63: =EEFFun!AX107 -> 196086.78 | AM63: =($W$63/($W$63+$W$71))*CalcIntCart!E19 -> 287879.08 | AN63: =($W$63/($W$63+$W$71))*CalcIntCart!F19 -> 313514.49 | AO63: =($W$63/($W$63+$W$71))*CalcIntCart!G19 -> 338712.63 | AP63: =($W$63/($W$63+$W$71))*CalcIntCart!H19 -> 363606.28 | AQ63: =($W$63/($W$63+$W$71))*CalcIntCart!I19 -> 388140.07 | AR63: =($W$63/($W$63+$W$71))*CalcIntCart!J19 -> 412532.74 | AS63: =($W$63/($W$63+$W$71))*CalcIntCart!K19 -> 436556.59 | AT63: =($W$63/($W$63+$W$71))*CalcIntCart!L19 -> 460259.17 | ... AX63: =($W$63/($W$63+$W$71))*CalcIntCart!P19 -> 551324.18 | AY63: =AX63-V63 -> -276813.8 | AZ63: =AX63-P63 -> -259348.39 | BA63: =P63/$P$5 -> 0.021242026 | BB63: =AX63/$AX$5 -> 0.0041222848 | BC63: =AT63-W63 -> -380224.15
A64: 4 | B64: =EEFFun!B113 -> 1434 | C64: =EEFFun!C113 -> CARTERA DE CRÉDITOS CONSUMO REFINANCIADA QUE NO DEVENGA INTERESES | D64: =EEFFun!P113 -> 0 | E64: =EEFFun!Q113 -> 0 | F64: =EEFFun!R113 -> 0 | G64: =EEFFun!S113 -> 0 | H64: =EEFFun!T113 -> 6439.92 | I64: =EEFFun!U113 -> 18249.72 | J64: =EEFFun!V113 -> 6135.4 | K64: =EEFFun!W113 -> 5981.42 | ... AL64: =EEFFun!AX113 -> 0 | AM64: =($W$64/($W$45+$W$46+$W$49)*CalcIntCart!E24) -> 148900.75 | AN64: =($W$64/($W$45+$W$46+$W$49)*CalcIntCart!F24) -> 149440.92 | AO64: =($W$64/($W$45+$W$46+$W$49)*CalcIntCart!G24) -> 149549.55 | AP64: =($W$64/($W$45+$W$46+$W$49)*CalcIntCart!H24) -> 149865.41 | AQ64: =($W$64/($W$45+$W$46+$W$49)*CalcIntCart!I24) -> 150049.67 | AR64: =($W$64/($W$45+$W$46+$W$49)*CalcIntCart!J24) -> 150208.16 | AS64: =($W$64/($W$45+$W$46+$W$49)*CalcIntCart!K24) -> 150236.34 | AT64: =($W$64/($W$45+$W$46+$W$49)*CalcIntCart!L24) -> 150235.6 | ... AX64: =($W$64/($W$45+$W$46+$W$49)*CalcIntCart!P24) -> 149476.71 | AY64: =AX64-V64 -> 12118.569 | AZ64: =AX64-P64 -> 81337.749 | BA64: =P64/$P$5 -> 0.0017854429 | BB64: =AX64/$AX$5 -> 0.0011176466 | BC64: =AT64-W64 -> -7011.6961
A65: 4 | B65: =EEFFun!B119 -> 1436 | C65: =EEFFun!C119 -> CARTERA DE MICROCRÉDITO REFINANCIADA QUE NO DEVENGA INTERESES | D65: =EEFFun!P119 -> 0 | E65: =EEFFun!Q119 -> 0 | F65: =EEFFun!R119 -> 0 | G65: =EEFFun!S119 -> 0 | H65: =EEFFun!T119 -> 0 | I65: =EEFFun!U119 -> 0 | J65: =EEFFun!V119 -> 0 | K65: =EEFFun!W119 -> 0 | ... AL65: =EEFFun!AX119 -> 11645.35 | AM65: =($W$65/($W$45+$W$46+$W$49)*CalcIntCart!E24) -> 63255.979 | AN65: =($W$65/($W$45+$W$46+$W$49)*CalcIntCart!F24) -> 63485.455 | AO65: =($W$65/($W$45+$W$46+$W$49)*CalcIntCart!G24) -> 63531.602 | AP65: =($W$65/($W$45+$W$46+$W$49)*CalcIntCart!H24) -> 63665.789 | AQ65: =($W$65/($W$45+$W$46+$W$49)*CalcIntCart!I24) -> 63744.063 | AR65: =($W$65/($W$45+$W$46+$W$49)*CalcIntCart!J24) -> 63811.396 | AS65: =($W$65/($W$45+$W$46+$W$49)*CalcIntCart!K24) -> 63823.366 | AT65: =($W$65/($W$45+$W$46+$W$49)*CalcIntCart!L24) -> 63823.053 | ... AX65: =($W$65/($W$45+$W$46+$W$49)*CalcIntCart!P24) -> 63500.659 | AY65: =AX65-V65 -> 4052.8192 | BC65: =AT65-W65 -> -2978.707
A66: 4 | B66: =EEFFun!B125 -> 1442 | C66: =EEFFun!C125 -> CARTERA DE CRÉDITOS CONSUMO REESTRUCTURADA QUE NO DEVENGA INTERESES | D66: =EEFFun!P125 -> 0 | E66: =EEFFun!Q125 -> 0 | F66: =EEFFun!R125 -> 0 | G66: =EEFFun!S125 -> 0 | H66: =EEFFun!T125 -> 0 | I66: =EEFFun!U125 -> 0 | J66: =EEFFun!V125 -> 0 | K66: =EEFFun!W125 -> 0 | ... AL66: =EEFFun!AX125 -> 12188.24 | AM66: =($W$66/($W$47+$W$48+$W$50)*CalcIntCart!E30) -> 22423.347 | AN66: =($W$66/($W$47+$W$48+$W$50)*CalcIntCart!F30) -> 22654.743 | AO66: =($W$66/($W$47+$W$48+$W$50)*CalcIntCart!G30) -> 22712.448 | AP66: =($W$66/($W$47+$W$48+$W$50)*CalcIntCart!H30) -> 22776.879 | AQ66: =($W$66/($W$47+$W$48+$W$50)*CalcIntCart!I30) -> 22770.39 | AR66: =($W$66/($W$47+$W$48+$W$50)*CalcIntCart!J30) -> 22783.529 | AS66: =($W$66/($W$47+$W$48+$W$50)*CalcIntCart!K30) -> 22726.453 | AT66: =($W$66/($W$47+$W$48+$W$50)*CalcIntCart!L30) -> 22638.881 | ... AX66: =($W$66/($W$47+$W$48+$W$50)*CalcIntCart!P30) -> 22065.35 | AY66: =AX66-V66 -> -63121.21 | BC66: =AT66-W66 -> -54805.249
A67: 4 | B67: =EEFFun!B131 -> 1444 | C67: =EEFFun!C131 -> CARTERA DE MICROCRÉDITO REESTRUCTURADA QUE NO DEVENGA INTERESES | D67: =EEFFun!P131 -> 2844.66 | E67: =EEFFun!Q131 -> 2247.66 | F67: =EEFFun!R131 -> 1942.48 | G67: =EEFFun!S131 -> 1632.31 | H67: =EEFFun!T131 -> 1314.48 | I67: =EEFFun!U131 -> 994.04 | J67: =EEFFun!V131 -> 667.83 | K67: =EEFFun!W131 -> 336.81 | ... AL67: =EEFFun!AX131 -> 1538.31 | AM67: =($W$67/($W$47+$W$48+$W$50)*CalcIntCart!E30) -> 26012.574 | AN67: =($W$67/($W$47+$W$48+$W$50)*CalcIntCart!F30) -> 26281.008 | AO67: =($W$67/($W$47+$W$48+$W$50)*CalcIntCart!G30) -> 26347.95 | AP67: =($W$67/($W$47+$W$48+$W$50)*CalcIntCart!H30) -> 26422.694 | AQ67: =($W$67/($W$47+$W$48+$W$50)*CalcIntCart!I30) -> 26415.166 | AR67: =($W$67/($W$47+$W$48+$W$50)*CalcIntCart!J30) -> 26430.409 | AS67: =($W$67/($W$47+$W$48+$W$50)*CalcIntCart!K30) -> 26364.196 | AT67: =($W$67/($W$47+$W$48+$W$50)*CalcIntCart!L30) -> 26262.607 | ... AX67: =($W$67/($W$47+$W$48+$W$50)*CalcIntCart!P30) -> 25597.273 | AY67: =AX67-V67 -> -8895.2472 | AZ67: =AX67-P67 -> 12289.163 | BA67: =P67/$P$5 -> 0.00034871196 | BB67: =AX67/$AX$5 -> 0.00019139238 | BC67: =AT67-W67 -> -63577.733
A68: 4 | B68: =EEFFun!B137 -> 1449 | C68: =EEFFun!C137 -> CARTERA DE CRÉDITOS PRODUCTIVO VENCIDA | D68: =EEFFun!P137 -> 12994.81 | E68: =EEFFun!Q137 -> 17439.56 | F68: =EEFFun!R137 -> 17439.56 | G68: =EEFFun!S137 -> 21972.91 | H68: =EEFFun!T137 -> 24267.64 | I68: =EEFFun!U137 -> 26567.5 | J68: =EEFFun!V137 -> 28899.6 | K68: =EEFFun!W137 -> 31237.39 | ... AL68: =EEFFun!AX137 -> 71 | AM68: =($W$68/($W$61+$W$68))*CalcIntCart!E7 -> 7477.3257 | AN68: =($W$68/($W$61+$W$68))*CalcIntCart!F7 -> 7476.8646 | AO68: =($W$68/($W$61+$W$68))*CalcIntCart!G7 -> 7467.3054 | AP68: =($W$68/($W$61+$W$68))*CalcIntCart!H7 -> 7457.4094 | AQ68: =($W$68/($W$61+$W$68))*CalcIntCart!I7 -> 7453.2709 | AR68: =($W$68/($W$61+$W$68))*CalcIntCart!J7 -> 7447.9746 | AS68: =($W$68/($W$61+$W$68))*CalcIntCart!K7 -> 7454.3386 | AT68: =($W$68/($W$61+$W$68))*CalcIntCart!L7 -> 7459.3815 | ... AX68: =($W$68/($W$61+$W$68))*CalcIntCart!P7 -> 7486.1811 | AY68: =AX68-V68 -> -51661.919 | AZ68: =AX68-P68 -> -36239.859 | BA68: =P68/$P$5 -> 0.001145752 | BB68: =AX68/$AX$5 -> 5.5974637e-05 | BC68: =AT68-W68 -> -54517.739
A69: 4 | B69: =EEFFun!B142 -> 1450 | C69: =EEFFun!C142 -> CARTERA DE CRÉDITOS CONSUMO VENCIDA | D69: =EEFFun!P142 -> 150435.48 | E69: =EEFFun!Q142 -> 199412.76 | F69: =EEFFun!R142 -> 223720.37 | G69: =EEFFun!S142 -> 243863.93 | H69: =EEFFun!T142 -> 258493.51 | I69: =EEFFun!U142 -> 284657.69 | J69: =EEFFun!V142 -> 314838.39 | K69: =EEFFun!W142 -> 341910.63 | ... AL69: =EEFFun!AX142 -> 48498.31 | AM69: =($W$69/($W$62+$W$69))*CalcIntCart!E13 -> 251431.8 | AN69: =($W$69/($W$62+$W$69))*CalcIntCart!F13 -> 277150.36 | AO69: =($W$69/($W$62+$W$69))*CalcIntCart!G13 -> 301910.82 | AP69: =($W$69/($W$62+$W$69))*CalcIntCart!H13 -> 324058.63 | AQ69: =($W$69/($W$62+$W$69))*CalcIntCart!I13 -> 347717.41 | AR69: =($W$69/($W$62+$W$69))*CalcIntCart!J13 -> 370994.34 | AS69: =($W$69/($W$62+$W$69))*CalcIntCart!K13 -> 393736.44 | AT69: =($W$69/($W$62+$W$69))*CalcIntCart!L13 -> 415937.79 | ... AX69: =($W$69/($W$62+$W$69))*CalcIntCart!P13 -> 498619.73 | AY69: =AX69-V69 -> -143660.42 | AZ69: =AX69-P69 -> 48696.233 | BA69: =P69/$P$5 -> 0.01178933 | BB69: =AX69/$AX$5 -> 0.0037282104 | BC69: =AT69-W69 -> -254230.26
A70: 4 | B70: =EEFFun!B148 -> 1451 | C70: =EEFFun!C148 -> CARTERA DE CREDITO DE INMOBILIARIA VENCIDA | D70: =EEFFun!P148 -> 1 | E70: =EEFFun!Q148 -> 1 | F70: =EEFFun!R148 -> 1 | G70: =EEFFun!S148 -> 1 | H70: =EEFFun!T148 -> 1 | I70: =EEFFun!U148 -> 1 | J70: =EEFFun!V148 -> 1 | K70: =EEFFun!W148 -> 1 | ... AL70: =EEFFun!AX148 -> 0 | AM70: =Q70 -> 0 | AN70: =R70 -> 0 | AO70: =S70 -> 0 | AP70: =T70 -> 0 | AQ70: =U70 -> 0 | AR70: =V70 -> 0 | AS70: =W70 -> 0 | AT70: =X70 -> 0 | ... AX70: =AB70 -> 0 | AY70: =AX70-V70 -> 0 | AZ70: =AX70-P70 -> -1 | BA70: =P70/$P$5 -> 2.6202966e-08 | BB70: =AX70/$AX$5 -> 0 | BC70: =AT70-W70 -> 0
A71: 4 | B71: =EEFFun!B154 -> 1452 | C71: =EEFFun!C154 -> CARTERA DE MICROCRÉDITO VENCIDA | D71: =EEFFun!P154 -> 30731.11 | E71: =EEFFun!Q154 -> 38775.34 | F71: =EEFFun!R154 -> 40957.43 | G71: =EEFFun!S154 -> 43977.82 | H71: =EEFFun!T154 -> 49936.68 | I71: =EEFFun!U154 -> 56540.06 | J71: =EEFFun!V154 -> 65878.65 | K71: =EEFFun!W154 -> 79549.88 | ... AL71: =EEFFun!AX154 -> 5944.48 | AM71: =($W$71/($W$63+$W$71))*CalcIntCart!E19 -> 60106.917 | AN71: =($W$71/($W$63+$W$71))*CalcIntCart!F19 -> 65459.391 | AO71: =($W$71/($W$63+$W$71))*CalcIntCart!G19 -> 70720.568 | AP71: =($W$71/($W$63+$W$71))*CalcIntCart!H19 -> 75918.167 | AQ71: =($W$71/($W$63+$W$71))*CalcIntCart!I19 -> 81040.633 | AR71: =($W$71/($W$63+$W$71))*CalcIntCart!J19 -> 86133.633 | AS71: =($W$71/($W$63+$W$71))*CalcIntCart!K19 -> 91149.625 | AT71: =($W$71/($W$63+$W$71))*CalcIntCart!L19 -> 96098.54 | ... AX71: =($W$71/($W$63+$W$71))*CalcIntCart!P19 -> 115112.21 | AY71: =AX71-V71 -> -58401.414 | AZ71: =AX71-P71 -> 13525.536 | BA71: =P71/$P$5 -> 0.0026618721 | BB71: =AX71/$AX$5 -> 0.00086070105 | BC71: =AT71-W71 -> -79387.85
A72: 4 | B72: =EEFFun!B160 -> 1458 | C72: =EEFFun!C160 -> CARTERA DE CRÉDITOS CONSUMO REFINANCIADA VENCIDA | D72: =EEFFun!P160 -> 0 | E72: =EEFFun!Q160 -> 0 | F72: =EEFFun!R160 -> 0 | G72: =EEFFun!S160 -> 0 | H72: =EEFFun!T160 -> 156.37 | I72: =EEFFun!U160 -> 471.65 | J72: =EEFFun!V160 -> 460.89 | K72: =EEFFun!W160 -> 614.87 | ... AL72: =EEFFun!AX160 -> 0 | AM72: =($W$72/($W$45+$W$46+$W$49)*CalcIntCart!E24) -> 9569.0991 | AN72: =($W$72/($W$45+$W$46+$W$49)*CalcIntCart!F24) -> 9603.8133 | AO72: =($W$72/($W$45+$W$46+$W$49)*CalcIntCart!G24) -> 9610.7943 | AP72: =($W$72/($W$45+$W$46+$W$49)*CalcIntCart!H24) -> 9631.0934 | AQ72: =($W$72/($W$45+$W$46+$W$49)*CalcIntCart!I24) -> 9642.9344 | AR72: =($W$72/($W$45+$W$46+$W$49)*CalcIntCart!J24) -> 9653.1203 | AS72: =($W$72/($W$45+$W$46+$W$49)*CalcIntCart!K24) -> 9654.9311 | AT72: =($W$72/($W$45+$W$46+$W$49)*CalcIntCart!L24) -> 9654.8837 | ... AX72: =($W$72/($W$45+$W$46+$W$49)*CalcIntCart!P24) -> 9606.1133 | AY72: =AX72-V72 -> 1406.0133 | AZ72: =AX72-P72 -> 6766.5133 | BA72: =P72/$P$5 -> 7.4405943e-05 | BB72: =AX72/$AX$5 -> 7.1825501e-05 | BC72: =AT72-W72 -> -450.6063
A73: 4 | B73: =EEFFun!B165 -> 1460 | C73: =EEFFun!C165 -> CARTERA DE MICROCRÉDITO REFINANCIADA VENCIDA | D73: =EEFFun!P165 -> 0 | E73: =EEFFun!Q165 -> 0 | F73: =EEFFun!R165 -> 0 | G73: =EEFFun!S165 -> 0 | H73: =EEFFun!T165 -> 0 | I73: =EEFFun!U165 -> 0 | J73: =EEFFun!V165 -> 0 | K73: =EEFFun!W165 -> 0 | ... AL73: =EEFFun!AX165 -> 586.73 | AM73: =($W$73/($W$45+$W$46+$W$49)*CalcIntCart!E24) -> 1684.9888 | AN73: =($W$73/($W$45+$W$46+$W$49)*CalcIntCart!F24) -> 1691.1015 | AO73: =($W$73/($W$45+$W$46+$W$49)*CalcIntCart!G24) -> 1692.3308 | AP73: =($W$73/($W$45+$W$46+$W$49)*CalcIntCart!H24) -> 1695.9052 | AQ73: =($W$73/($W$45+$W$46+$W$49)*CalcIntCart!I24) -> 1697.9902 | AR73: =($W$73/($W$45+$W$46+$W$49)*CalcIntCart!J24) -> 1699.7838 | AS73: =($W$73/($W$45+$W$46+$W$49)*CalcIntCart!K24) -> 1700.1027 | AT73: =($W$73/($W$45+$W$46+$W$49)*CalcIntCart!L24) -> 1700.0943 | ... AX73: =($W$73/($W$45+$W$46+$W$49)*CalcIntCart!P24) -> 1691.5065 | AY73: =AX73-V73 -> 224.16653 | BC73: =AT73-W73 -> -79.345671
A74: 4 | B74: =EEFFun!B169 -> 1466 | C74: =EEFFun!C169 -> CARTERA DE CRÉDITOS CONSUMO REESTRUCTURADA VENCIDA | D74: =EEFFun!P169 -> 0 | E74: =EEFFun!Q169 -> 0 | F74: =EEFFun!R169 -> 0 | G74: =EEFFun!S169 -> 0 | H74: =EEFFun!T169 -> 0 | I74: =EEFFun!U169 -> 0 | J74: =EEFFun!V169 -> 0 | K74: =EEFFun!W169 -> 0 | ... AL74: =EEFFun!AX169 -> 756.13 | AM74: =($W$74/($W$47+$W$48+$W$50)*CalcIntCart!E30) -> 1361.4624 | AN74: =($W$74/($W$47+$W$48+$W$50)*CalcIntCart!F30) -> 1375.5119 | AO74: =($W$74/($W$47+$W$48+$W$50)*CalcIntCart!G30) -> 1379.0155 | AP74: =($W$74/($W$47+$W$48+$W$50)*CalcIntCart!H30) -> 1382.9275 | AQ74: =($W$74/($W$47+$W$48+$W$50)*CalcIntCart!I30) -> 1382.5335 | AR74: =($W$74/($W$47+$W$48+$W$50)*CalcIntCart!J30) -> 1383.3313 | AS74: =($W$74/($W$47+$W$48+$W$50)*CalcIntCart!K30) -> 1379.8658 | AT74: =($W$74/($W$47+$W$48+$W$50)*CalcIntCart!L30) -> 1374.5488 | ... AX74: =($W$74/($W$47+$W$48+$W$50)*CalcIntCart!P30) -> 1339.7261 | AY74: =AX74-V74 -> -2623.9939 | BC74: =AT74-W74 -> -3327.5712
A75: 4 | B75: =EEFFun!B174 -> 1468 | C75: =EEFFun!C174 -> CARTERA DE MICROCRÉDITO REESTRUCTURADA VENCIDA | D75: =EEFFun!P174 -> 4633.61 | E75: =EEFFun!Q174 -> 5230.61 | F75: =EEFFun!R174 -> 5494.1 | G75: =EEFFun!S174 -> 5604.27 | H75: =EEFFun!T174 -> 5123.81 | I75: =EEFFun!U174 -> 3444.25 | J75: =EEFFun!V174 -> 2870.46 | K75: =EEFFun!W174 -> 2491.79 | ... AL75: =EEFFun!AX174 -> 173.42 | AM75: =($W$75/($W$47+$W$48+$W$50)*CalcIntCart!E30) -> 583.14098 | AN75: =($W$75/($W$47+$W$48+$W$50)*CalcIntCart!F30) -> 589.15864 | AO75: =($W$75/($W$47+$W$48+$W$50)*CalcIntCart!G30) -> 590.65932 | AP75: =($W$75/($W$47+$W$48+$W$50)*CalcIntCart!H30) -> 592.33492 | AQ75: =($W$75/($W$47+$W$48+$W$50)*CalcIntCart!I30) -> 592.16615 | AR75: =($W$75/($W$47+$W$48+$W$50)*CalcIntCart!J30) -> 592.50786 | AS75: =($W$75/($W$47+$W$48+$W$50)*CalcIntCart!K30) -> 591.02353 | AT75: =($W$75/($W$47+$W$48+$W$50)*CalcIntCart!L30) -> 588.74614 | ... AX75: =($W$75/($W$47+$W$48+$W$50)*CalcIntCart!P30) -> 573.8309 | AY75: =AX75-V75 -> -692.5291 | AZ75: =AX75-P75 -> -804.0391 | BA75: =P75/$P$5 -> 3.6104281e-05 | BB75: =AX75/$AX$5 -> 4.290569e-06 | BC75: =AT75-W75 -> -1425.2639
A76: 4 | B76: =EEFFun!B179 -> 1491 | C76: =EEFFun!C179 -> CARTERA REFINACIADA COVID 19 POR VENCER | D76: =EEFFun!P179 -> 33973.81 | E76: =EEFFun!Q179 -> 33183.34 | F76: =EEFFun!R179 -> 32381.94 | G76: =EEFFun!S179 -> 31526.11 | H76: =EEFFun!T179 -> 30982.56 | I76: =EEFFun!U179 -> 29852.37 | J76: =EEFFun!V179 -> 29153.35 | K76: =EEFFun!W179 -> 27991.67 | ... AL76: =EEFFun!AX179 -> 98200.69 | AM76: =AM77 -> 12418.696 | AN76: =AN77 -> 12463.748 | AO76: =AO77 -> 12472.808 | AP76: =AP77 -> 12499.152 | AQ76: =AQ77 -> 12514.519 | AR76: =AR77 -> 12527.738 | AS76: =AS77 -> 12530.088 | AT76: =AT77 -> 12530.027 | ... AX76: =AX77 -> 12466.733 | AY76: =AX76-V76 -> -1158.8069 | AZ76: =AX76-P76 -> -5496.9769 | BA76: =P76/$P$5 -> 0.00047070249 | BB76: =AX76/$AX$5 -> 9.3214531e-05 | BC76: =AT76-W76 -> -584.79307
A77: 6 | B77: =EEFFun!B181 -> 149120 | C77: =EEFFun!C181 -> CONSUMO POR VENCER | D77: =EEFFun!P181 -> 33973.81 | E77: =EEFFun!Q181 -> 33183.34 | F77: =EEFFun!R181 -> 32381.94 | G77: =EEFFun!S181 -> 31526.11 | H77: =EEFFun!T181 -> 30982.56 | I77: =EEFFun!U181 -> 29852.37 | J77: =EEFFun!V181 -> 29153.35 | K77: =EEFFun!W181 -> 27991.67 | ... AL77: =EEFFun!AX181 -> 10487.23 | AM77: =($W$77/($W$45+$W$46+$W$49)*CalcIntCart!E24) -> 12418.696 | AN77: =($W$77/($W$45+$W$46+$W$49)*CalcIntCart!F24) -> 12463.748 | AO77: =($W$77/($W$45+$W$46+$W$49)*CalcIntCart!G24) -> 12472.808 | AP77: =($W$77/($W$45+$W$46+$W$49)*CalcIntCart!H24) -> 12499.152 | AQ77: =($W$77/($W$45+$W$46+$W$49)*CalcIntCart!I24) -> 12514.519 | AR77: =($W$77/($W$45+$W$46+$W$49)*CalcIntCart!J24) -> 12527.738 | AS77: =($W$77/($W$45+$W$46+$W$49)*CalcIntCart!K24) -> 12530.088 | AT77: =($W$77/($W$45+$W$46+$W$49)*CalcIntCart!L24) -> 12530.027 | ... AX77: =($W$77/($W$45+$W$46+$W$49)*CalcIntCart!P24) -> 12466.733 | AY77: =AX77-V77 -> -1158.8069 | AZ77: =AX77-P77 -> -5496.9769 | BA77: =P77/$P$5 -> 0.00047070249 | BB77: =AX77/$AX$5 -> 9.3214531e-05 | BC77: =AT77-W77 -> -584.79307
A78: 4 | B78: =EEFFun!B182 -> 1492 | C78: =EEFFun!C182 -> CARTERA REFINACIADA COVID 19 NO DEVENGA | D78: =EEFFun!P182 -> 5403.96 | E78: =EEFFun!Q182 -> 5190.71 | F78: =EEFFun!R182 -> 5190.71 | G78: =EEFFun!S182 -> 4967.16 | H78: =EEFFun!T182 -> 4967.16 | I78: =EEFFun!U182 -> 4742.03 | J78: =EEFFun!V182 -> 4742.03 | K78: =EEFFun!W182 -> 4510.73 | ... AL78: =EEFFun!AX182 -> 16622.56 | AM78: =AM79 -> 6297.9232 | AN78: =AN79 -> 6320.7704 | AO78: =AO79 -> 6325.3649 | AP78: =AP79 -> 6338.7249 | AQ78: =AQ79 -> 6346.518 | AR78: =AR79 -> 6353.2219 | AS78: =AS79 -> 6354.4137 | AT78: =AT79 -> 6354.3825 | ... AX78: =AX79 -> 6322.2842 | AY78: =AX78-V78 -> -1614.4858 | AZ78: =AX78-P78 -> -3245.5458 | BA78: =P78/$P$5 -> 0.00025070553 | BB78: =AX78/$AX$5 -> 4.7272108e-05 | BC78: =AT78-W78 -> -296.56751
A79: 6 | B79: =EEFFun!B183 -> 149220 | C79: =EEFFun!C183 -> CONSUMO QUE NO DEVENGA INTERESES | D79: =EEFFun!P183 -> 5403.96 | E79: =EEFFun!Q183 -> 5190.71 | F79: =EEFFun!R183 -> 5190.71 | G79: =EEFFun!S183 -> 4967.16 | H79: =EEFFun!T183 -> 4967.16 | I79: =EEFFun!U183 -> 4742.03 | J79: =EEFFun!V183 -> 4742.03 | K79: =EEFFun!W183 -> 4510.73 | ... AL79: =EEFFun!AX183 -> 0 | AM79: =($W$79/($W$45+$W$46+$W$49)*CalcIntCart!E24) -> 6297.9232 | AN79: =($W$79/($W$45+$W$46+$W$49)*CalcIntCart!F24) -> 6320.7704 | AO79: =($W$79/($W$45+$W$46+$W$49)*CalcIntCart!G24) -> 6325.3649 | AP79: =($W$79/($W$45+$W$46+$W$49)*CalcIntCart!H24) -> 6338.7249 | AQ79: =($W$79/($W$45+$W$46+$W$49)*CalcIntCart!I24) -> 6346.518 | AR79: =($W$79/($W$45+$W$46+$W$49)*CalcIntCart!J24) -> 6353.2219 | AS79: =($W$79/($W$45+$W$46+$W$49)*CalcIntCart!K24) -> 6354.4137 | AT79: =($W$79/($W$45+$W$46+$W$49)*CalcIntCart!L24) -> 6354.3825 | ... AX79: =($W$79/($W$45+$W$46+$W$49)*CalcIntCart!P24) -> 6322.2842 | AY79: =AX79-V79 -> -1614.4858 | AZ79: =AX79-P79 -> -3245.5458 | BA79: =P79/$P$5 -> 0.00025070553 | BB79: =AX79/$AX$5 -> 4.7272108e-05 | BC79: =AT79-W79 -> -296.56751
A80: 4 | B80: =EEFFun!B184 -> 1493 | C80: =EEFFun!C184 -> CARTERA REFINACIADA COVID 19 VENCIDA | D80: =EEFFun!P184 -> 1338.91 | E80: =EEFFun!Q184 -> 1552.16 | F80: =EEFFun!R184 -> 1552.16 | G80: =EEFFun!S184 -> 1775.71 | H80: =EEFFun!T184 -> 1775.71 | I80: =EEFFun!U184 -> 2000.84 | J80: =EEFFun!V184 -> 2000.84 | K80: =EEFFun!W184 -> 2232.14 | ... AL80: =EEFFun!AX184 -> 1139.32 | AM80: =AM81 -> 3893.5491 | AN80: =AN81 -> 3907.6739 | AO80: =AO81 -> 3910.5144 | AP80: =AP81 -> 3918.7739 | AQ80: =AQ81 -> 3923.5918 | AR80: =AR81 -> 3927.7363 | AS80: =AS81 -> 3928.4731 | AT80: =AT81 -> 3928.4538 | ... AX80: =AX81 -> 3908.6098 | AY80: =AX80-V80 -> 748.56975 | AZ80: =AX80-P80 -> 1595.7198 | BA80: =P80/$P$5 -> 6.0604579e-05 | BB80: =AX80/$AX$5 -> 2.9224916e-05 | BC80: =AT80-W80 -> -183.34618
A81: 6 | B81: =EEFFun!B185 -> 149320 | C81: =EEFFun!C185 -> CONSUMO VENCIDA | D81: =EEFFun!P185 -> 1338.91 | E81: =EEFFun!Q185 -> 1552.16 | F81: =EEFFun!R185 -> 1552.16 | G81: =EEFFun!S185 -> 1775.71 | H81: =EEFFun!T185 -> 1775.71 | I81: =EEFFun!U185 -> 2000.84 | J81: =EEFFun!V185 -> 2000.84 | K81: =EEFFun!W185 -> 2232.14 | ... AL81: =EEFFun!AX185 -> 0 | AM81: =($W$81/($W$45+$W$46+$W$49)*CalcIntCart!E24) -> 3893.5491 | AN81: =($W$81/($W$45+$W$46+$W$49)*CalcIntCart!F24) -> 3907.6739 | AO81: =($W$81/($W$45+$W$46+$W$49)*CalcIntCart!G24) -> 3910.5144 | AP81: =($W$81/($W$45+$W$46+$W$49)*CalcIntCart!H24) -> 3918.7739 | AQ81: =($W$81/($W$45+$W$46+$W$49)*CalcIntCart!I24) -> 3923.5918 | AR81: =($W$81/($W$45+$W$46+$W$49)*CalcIntCart!J24) -> 3927.7363 | AS81: =($W$81/($W$45+$W$46+$W$49)*CalcIntCart!K24) -> 3928.4731 | AT81: =($W$81/($W$45+$W$46+$W$49)*CalcIntCart!L24) -> 3928.4538 | ... AX81: =($W$81/($W$45+$W$46+$W$49)*CalcIntCart!P24) -> 3908.6098 | AY81: =AX81-V81 -> 748.56975 | AZ81: =AX81-P81 -> 1595.7198 | BA81: =P81/$P$5 -> 6.0604579e-05 | BB81: =AX81/$AX$5 -> 2.9224916e-05 | BC81: =AT81-W81 -> -183.34618
A82: 4 | B82: =EEFFun!B186 -> 1494 | C82: =EEFFun!C186 -> CARTERA REESTRUCTURADA COVID 19 POR VENCER | D82: =EEFFun!P186 -> 233119.53 | E82: =EEFFun!Q186 -> 172949.38 | F82: =EEFFun!R186 -> 195458.09 | G82: =EEFFun!S186 -> 160860.48 | H82: =EEFFun!T186 -> 192397.9 | I82: =EEFFun!U186 -> 158699.98 | J82: =EEFFun!V186 -> 196475.88 | K82: =EEFFun!W186 -> 164265.63 | ... AL82: =EEFFun!AX186 -> 41922.38 | AM82: =AM83+AM84 -> 25661.756 | AN82: =AN83+AN84 -> 25926.57 | AO82: =AO83+AO84 -> 25992.609 | AP82: =AP83+AP84 -> 26066.345 | AQ82: =AQ83+AQ84 -> 26058.918 | AR82: =AR83+AR84 -> 26073.956 | AS82: =AS83+AS84 -> 26008.636 | AT82: =AT83+AT84 -> 25908.417 | ... AX82: =AX83+AX84 -> 25252.056 | AY82: =AX82-V82 -> -97683.644 | AZ82: =AX82-P82 -> -107731.24 | BA82: =P82/$P$5 -> 0.0034845569 | BB82: =AX82/$AX$5 -> 0.00018881118 | BC82: =AT82-W82 -> -62720.293
A83: 6 | B83: =EEFFun!B187 -> 149420 | C83: =EEFFun!C187 -> CONSUMO POR VENCER | D83: =EEFFun!P187 -> 218842.89 | E83: =EEFFun!Q187 -> 159231.65 | F83: =EEFFun!R187 -> 182308.28 | G83: =EEFFun!S187 -> 148307.83 | H83: =EEFFun!T187 -> 180431.97 | I83: =EEFFun!U187 -> 150159.73 | J83: =EEFFun!V187 -> 188090.14 | K83: =EEFFun!W187 -> 156040.98 | ... AL83: =EEFFun!AX187 -> 39040.96 | AM83: =($W$83/($W$47+$W$48+$W$50)*CalcIntCart!E30) -> 23890.562 | AN83: =($W$83/($W$47+$W$48+$W$50)*CalcIntCart!F30) -> 24137.098 | AO83: =($W$83/($W$47+$W$48+$W$50)*CalcIntCart!G30) -> 24198.579 | AP83: =($W$83/($W$47+$W$48+$W$50)*CalcIntCart!H30) -> 24267.227 | AQ83: =($W$83/($W$47+$W$48+$W$50)*CalcIntCart!I30) -> 24260.312 | AR83: =($W$83/($W$47+$W$48+$W$50)*CalcIntCart!J30) -> 24274.312 | AS83: =($W$83/($W$47+$W$48+$W$50)*CalcIntCart!K30) -> 24213.5 | AT83: =($W$83/($W$47+$W$48+$W$50)*CalcIntCart!L30) -> 24120.199 | ... AX83: =($W$83/($W$47+$W$48+$W$50)*CalcIntCart!P30) -> 23509.14 | AY83: =AX83-V83 -> -93117.1 | AZ83: =AX83-P83 -> -102079.46 | BA83: =P83/$P$5 -> 0.0032907939 | BB83: =AX83/$AX$5 -> 0.00017577929 | BC83: =AT83-W83 -> -58391.291
A84: 6 | B84: =EEFFun!B188 -> 149440 | C84: =EEFFun!C188 -> MICROCRÉDITO POR VENCER | D84: =EEFFun!P188 -> 14276.64 | E84: =EEFFun!Q188 -> 13717.73 | F84: =EEFFun!R188 -> 13149.81 | G84: =EEFFun!S188 -> 12552.65 | H84: =EEFFun!T188 -> 11965.93 | I84: =EEFFun!U188 -> 8540.25 | J84: =EEFFun!V188 -> 8385.74 | K84: =EEFFun!W188 -> 8224.65 | ... AL84: =EEFFun!AX188 -> 2881.42 | AM84: =($W$84/($W$47+$W$48+$W$50)*CalcIntCart!E30) -> 1771.1936 | AN84: =($W$84/($W$47+$W$48+$W$50)*CalcIntCart!F30) -> 1789.4713 | AO84: =($W$84/($W$47+$W$48+$W$50)*CalcIntCart!G30) -> 1794.0293 | AP84: =($W$84/($W$47+$W$48+$W$50)*CalcIntCart!H30) -> 1799.1187 | AQ84: =($W$84/($W$47+$W$48+$W$50)*CalcIntCart!I30) -> 1798.6061 | AR84: =($W$84/($W$47+$W$48+$W$50)*CalcIntCart!J30) -> 1799.644 | AS84: =($W$84/($W$47+$W$48+$W$50)*CalcIntCart!K30) -> 1795.1355 | AT84: =($W$84/($W$47+$W$48+$W$50)*CalcIntCart!L30) -> 1788.2184 | ... AX84: =($W$84/($W$47+$W$48+$W$50)*CalcIntCart!P30) -> 1742.9158 | AY84: =AX84-V84 -> -4566.5442 | AZ84: =AX84-P84 -> -5651.7842 | BA84: =P84/$P$5 -> 0.00019376308 | BB84: =AX84/$AX$5 -> 1.3031889e-05 | BC84: =AT84-W84 -> -4329.0016
A85: 4 | B85: =EEFFun!B189 -> 1495 | C85: =EEFFun!C189 -> CARTERA REESTRUCTURADA COVID 19 NO DEVENGA | D85: =EEFFun!P189 -> 98944.98 | E85: =EEFFun!Q189 -> 150556.08 | F85: =EEFFun!R189 -> 124055.93 | G85: =EEFFun!S189 -> 140890.05 | H85: =EEFFun!T189 -> 105197.76 | I85: =EEFFun!U189 -> 119729.73 | J85: =EEFFun!V189 -> 77584.18 | K85: =EEFFun!W189 -> 102579.05 | ... AL85: =EEFFun!AX189 -> 14356.64 | AM85: =AM86+AM87 -> 23920.125 | AN85: =AN86+AN87 -> 24166.966 | AO85: =AO86+AO87 -> 24228.523 | AP85: =AP86+AP87 -> 24297.255 | AQ85: =AQ86+AQ87 -> 24290.332 | AR85: =AR86+AR87 -> 24304.349 | AS85: =AS86+AS87 -> 24243.462 | AT85: =AT86+AT87 -> 24150.045 | ... AX85: =AX86+AX87 -> 23538.23 | AY85: =AX85-V85 -> -33661.7 | AZ85: =AX85-P85 -> -65641.09 | BA85: =P85/$P$5 -> 0.0023367627 | BB85: =AX85/$AX$5 -> 0.0001759968 | BC85: =AT85-W85 -> -58463.545
A86: 6 | B86: =EEFFun!B190 -> 149520 | C86: =EEFFun!C190 -> CONSUMO QUE NO DEVENGA INTERESES | D86: =EEFFun!P190 -> 98944.98 | E86: =EEFFun!Q190 -> 150556.08 | F86: =EEFFun!R190 -> 124055.93 | G86: =EEFFun!S190 -> 140890.05 | H86: =EEFFun!T190 -> 105197.76 | I86: =EEFFun!U190 -> 119729.73 | J86: =EEFFun!V190 -> 77584.18 | K86: =EEFFun!W190 -> 102579.05 | ... AL86: =EEFFun!AX190 -> 14356.64 | AM86: =($W$86/($W$47+$W$48+$W$50)*CalcIntCart!E30) -> 23920.125 | AN86: =($W$86/($W$47+$W$48+$W$50)*CalcIntCart!F30) -> 24166.966 | AO86: =($W$86/($W$47+$W$48+$W$50)*CalcIntCart!G30) -> 24228.523 | AP86: =($W$86/($W$47+$W$48+$W$50)*CalcIntCart!H30) -> 24297.255 | AQ86: =($W$86/($W$47+$W$48+$W$50)*CalcIntCart!I30) -> 24290.332 | AR86: =($W$86/($W$47+$W$48+$W$50)*CalcIntCart!J30) -> 24304.349 | AS86: =($W$86/($W$47+$W$48+$W$50)*CalcIntCart!K30) -> 24243.462 | AT86: =($W$86/($W$47+$W$48+$W$50)*CalcIntCart!L30) -> 24150.045 | ... AX86: =($W$86/($W$47+$W$48+$W$50)*CalcIntCart!P30) -> 23538.23 | AY86: =AX86-V86 -> -33661.7 | AZ86: =AX86-P86 -> -65641.09 | BA86: =P86/$P$5 -> 0.0023367627 | BB86: =AX86/$AX$5 -> 0.0001759968 | BC86: =AT86-W86 -> -58463.545
A87: 6 | B87: =EEFFun!B191 -> 149540 | C87: =EEFFun!C191 -> MICROCRÉDITO QUE NO DEVENGA INTERESES | D87: =EEFFun!P191 -> 0 | E87: =EEFFun!Q191 -> 0 | F87: =EEFFun!R191 -> 0 | G87: =EEFFun!S191 -> 0 | H87: =EEFFun!T191 -> 0 | I87: =EEFFun!U191 -> 0 | J87: =EEFFun!V191 -> 0 | K87: =EEFFun!W191 -> 0 | ... AL87: =EEFFun!AX191 -> 0 | AM87: =($W$87/($W$47+$W$48+$W$50)*CalcIntCart!E30) -> 0 | AN87: =($W$87/($W$47+$W$48+$W$50)*CalcIntCart!F30) -> 0 | AO87: =($W$87/($W$47+$W$48+$W$50)*CalcIntCart!G30) -> 0 | AP87: =($W$87/($W$47+$W$48+$W$50)*CalcIntCart!H30) -> 0 | AQ87: =($W$87/($W$47+$W$48+$W$50)*CalcIntCart!I30) -> 0 | AR87: =($W$87/($W$47+$W$48+$W$50)*CalcIntCart!J30) -> 0 | AS87: =($W$87/($W$47+$W$48+$W$50)*CalcIntCart!K30) -> 0 | AT87: =($W$87/($W$47+$W$48+$W$50)*CalcIntCart!L30) -> 0 | ... AX87: =($W$87/($W$47+$W$48+$W$50)*CalcIntCart!P30) -> 0 | AY87: =AX87-V87 -> 0 | AZ87: =AX87-P87 -> 0 | BA87: =P87/$P$5 -> 0 | BB87: =AX87/$AX$5 -> 0 | BC87: =AT87-W87 -> 0
A88: 4 | B88: =EEFFun!B192 -> 1496 | C88: =EEFFun!C192 -> CARTERA REESTRUCTURADA COVID 19 VENCIDA | D88: =EEFFun!P192 -> 18748.4 | E88: =EEFFun!Q192 -> 22888.4 | F88: =EEFFun!R192 -> 22179.05 | G88: =EEFFun!S192 -> 25886.51 | H88: =EEFFun!T192 -> 25142.07 | I88: =EEFFun!U192 -> 28166.85 | J88: =EEFFun!V192 -> 27424.73 | K88: =EEFFun!W192 -> 30978.3 | ... AL88: =EEFFun!AX192 -> 981.84 | AM88: =AM89+AM90 -> 11463.036 | AN88: =AN89+AN90 -> 11581.327 | AO88: =AO89+AO90 -> 11610.827 | AP88: =AP89+AP90 -> 11643.764 | AQ88: =AQ89+AQ90 -> 11640.447 | AR88: =AR89+AR90 -> 11647.164 | AS88: =AS89+AS90 -> 11617.986 | AT88: =AT89+AT90 -> 11573.218 | ... AX88: =AX89+AX90 -> 11280.024 | AY88: =AX88-V88 -> -24178.686 | AZ88: =AX88-P88 -> -23123.106 | BA88: =P88/$P$5 -> 0.00090146406 | BB88: =AX88/$AX$5 -> 8.4341431e-05 | BC88: =AT88-W88 -> -28016.982
A89: 6 | B89: =EEFFun!B193 -> 149620 | C89: =EEFFun!C193 -> CONSUMO VENCIDA | D89: =EEFFun!P193 -> 18748.4 | E89: =EEFFun!Q193 -> 22888.4 | F89: =EEFFun!R193 -> 22179.05 | G89: =EEFFun!S193 -> 25886.51 | H89: =EEFFun!T193 -> 25142.07 | I89: =EEFFun!U193 -> 28166.85 | J89: =EEFFun!V193 -> 27424.73 | K89: =EEFFun!W193 -> 30978.3 | ... AL89: =EEFFun!AX193 -> 981.84 | AM89: =($W$89/($W$47+$W$48+$W$50)*CalcIntCart!E30) -> 11463.036 | AN89: =($W$89/($W$47+$W$48+$W$50)*CalcIntCart!F30) -> 11581.327 | AO89: =($W$89/($W$47+$W$48+$W$50)*CalcIntCart!G30) -> 11610.827 | AP89: =($W$89/($W$47+$W$48+$W$50)*CalcIntCart!H30) -> 11643.764 | AQ89: =($W$89/($W$47+$W$48+$W$50)*CalcIntCart!I30) -> 11640.447 | AR89: =($W$89/($W$47+$W$48+$W$50)*CalcIntCart!J30) -> 11647.164 | AS89: =($W$89/($W$47+$W$48+$W$50)*CalcIntCart!K30) -> 11617.986 | AT89: =($W$89/($W$47+$W$48+$W$50)*CalcIntCart!L30) -> 11573.218 | ... AX89: =($W$89/($W$47+$W$48+$W$50)*CalcIntCart!P30) -> 11280.024 | AY89: =AX89-V89 -> -24178.686 | AZ89: =AX89-P89 -> -23123.106 | BA89: =P89/$P$5 -> 0.00090146406 | BB89: =AX89/$AX$5 -> 8.4341431e-05 | BC89: =AT89-W89 -> -28016.982
A90: 6 | B90: =EEFFun!B194 -> 149640 | C90: =EEFFun!C194 -> MICROCRÉDITO VENCIDA | D90: =EEFFun!P194 -> 0 | E90: =EEFFun!Q194 -> 0 | F90: =EEFFun!R194 -> 0 | G90: =EEFFun!S194 -> 0 | H90: =EEFFun!T194 -> 0 | I90: =EEFFun!U194 -> 0 | J90: =EEFFun!V194 -> 0 | K90: =EEFFun!W194 -> 0 | ... AL90: =EEFFun!AX194 -> 0 | AM90: =($P$90/($P$47+$P$48+$P$50)*CalcIntCart!E30) -> 0 | AN90: =($P$90/($P$47+$P$48+$P$50)*CalcIntCart!F30) -> 0 | AO90: =($P$90/($P$47+$P$48+$P$50)*CalcIntCart!G30) -> 0 | AP90: =($P$90/($P$47+$P$48+$P$50)*CalcIntCart!H30) -> 0 | AQ90: =($P$90/($P$47+$P$48+$P$50)*CalcIntCart!I30) -> 0 | AR90: =($P$90/($P$47+$P$48+$P$50)*CalcIntCart!J30) -> 0 | AS90: =($P$90/($P$47+$P$48+$P$50)*CalcIntCart!K30) -> 0 | AT90: =($P$90/($P$47+$P$48+$P$50)*CalcIntCart!L30) -> 0 | ... AX90: =($P$90/($P$47+$P$48+$P$50)*CalcIntCart!P30) -> 0 | AY90: =AX90-V90 -> 0 | AZ90: =AX90-P90 -> 0 | BA90: =P90/$P$5 -> 0 | BB90: =AX90/$AX$5 -> 0 | BC90: =AT90-W90 -> 0
A91: 4 | B91: =EEFFun!B195 -> 1499 | C91: =EEFFun!C195 -> (Provisiones para créditos incobrables) | D91: =EEFFun!P195 -> -1615254.5 | E91: =EEFFun!Q195 -> -1614105.4 | F91: =EEFFun!R195 -> -1610345.1 | G91: =EEFFun!S195 -> -1638012.4 | H91: =EEFFun!T195 -> -1672236.3 | I91: =EEFFun!U195 -> -1809112.8 | J91: =EEFFun!V195 -> -1902226.8 | K91: =EEFFun!W195 -> -1976006.1 | ... AL91: =EEFFun!AX195 -> -1090856.6 | AM91: =SUM(AM92:AM101) -> -1172423.5 | AN91: =SUM(AN92:AN101) -> -1253371.7 | AO91: =SUM(AO92:AO101) -> -1331581 | AP91: =SUM(AP92:AP101) -> -1403594.3 | AQ91: =SUM(AQ92:AQ101) -> -1478691 | AR91: =SUM(AR92:AR101) -> -1552802.5 | AS91: =SUM(AS92:AS101) -> -1625320.9 | AT91: =SUM(AT92:AT101) -> -1669410.1 | ... AX91: =SUM(AX92:AX101) -> -2181868.9 | AY91: =AX91-V91 -> 192647.37 | AZ91: =AX91-P91 -> -112223.29 | BA91: =P91/$P$5 -> -0.054230854 | BB91: =AX91/$AX$5 -> -0.016313968 | BC91: =AT91-W91 -> 591314.01
A92: 6 | B92: =EEFFun!B196 -> 149905 | C92: =EEFFun!C196 -> (CARTERA DE CRÉDITOS PRODUCTIVO ) | D92: =EEFFun!P196 -> -105673.91 | E92: =EEFFun!Q196 -> -84286.01 | F92: =EEFFun!R196 -> -86032.16 | G92: =EEFFun!S196 -> -75212.08 | H92: =EEFFun!T196 -> -61188.16 | I92: =EEFFun!U196 -> -96344.25 | J92: =EEFFun!V196 -> -91498.68 | K92: =EEFFun!W196 -> -82823.52 | ... AL92: =EEFFun!AX196 -> -4698.86 | AM92: =RecupProv!C83 -> -4693.3017 | AN92: =RecupProv!D83 -> -4693.0123 | AO92: =RecupProv!E83 -> -4687.0122 | AP92: =RecupProv!F83 -> -4680.8008 | AQ92: =RecupProv!G83 -> -4678.2032 | AR92: =RecupProv!H83 -> -4674.8789 | AS92: =RecupProv!I83 -> -4678.8734 | AT92: =RecupProv!J83 -> -4682.0387 | ... AX92: =RecupProv!N83 -> -4698.86 | AY92: =AX92-V92 -> 78288.48 | AZ92: =AX92-P92 -> 76162.74 | BA92: =P92/$P$5 -> -0.0021188138 | BB92: =AX92/$AX$5 -> -3.5133666e-05 | BC92: =AT92-W92 -> 77475.931
A93: 6 | B93: =EEFFun!B198 -> 149910 | C93: =EEFFun!C198 -> (CARTERA DE CRÉDITOS CONSUMO ) | D93: =EEFFun!P198 -> -822756.82 | E93: =EEFFun!Q198 -> -985160.79 | F93: =EEFFun!R198 -> -1042014.4 | G93: =EEFFun!S198 -> -1099288.4 | H93: =EEFFun!T198 -> -1110490.3 | I93: =EEFFun!U198 -> -1184528.5 | J93: =EEFFun!V198 -> -1232812.9 | K93: =EEFFun!W198 -> -1251395.7 | ... AL93: =EEFFun!AX198 -> -514259.37 | AM93: =RecupProv!C84 -> -574340.97 | AN93: =RecupProv!D84 -> -633089.38 | AO93: =RecupProv!E84 -> -689649.25 | AP93: =RecupProv!F84 -> -740241.07 | AQ93: =RecupProv!G84 -> -794284.39 | AR93: =RecupProv!H84 -> -847455.44 | AS93: =RecupProv!I84 -> -899404.8 | AT93: =RecupProv!J84 -> -931116.55 | ... AX93: =RecupProv!N84 -> -988065.88 | AY93: =AX93-V93 -> 395799.46 | AZ93: =AX93-P93 -> 233655.87 | BA93: =P93/$P$5 -> -0.032012734 | BB93: =AX93/$AX$5 -> -0.0073878294 | BC93: =AT93-W93 -> 371418.54
A94: 6 | B94: =EEFFun!B200 -> 149915 | C94: =EEFFun!C200 -> (CARTERA DE CREDITO INMOBILIARIO) | D94: =EEFFun!P200 -> -1 | E94: =EEFFun!Q200 -> -1 | F94: =EEFFun!R200 -> -1 | G94: =EEFFun!S200 -> -1 | H94: =EEFFun!T200 -> -1 | I94: =EEFFun!U200 -> -1 | J94: =EEFFun!V200 -> -1 | K94: =EEFFun!W200 -> -1 | ... AL94: =EEFFun!AX200 -> 0 | AM94: -1 | AN94: -1 | AO94: -1 | AP94: -1 | AQ94: -1 | AR94: -1 | AS94: -1 | AT94: -1 | AU94: -1 | AV94: -1 | AW94: -1 | AX94: -1 | AY94: =AX94-V94 -> -1 | AZ94: =AX94-P94 -> 0 | BA94: =P94/$P$5 -> -2.6202966e-08 | BB94: =AX94/$AX$5 -> -7.4770616e-09 | BC94: =AT94-W94 -> -1
A95: 6 | B95: =EEFFun!B202 -> 149920 | C95: =EEFFun!C202 -> (CARTERA DE MICROCRÉDITO ) | D95: =EEFFun!P202 -> -142248.12 | E95: =EEFFun!Q202 -> -226754.59 | F95: =EEFFun!R202 -> -264203.17 | G95: =EEFFun!S202 -> -298723.79 | H95: =EEFFun!T202 -> -337735.91 | I95: =EEFFun!U202 -> -372792.55 | J95: =EEFFun!V202 -> -423376.16 | K95: =EEFFun!W202 -> -468457.32 | ... AL95: =EEFFun!AX202 -> -224495.77 | AM95: =RecupProv!C86 -> -246816.24 | AN95: =RecupProv!D86 -> -268795.04 | AO95: =RecupProv!E86 -> -290398.94 | AP95: =RecupProv!F86 -> -311741.78 | AQ95: =RecupProv!G86 -> -332776.09 | AR95: =RecupProv!H86 -> -353689.41 | AS95: =RecupProv!I86 -> -374286.51 | AT95: =RecupProv!J86 -> -386716.01 | ... AX95: =RecupProv!N86 -> -342676.11 | AY95: =AX95-V95 -> 279627.08 | AZ95: =AX95-P95 -> 140352.41 | BA95: =P95/$P$5 -> -0.01265678 | BB95: =AX95/$AX$5 -> -0.0025622104 | BC95: =AT95-W95 -> 202054.91
A96: 6 | B96: =EEFFun!B204 -> 149945 | C96: =EEFFun!C204 -> (CARTERA DE CREDITO REFINANCIADA) | D96: =EEFFun!P204 -> -7275.36 | E96: =EEFFun!Q204 -> -7394.6 | F96: =EEFFun!R204 -> -7326.18 | G96: =EEFFun!S204 -> -7435.93 | H96: =EEFFun!T204 -> -7736.66 | I96: =EEFFun!U204 -> -9345.8 | J96: =EEFFun!V204 -> -11520.46 | K96: =EEFFun!W204 -> -14554.06 | ... AL96: =EEFFun!AX204 -> -19986.8 | AM96: =RecupProv!C87 -> -20830.489 | AN96: =RecupProv!D87 -> -20906.056 | AO96: =RecupProv!E87 -> -20921.253 | AP96: =RecupProv!F87 -> -20965.441 | AQ96: =RecupProv!G87 -> -20991.217 | AR96: =RecupProv!H87 -> -21013.39 | AS96: =RecupProv!I87 -> -21017.332 | AT96: =RecupProv!J87 -> -21017.229 | ... AX96: =RecupProv!N87 -> -20911.063 | AY96: =AX96-V96 -> 74954.037 | AZ96: =AX96-P96 -> 22115.167 | BA96: =P96/$P$5 -> -0.0011274149 | BB96: =AX96/$AX$5 -> -0.00015635331 | BC96: =AT96-W96 -> 66941.921
A97: 6 | B97: =EEFFun!B205 -> 149950 | C97: =EEFFun!C205 -> (CARTERA DE CREDITO REESTRUCTURADA) | D97: =EEFFun!P205 -> -115853.18 | E97: =EEFFun!Q205 -> -123814.9 | F97: =EEFFun!R205 -> -119328.19 | G97: =EEFFun!S205 -> -125424.32 | H97: =EEFFun!T205 -> -123157.4 | I97: =EEFFun!U205 -> -114173.81 | J97: =EEFFun!V205 -> -111090.79 | K97: =EEFFun!W205 -> -126847.62 | ... AL97: =EEFFun!AX205 -> -15798.23 | AM97: =RecupProv!C88 -> -14123.942 | AN97: =RecupProv!D88 -> -14269.692 | AO97: =RecupProv!E88 -> -14306.04 | AP97: =RecupProv!F88 -> -14346.623 | AQ97: =RecupProv!G88 -> -14342.536 | AR97: =RecupProv!H88 -> -14350.812 | AS97: =RecupProv!I88 -> -14314.861 | AT97: =RecupProv!J88 -> -14259.702 | ... AX97: =RecupProv!N88 -> -13898.448 | AY97: =AX97-V97 -> 143669.98 | AZ97: =AX97-P97 -> 195181.19 | BA97: =P97/$P$5 -> -0.0054785068 | BB97: =AX97/$AX$5 -> -0.00010391955 | BC97: =AT97-W97 -> 153114.39
A98: 6 | B98: =EEFFun!B206 -> 149980 | C98: =EEFFun!C206 -> (PROVISIÓN GENERICA POR TECNOLOGIA CREDITICIA) | D98: =EEFFun!P206 -> 0 | E98: =EEFFun!Q206 -> 0 | F98: =EEFFun!R206 -> 0 | G98: =EEFFun!S206 -> 0 | H98: =EEFFun!T206 -> 0 | I98: =EEFFun!U206 -> 0 | J98: =EEFFun!V206 -> 0 | K98: =EEFFun!W206 -> 0 | ... AL98: =EEFFun!AX206 -> 0 | AM98: =RecupProv!C89 -> 0 | AN98: =RecupProv!D89 -> 0 | AO98: =RecupProv!E89 -> 0 | AP98: =RecupProv!F89 -> 0 | AQ98: =RecupProv!G89 -> 0 | AR98: =RecupProv!H89 -> 0 | AS98: =RecupProv!I89 -> 0 | AT98: =RecupProv!J89 -> 0 | ... AX98: =RecupProv!N89 -> 0 | AY98: =AX98-V98 -> 0 | AZ98: =AX98-P98 -> 0 | BA98: =P98/$P$5 -> 0 | BB98: =AX98/$AX$5 -> 0 | BC98: =AT98-W98 -> 0
A99: 6 | B99: =EEFFun!B207 -> 149985 | C99: =EEFFun!C207 -> (PROVISION ANTICICLICA) | D99: =EEFFun!P207 -> -29381.42 | E99: =EEFFun!Q207 -> -29381.42 | F99: =EEFFun!R207 -> -29381.42 | G99: =EEFFun!S207 -> -29381.42 | H99: =EEFFun!T207 -> -29381.42 | I99: =EEFFun!U207 -> -29381.42 | J99: =EEFFun!V207 -> -29381.42 | K99: =EEFFun!W207 -> -29381.42 | ... AL99: =EEFFun!AX207 -> -29381.42 | AM99: =RecupProv!C90 -> -29381.42 | AN99: =RecupProv!D90 -> -29381.42 | AO99: =RecupProv!E90 -> -29381.42 | AP99: =RecupProv!F90 -> -29381.42 | AQ99: =RecupProv!G90 -> -29381.42 | AR99: =RecupProv!H90 -> -29381.42 | AS99: =RecupProv!I90 -> -29381.42 | AT99: =RecupProv!J90 -> -29381.42 | ... AX99: =RecupProv!N90 -> -29381.42 | AY99: =AX99-V99 -> 0 | AZ99: =AX99-P99 -> 0 | BA99: =P99/$P$5 -> -0.00076988036 | BB99: =AX99/$AX$5 -> -0.00021968669 | BC99: =AT99-W99 -> 0
A100: 6 | B100: =EEFFun!B208 -> 149987 | C100: =EEFFun!C208 -> (PROVISION NO REVERSADAS POR REQUER. NORMATIVO) | D100: =EEFFun!P208 -> -389519.28 | E100: =EEFFun!Q208 -> -154766.68 | F100: =EEFFun!R208 -> -59513.08 | G100: =EEFFun!S208 -> 0 | H100: =EEFFun!T208 -> 0 | I100: =EEFFun!U208 -> 0 | J100: =EEFFun!V208 -> 0 | K100: =EEFFun!W208 -> 0 | ... AL100: =EEFFun!AX208 -> -279690.67 | AM100: =+AL100 -> -279690.67 | AN100: =+AM100 -> -279690.67 | AO100: =+AN100 -> -279690.67 | AP100: =+AO100 -> -279690.67 | AQ100: =+AP100 -> -279690.67 | AR100: =+AQ100 -> -279690.67 | AS100: =+AR100 -> -279690.67 | AT100: =+AS100 -> -279690.67 | ... AW100: =+AV100 -> -279690.67 | AX100: =+AW100-500000 -> -779690.67 | AY100: =AX100-V100 -> -779690.67 | AZ100: =AX100-P100 -> -779690.67 | BA100: =P100/$P$5 -> 0 | BB100: =AX100/$AX$5 -> -0.0058297951 | BC100: =AT100-W100 -> -279690.67
...

Sheet BGresu
A1: 📊 Análisis inicial – Recuperación y provisiones de cartera
A3: Fuente analizada: RecupProv | Proyección mensual 2025
A5: Recuperación capital | B5: Recuperación intereses | C5: Recuperación total | D5: Riesgo ene→dic 2025 | E5: Cobertura ene→dic 2025 | F5: Castigos proyectados | H5: 🥇 Mix de recuperación por segmento
A6: =RecupProv!O27 -> 8241824.4 | B6: =RecupProv!O53 -> 3207702.3 | C6: =A6+B6 -> 11449527 | D6: =(RecupProv!N108/RecupProv!C108)-1 -> 0.93652015 | E6: =RecupProv!N115-RecupProv!C115 -> -0.2923764 | F6: =RecupProv!O127/RecupProv!O27 -> 0.02078115 | H6: Segmento | I6: Capital total | J6: Participación
H7: Productivo | I7: =RecupProv!O6 -> 182676.18 | J7: =I7/$C$6 -> 0.015954911
A8: 🧠 Hallazgos iniciales | H8: Consumo | I8: =RecupProv!O10 -> 6488683.9 | J8: =I8/$C$6 -> 0.56672071
A9: 1 | B9: La recuperación total proyectada del año supera los $11 MM al sumar capital e intereses. | H9: Microcrédito | I9: =RecupProv!O11 -> 1332189.9 | J9: =I9/$C$6 -> 0.11635328
A10: 2 | B10: Consumo concentra la mayor parte de la recuperación y también lidera el crecimiento del riesgo. | H10: Refinanciada | I10: =RecupProv!O15 -> 99983.89 | J10: =I10/$C$6 -> 0.0087325784
A11: 3 | B11: La cartera en riesgo casi se duplica durante 2025, mientras la cobertura pierde solidez. | H11: Reestructurada | I11: =RecupProv!O21 -> 138290.52 | J11: =I11/$C$6 -> 0.012078274
A12: 4 | B12: Los castigos aparecen al final del año y octubre es el mes más exigente.
A13: 5 | B13: La cartera bruta crece con fuerza, impulsada sobre todo por Consumo y Microcrédito.
A15: 📈 Recuperación mensual total | H15: ⚠️ Riesgo y cobertura
A16: Mes | B16: Capital | C16: Intereses | D16: Total | H16: Mes | I16: Riesgo cartera | J16: Provisión proyectada | K16: Cobertura
A17: Enero | B17: =RecupProv!C27 -> 653294.65 | C17: =RecupProv!C53 -> 281063.45 | D17: =B17+C17 -> 934358.1 | H17: Enero | I17: =RecupProv!C108 -> 1039490.2 | J17: =ABS(RecupProv!C93) -> 1172422.5 | K17: =RecupProv!C115 -> 1.1278822
A18: Febrero | B18: =RecupProv!D27 -> 654499.52 | C18: =RecupProv!D53 -> 327572.51 | D18: =B18+C18 -> 982072.03 | H18: Febrero | I18: =RecupProv!D108 -> 1138697 | J18: =ABS(RecupProv!D93) -> 1253370.7 | K18: =RecupProv!D115 -> 1.1007061
A19: Marzo | B19: =RecupProv!E27 -> 714310.43 | C19: =RecupProv!E53 -> 264660.72 | D19: =B19+C19 -> 978971.15 | H19: Marzo | I19: =RecupProv!E108 -> 1234770.1 | J19: =ABS(RecupProv!E93) -> 1331580 | K19: =RecupProv!E115 -> 1.0784032
A20: Abril | B20: =RecupProv!F27 -> 981352.93 | C20: =RecupProv!F53 -> 311606.03 | D20: =B20+C20 -> 1292959 | H20: Abril | I20: =RecupProv!F108 -> 1323564.7 | J20: =ABS(RecupProv!F93) -> 1403593.3 | K20: =RecupProv!F115 -> 1.0604644
A21: Mayo | B21: =RecupProv!G27 -> 706418.78 | C21: =RecupProv!G53 -> 270190.82 | D21: =B21+C21 -> 976609.6 | H21: Mayo | I21: =RecupProv!G108 -> 1415920.5 | J21: =ABS(RecupProv!G93) -> 1478690 | K21: =RecupProv!G115 -> 1.0443312
A22: Junio | B22: =RecupProv!H27 -> 668712.15 | C22: =RecupProv!H53 -> 272112.5 | D22: =B22+C22 -> 940824.65 | H22: Junio | I22: =RecupProv!H108 -> 1507092.9 | J22: =ABS(RecupProv!H93) -> 1552801.5 | K22: =RecupProv!H115 -> 1.030329
A23: Julio | B23: =RecupProv!I27 -> 664873.7 | C23: =RecupProv!I53 -> 257650.41 | D23: =B23+C23 -> 922524.11 | H23: Julio | I23: =RecupProv!I108 -> 1596404.5 | J23: =ABS(RecupProv!I93) -> 1625319.9 | K23: =RecupProv!I115 -> 1.0181129
A24: Agosto | B24: =RecupProv!J27 -> 653222.28 | C24: =RecupProv!J53 -> 260499.19 | D24: =B24+C24 -> 913721.47 | H24: Agosto | I24: =RecupProv!J108 -> 1683886.5 | J24: =ABS(RecupProv!J93) -> 1669409.1 | K24: =RecupProv!J115 -> 0.99140239
A25: Septiembre | B25: =RecupProv!K27 -> 641504.56 | C25: =RecupProv!K53 -> 252911.22 | D25: =B25+C25 -> 894415.78 | H25: Septiembre | I25: =RecupProv!K108 -> 1769202.5 | J25: =ABS(RecupProv!K93) -> 1697345.2 | K25: =RecupProv!K115 -> 0.95938433
A26: Octubre | B26: =RecupProv!L27 -> 646112.55 | C26: =RecupProv!L53 -> 239459.25 | D26: =B26+C26 -> 885571.8 | H26: Octubre | I26: =RecupProv!L108 -> 1851467.8 | J26: =ABS(RecupProv!L93) -> 1698191.5 | K26: =RecupProv!L115 -> 0.91721361
A27: Noviembre | B27: =RecupProv!M27 -> 625184.01 | C27: =RecupProv!M53 -> 241047.21 | D27: =B27+C27 -> 866231.22 | H27: Noviembre | I27: =RecupProv!M108 -> 1933068 | J27: =ABS(RecupProv!M93) -> 1686449.2 | K27: =RecupProv!M115 -> 0.87242103
A28: Diciembre | B28: =RecupProv!N27 -> 632338.86 | C28: =RecupProv!N53 -> 228928.99 | D28: =B28+C28 -> 861267.85 | H28: Diciembre | I28: =RecupProv!N108 -> 2012993.7 | J28: =ABS(RecupProv!N93) -> 1681867.9 | K28: =RecupProv!N115 -> 0.83550578
A31: 🗓️ Castigos proyectados por mes | H31: 📌 Lectura rápida
A32: Mes | B32: Castigos | H32: Indicador | I32: Valor
A33: Enero | B33: =RecupProv!C127 -> 0 | H33: Mes pico recuperación capital | I33: =INDEX($A$17:$A$28,MATCH(MAX($B$17:$B$28),$B$17:$B$28,0)) -> Abril
A34: Febrero | B34: =RecupProv!D127 -> 0 | H34: Mes pico recuperación intereses | I34: =INDEX($A$17:$A$28,MATCH(MAX($C$17:$C$28),$C$17:$C$28,0)) -> Febrero
A35: Marzo | B35: =RecupProv!E127 -> 0 | H35: Mes pico castigos | I35: =INDEX($A$33:$A$44,MATCH(MAX($B$33:$B$44),$B$33:$B$44,0)) -> Octubre
A36: Abril | B36: =RecupProv!F127 -> 0 | H36: Participación Consumo capital | I36: =J8 -> 0.56672071
A37: Mayo | B37: =RecupProv!G127 -> 0 | H37: Participación Microcrédito capital | I37: =J9 -> 0.11635328
A38: Junio | B38: =RecupProv!H127 -> 0 | H38: Cobertura dic-25 | I38: =K28 -> 0.83550578
A39: Julio | B39: =RecupProv!I127 -> 0
A40: Agosto | B40: =RecupProv!J127 -> 6252.31
A41: Septiembre | B41: =RecupProv!K127 -> 29391.3
A42: Octubre | B42: =RecupProv!L127 -> 80444.05
A43: Noviembre | B43: =RecupProv!M127 -> 37748.58
A44: Diciembre | B44: =RecupProv!N127 -> 17438.35

Sheet BRhoriz
B1: =BGresu!A1 -> 📊 Análisis inicial – Recuperación y provisiones de cartera | Q1: =B1 -> 📊 Análisis inicial – Recuperación y provisiones de cartera | AC1: =AY1 -> 📊 Análisis inicial – Recuperación y provisiones de cartera | AY1: =B1 -> 📊 Análisis inicial – Recuperación y provisiones de cartera
B2: =Premisas!D1 -> PRESUPUESTO 2026
B3: ESTADO DE RESULTADOS MENSUAL | E3: EJECUCIÓN MENSUAL 2023 | Q3: EJECUCIÓN ACUMULADA 2023 | AC3: EJECUCIÓN ACUMULADA | AD3: EJECUCIÓN ACUMULADA | AE3: EJECUCIÓN ACUMULADA | AF3: EJECUCIÓN ACUMULADA | AG3: EJECUCIÓN ACUMULADA | AH3: EJECUCIÓN ACUMULADA | AI3: EJECUCIÓN ACUMULADA | AJ3: EJECUCIÓN ACUMULADA | AK3: EJECUCIÓN ACUMULADA | AL3: EJECUCIÓN ACUMULADA | AM3: EJECUCIÓN ACUMULADA | AN3: EJECUCIÓN ACUMULADA | AO3: EJECUCIÓN ACUMULADA | AP3: EJECUCIÓN ACUMULADA | AQ3: EJECUCIÓN ACUMULADA | AR3: EJECUCIÓN ACUMULADA | AS3: EJECUCIÓN ACUMULADA | AT3: EJECUCIÓN ACUMULADA | AU3: EJECUCIÓN ACUMULADA | AV3: EJECUCIÓN ACUMULADA | AW3: EJECUCIÓN ACUMULADA | AX3: EJECUCIÓN ACUMULADA | AY3: PRESUPUESTO MENSUAL | AZ3: PRESUPUESTO MENSUAL | BA3: PRESUPUESTO MENSUAL | BB3: PRESUPUESTO MENSUAL | BC3: PRESUPUESTO MENSUAL | BD3: PRESUPUESTO MENSUAL | BE3: PRESUPUESTO MENSUAL | BF3: PRESUPUESTO MENSUAL | BG3: PRESUPUESTO MENSUAL | BH3: PRESUPUESTO MENSUAL | BI3: PRESUPUESTO MENSUAL | BJ3: PRESUPUESTO MENSUAL | BK3: PRESUPUESTO ACUMULADO | BL3: PRESUPUESTO ACUMULADO | BM3: PRESUPUESTO ACUMULADO | BN3: PRESUPUESTO ACUMULADO | BO3: PRESUPUESTO ACUMULADO | BP3: PRESUPUESTO ACUMULADO | BQ3: PRESUPUESTO ACUMULADO | BR3: PRESUPUESTO ACUMULADO | BS3: PRESUPUESTO ACUMULADO | BT3: PRESUPUESTO ACUMULADO | BU3: PRESUPUESTO ACUMULADO | BV3: PRESUPUESTO ACUMULADO
D4: =EEFFun!P2 -> 12 | E4: 1 | F4: 2 | G4: 3 | H4: 4 | I4: 5 | J4: 6 | K4: 7 | L4: 8 | M4: 9 | N4: 10 | O4: 11 | P4: 12 | Q4: =EEFFun!Q2 -> 1 | R4: =EEFFun!R2 -> 2 | S4: =EEFFun!S2 -> 3 | T4: =EEFFun!T2 -> 4 | U4: 5 | V4: 6 | W4: 7 | X4: 8 | Y4: 9 | Z4: 10 | AA4: 11 | AB4: 12 | AC4: 1 | AD4: 2 | AE4: 3 | AF4: 4 | AG4: 5 | AH4: 6 | AI4: 7 | AJ4: 8 | AK4: 9 | AL4: 10 | AM4: 11 | AN4: 12 | AO4: 1 | AP4: 2 | AQ4: 3 | AR4: 4 | AS4: 5 | AT4: 6 | AU4: 7 | AV4: 8 | AW4: 9 | AX4: 10 | AY4: 1 | AZ4: 2 | BA4: 3 | BB4: 4 | BC4: 5 | BD4: 6 | BE4: 7 | BF4: 8 | BG4: 9 | BH4: 10 | BI4: 11 | BJ4: 12 | BK4: 1 | BL4: 2 | BM4: 3 | BN4: 4 | BO4: 5 | BP4: 6 | BQ4: 7 | BR4: 8 | BS4: 9 | BT4: 10 | BU4: 11 | BV4: 12
A5: D | B5: Código | C5: CONCEPTOS | D5: =EEFFun!P3 -> 44926 | E5: Enero | F5: Febrero | G5: Marzo | H5: Abril | I5: Mayo | J5: Junio | K5: Julio | L5: Agosto | M5: Septiembre | N5: Octubre | O5: Noviembre | P5: Diciembre | Q5: =EEFFun!Q3 -> 44957 | R5: =EEFFun!R3 -> 44985 | S5: =EEFFun!S3 -> 45016 | T5: =EEFFun!T3 -> 45046 | U5: =EEFFun!U3 -> 45077 | V5: =EEFFun!V3 -> 45107 | W5: =EEFFun!W3 -> 45138 | X5: =EEFFun!X3 -> 45169 | ... AH5: =EEFFun!AH3 -> 45473 | AI5: 45504 | AJ5: =EEFFun!AJ3 -> 45535 | AK5: 45505 | AL5: =EEFFun!AL3 -> 45596 | AM5: 45506 | AN5: =EEFFun!AN3 -> 45657 | AO5: 45688 | AP5: 45716 | AQ5: 45747 | AR5: 45777 | AS5: 45808 | AT5: 45838 | AU5: 45869 | AV5: 45900 | AW5: 45930 | AX5: 45961 | AY5: Enero | AZ5: Febrero | BA5: Marzo | BB5: Abril | BC5: Mayo | BD5: Junio | BE5: Julio | BF5: Agosto | BG5: Septiembre | BH5: Octubre | BI5: Noviembre | BJ5: Diciembre | BK5: 45688 | BL5: 45716 | BM5: 45747 | BN5: 45777 | BO5: 45808 | BP5: 45838 | BQ5: 45869 | BR5: 45900 | BS5: 45930 | BT5: 45961 | BU5: 45991 | BV5: 46022
A6: 1 | B6: =EEFFun!B475 -> 4 | C6: =EEFFun!C475 -> GASTOS | D6: =EEFFun!P475 -> 5900345.7 | E6: =E8+E16+E18+E20+E30+E136+E139+E145 -> 410670.13 | F6: =F8+F16+F18+F20+F30+F136+F139+F145 -> 380863.57 | G6: =G8+G16+G18+G20+G30+G136+G139+G145 -> 448701.99 | H6: =H8+H16+H18+H20+H30+H136+H139+H145 -> 504459.02 | I6: =I8+I16+I18+I20+I30+I136+I139+I145 -> 522271.88 | J6: =J8+J16+J18+J20+J30+J136+J139+J145 -> 497111.03 | K6: =K8+K16+K18+K20+K30+K136+K139+K145 -> 491172.39 | L6: =L8+L16+L18+L20+L30+L136+L139+L145 -> 441468.52 | ... P6: =P8+P16+P18+P20+P30+P136+P139+P145 -> 446467.81 | Q6: =EEFFun!Q475 -> 410670.13 | R6: =EEFFun!R475 -> 791533.7 | S6: =EEFFun!S475 -> 1240235.7 | T6: =EEFFun!T475 -> 1744694.7 | U6: =EEFFun!U475 -> 2266966.6 | V6: =EEFFun!V475 -> 2764077.6 | W6: =EEFFun!W475 -> 3255250 | X6: =EEFFun!X475 -> 3696718.5 | ... AX6: =EEFFun!AX475 -> 8433506.1 | AY6: =AY8+AY16+AY18+AY20+AY30+AY136+AY139+AY145 -> 1000590 | AZ6: =AZ8+AZ16+AZ18+AZ20+AZ30+AZ136+AZ139+AZ145 -> 981746.94 | BA6: =BA8+BA16+BA18+BA20+BA30+BA136+BA139+BA145 -> 1032058.4 | BB6: =BB8+BB16+BB18+BB20+BB30+BB136+BB139+BB145 -> 1044166.7 | BC6: =BC8+BC16+BC18+BC20+BC30+BC136+BC139+BC145 -> 1115405.2 | BD6: =BD8+BD16+BD18+BD20+BD30+BD136+BD139+BD145 -> 1142172.5 | BE6: =BE8+BE16+BE18+BE20+BE30+BE136+BE139+BE145 -> 1211095.9 | BF6: =BF8+BF16+BF18+BF20+BF30+BF136+BF139+BF145 -> 1247972.5 | ... BV6: =BV8+BV16+BV18+BV20+BV30+BV136+BV139+BV145 -> 14293603
B7: 4-48 | C7: GASTOS SIN GRUPO 48 | D7: =D6-D145 -> 5900345.7 | E7: =E8+E16+E18+E20+E30+E136+E139 -> 410670.13 | F7: =F8+F16+F18+F20+F30+F136+F139 -> 380863.57 | G7: =G8+G16+G18+G20+G30+G136+G139 -> 448701.99 | H7: =H8+H16+H18+H20+H30+H136+H139 -> 439362.6 | I7: =I8+I16+I18+I20+I30+I136+I139 -> 570425.75 | J7: =J8+J16+J18+J20+J30+J136+J139 -> 514053.58 | K7: =K8+K16+K18+K20+K30+K136+K139 -> 491172.39 | L7: =L8+L16+L18+L20+L30+L136+L139 -> 441468.52 | ... P7: =P8+P16+P18+P20+P30+P136+P139 -> 399809.86 | Q7: =Q6-Q145 -> 410670.13 | R7: =R6-R145 -> 791533.7 | S7: =S6-S145 -> 1240235.7 | T7: =T6-T145 -> 1679598.3 | U7: =U6-U145 -> 2250024 | V7: =V6-V145 -> 2764077.6 | W7: =W6-W145 -> 3255250 | X7: =X6-X145 -> 3696718.5 | ... AX7: =AX6-AX145 -> 8433506.1 | AY7: =AY8+AY16+AY18+AY20+AY30+AY136+AY139 -> 980647.45 | AZ7: =AZ8+AZ16+AZ18+AZ20+AZ30+AZ136+AZ139 -> 957672.1 | BA7: =BA8+BA16+BA18+BA20+BA30+BA136+BA139 -> 972632.03 | BB7: =BB8+BB16+BB18+BB20+BB30+BB136+BB139 -> 975393.92 | BC7: =BC8+BC16+BC18+BC20+BC30+BC136+BC139 -> 1039239.4 | BD7: =BD8+BD16+BD18+BD20+BD30+BD136+BD139 -> 1060988.4 | BE7: =BE8+BE16+BE18+BE20+BE30+BE136+BE139 -> 1122938.1 | BF7: =BF8+BF16+BF18+BF20+BF30+BF136+BF139 -> 1137643.7 | ... BV7: =BV8+BV16+BV18+BV20+BV30+BV136+BV139 -> 13324458
A8: 2 | B8: =EEFFun!B476 -> 41 | C8: =EEFFun!C476 -> INTERESES CAUSADOS | D8: =EEFFun!P476 -> 2280593 | E8: =E9+E14 -> 209360.54 | F8: =F9+F14 -> 189049.53 | G8: =G9+G14 -> 208712.9 | H8: =H9+H14 -> 199784.5 | I8: =I9+I14 -> 215742.92 | J8: =J9+J14 -> 204322.86 | K8: =K9+K14 -> 207671.84 | L8: =L9+L14 -> 206297.81 | ... P8: =P9+P14 -> 208819.12 | Q8: =EEFFun!Q476 -> 209360.54 | R8: =EEFFun!R476 -> 398410.07 | S8: =EEFFun!S476 -> 607122.97 | T8: =EEFFun!T476 -> 806907.47 | U8: =EEFFun!U476 -> 1022650.4 | V8: =EEFFun!V476 -> 1226973.2 | W8: =EEFFun!W476 -> 1434645.1 | X8: =EEFFun!X476 -> 1640942.9 | ... AX8: =EEFFun!AX476 -> 3301749.6 | AY8: =AY9+AY14 -> 438058.98 | AZ8: =AZ9+AZ14 -> 416753.22 | BA8: =BA9+BA14 -> 504282.29 | BB8: =BB9+BB14 -> 529806.75 | BC8: =BC9+BC14 -> 590505.61 | BD8: =BD9+BD14 -> 613248.67 | BE8: =BE9+BE14 -> 676728.92 | BF8: =BF9+BF14 -> 719840.58 | ... BV8: =BV9+BV14 -> 7746169.9
A9: 4 | B9: =EEFFun!B477 -> 4101 | C9: =EEFFun!C477 -> Obligaciones con el público | D9: =EEFFun!P477 -> 2229307.1 | E9: =+SUM(E10:E12) -> 209360.54 | F9: =+SUM(F10:F12) -> 189049.53 | G9: =+SUM(G10:G12) -> 208712.9 | H9: =+SUM(H10:H12) -> 199784.5 | I9: =+SUM(I10:I12) -> 201460.78 | J9: =+SUM(J10:J12) -> 192081.03 | K9: =+SUM(K10:K12) -> 197470.31 | L9: =+SUM(L10:L12) -> 195999.06 | ... P9: =+SUM(P10:P12) -> 208819.13 | Q9: =EEFFun!Q477 -> 209360.54 | R9: =EEFFun!R477 -> 398410.07 | S9: =EEFFun!S477 -> 607122.97 | T9: =EEFFun!T477 -> 806907.47 | U9: =EEFFun!U477 -> 1008368.2 | V9: =EEFFun!V477 -> 1200449.3 | W9: =EEFFun!W477 -> 1397919.6 | X9: =EEFFun!X477 -> 1593918.6 | ... AX9: =EEFFun!AX477 -> 3301331.4 | AY9: =+SUM(AY10:AY12) -> 438058.98 | AZ9: =+SUM(AZ10:AZ12) -> 416753.22 | BA9: =+SUM(BA10:BA12) -> 504282.29 | BB9: =+SUM(BB10:BB12) -> 529806.75 | BC9: =+SUM(BC10:BC12) -> 590505.61 | BD9: =+SUM(BD10:BD12) -> 613248.67 | BE9: =+SUM(BE10:BE12) -> 676728.92 | BF9: =+SUM(BF10:BF12) -> 719840.58 | ... BV9: =+SUM(BV10:BV12) -> 7746169.9
A10: 6 | B10: =EEFFun!B478 -> 410105 | C10: =EEFFun!C478 -> DEPOSITOS MONETARIOS | D10: =EEFFun!P478 -> 104.57 | E10: =Q10 -> 1.73 | F10: =R10-Q10 -> 1.56 | G10: =S10-R10 -> 1.73 | H10: =T10-S10 -> 115.19 | I10: =U10-T10 -> 118.81 | J10: =V10-U10 -> 18.91 | K10: =W10-V10 -> 19.55 | L10: =X10-W10 -> 19.57 | M10: =Y10-X10 -> 18.64 | ... P10: =AB10-AA10 -> 0.93 | Q10: =EEFFun!Q478 -> 1.73 | R10: =EEFFun!R478 -> 3.29 | S10: =EEFFun!S478 -> 5.02 | T10: =EEFFun!T478 -> 120.21 | U10: =EEFFun!U478 -> 239.02 | V10: =EEFFun!V478 -> 257.93 | W10: =EEFFun!W478 -> 277.48 | X10: =EEFFun!X478 -> 297.05 | ... AX10: =EEFFun!AX478 -> 21907.15 | AY10: =+AX10/10 -> 2190.715 | AZ10: =AY10 -> 2190.715 | BA10: =AZ10 -> 2190.715 | BB10: =BA10 -> 2190.715 | BC10: =BB10 -> 2190.715 | BD10: =BC10 -> 2190.715 | BE10: =BD10 -> 2190.715 | BF10: =BE10 -> 2190.715 | BG10: =BF10 -> 2190.715 | ... BJ10: =BI10 -> 2190.715 | BK10: =SUM($AY$10:AY10) -> 2190.715 | BL10: =SUM($AY$10:AZ10) -> 4381.43 | BM10: =SUM($AY$10:BA10) -> 6572.145 | BN10: =SUM($AY$10:BB10) -> 8762.86 | BO10: =SUM($AY$10:BC10) -> 10953.575 | BP10: =SUM($AY$10:BD10) -> 13144.29 | BQ10: =SUM($AY$10:BE10) -> 15335.005 | BR10: =SUM($AY$10:BF10) -> 17525.72 | ... BV10: =SUM($AY$10:BJ10) -> 26288.58
A11: 6 | B11: =EEFFun!B479 -> 410115 | C11: =EEFFun!C479 -> DEPÓSITOS DE AHORROS | D11: =EEFFun!P479 -> 23162.13 | E11: =Q11 -> 1657.33 | F11: =R11-Q11 -> 1499.88 | G11: =S11-R11 -> 1363.97 | H11: =T11-S11 -> 1291.22 | I11: =U11-T11 -> 1360.75 | J11: =V11-U11 -> 1288.87 | K11: =W11-V11 -> 1382.17 | L11: =X11-W11 -> 1923.66 | M11: =Y11-X11 -> 1204.96 | ... P11: =AB11-AA11 -> 1153.39 | Q11: =EEFFun!Q479 -> 1657.33 | R11: =EEFFun!R479 -> 3157.21 | S11: =EEFFun!S479 -> 4521.18 | T11: =EEFFun!T479 -> 5812.4 | U11: =EEFFun!U479 -> 7173.15 | V11: =EEFFun!V479 -> 8462.02 | W11: =EEFFun!W479 -> 9844.19 | X11: =EEFFun!X479 -> 11767.85 | ... AX11: =EEFFun!AX479 -> 25343.57 | AY11: =IntCaptac!E6 -> 7354.827 | AZ11: =IntCaptac!F6 -> 7026.6312 | BA11: =IntCaptac!G6 -> 8204.1421 | BB11: =IntCaptac!H6 -> 8350.4513 | BC11: =IntCaptac!I6 -> 9053.4572 | BD11: =IntCaptac!J6 -> 9172.3691 | BE11: =IntCaptac!K6 -> 9902.7722 | BF11: =IntCaptac!L6 -> 10327.43 | ... BJ11: =IntCaptac!P6 -> 11601.402 | BK11: =SUM($AY$11:AY11) -> 7354.827 | BL11: =SUM($AY$11:AZ11) -> 14381.458 | BM11: =SUM($AY$11:BA11) -> 22585.6 | BN11: =SUM($AY$11:BB11) -> 30936.052 | BO11: =SUM($AY$11:BC11) -> 39989.509 | BP11: =SUM($AY$11:BD11) -> 49161.878 | BQ11: =SUM($AY$11:BE11) -> 59064.65 | BR11: =SUM($AY$11:BF11) -> 69392.08 | ... BV11: =SUM($AY$11:BJ11) -> 112556.06
A12: 6 | B12: =EEFFun!B480 -> 410130 | C12: =EEFFun!C480 -> Depósitos a plazo | D12: =EEFFun!P480 -> 2206040.4 | E12: =E13 -> 207701.48 | F12: =F13 -> 187548.09 | G12: =G13 -> 207347.2 | H12: =H13 -> 198378.09 | I12: =I13 -> 199981.22 | J12: =J13 -> 190773.25 | K12: =K13 -> 196068.59 | L12: =L13 -> 194055.83 | ... P12: =P13 -> 207664.81 | Q12: =EEFFun!Q480 -> 207701.48 | R12: =EEFFun!R480 -> 395249.57 | S12: =EEFFun!S480 -> 602596.77 | T12: =EEFFun!T480 -> 800974.86 | U12: =EEFFun!U480 -> 1000956.1 | V12: =EEFFun!V480 -> 1191729.3 | W12: =EEFFun!W480 -> 1387797.9 | X12: =EEFFun!X480 -> 1581853.8 | ... AX12: =EEFFun!AX480 -> 3254080.6 | AY12: =AY13 -> 428513.43 | AZ12: =AZ13 -> 407535.88 | BA12: =BA13 -> 493887.43 | BB12: =BB13 -> 519265.58 | BC12: =BC13 -> 579261.43 | BD12: =BD13 -> 601885.58 | BE12: =BE13 -> 664635.43 | BF12: =BF13 -> 707322.43 | ... BV12: =BV13 -> 7607325.2
A13: 8 | B13: =EEFFun!B481 -> 41013010 | C13: =EEFFun!C481 -> DEPOSITOS A PLAZO | D13: =EEFFun!P481 -> 2206040.4 | E13: =Q13 -> 207701.48 | F13: =R13-Q13 -> 187548.09 | G13: =S13-R13 -> 207347.2 | H13: =T13-S13 -> 198378.09 | I13: =U13-T13 -> 199981.22 | J13: =V13-U13 -> 190773.25 | K13: =W13-V13 -> 196068.59 | L13: =X13-W13 -> 194055.83 | M13: =Y13-X13 -> 189196.36 | ... P13: =AB13-AA13 -> 207664.81 | Q13: =EEFFun!Q481 -> 207701.48 | R13: =EEFFun!R481 -> 395249.57 | S13: =EEFFun!S481 -> 602596.77 | T13: =EEFFun!T481 -> 800974.86 | U13: =EEFFun!U481 -> 1000956.1 | V13: =EEFFun!V481 -> 1191729.3 | W13: =EEFFun!W481 -> 1387797.9 | X13: =EEFFun!X481 -> 1581853.8 | ... AX13: =EEFFun!AX481 -> 3254080.6 | AY13: =IntCaptac!E7+20000 -> 428513.43 | AZ13: =IntCaptac!F7 -> 407535.88 | BA13: =IntCaptac!G7 -> 493887.43 | BB13: =IntCaptac!H7 -> 519265.58 | BC13: =IntCaptac!I7 -> 579261.43 | BD13: =IntCaptac!J7 -> 601885.58 | BE13: =IntCaptac!K7 -> 664635.43 | BF13: =IntCaptac!L7 -> 707322.43 | BG13: =IntCaptac!M7 -> 725815.58 | ... BJ13: =IntCaptac!P7 -> 878070.43 | BK13: =SUM($AY$13:AY13) -> 428513.43 | BL13: =SUM($AY$13:AZ13) -> 836049.31 | BM13: =SUM($AY$13:BA13) -> 1329936.7 | BN13: =SUM($AY$13:BB13) -> 1849202.3 | BO13: =SUM($AY$13:BC13) -> 2428463.8 | BP13: =SUM($AY$13:BD13) -> 3030349.3 | BQ13: =SUM($AY$13:BE13) -> 3694984.8 | BR13: =SUM($AY$13:BF13) -> 4402307.2 | ... BV13: =SUM($AY$13:BJ13) -> 7607325.2
A14: 4 | B14: =EEFFun!B482 -> 4103 | C14: =EEFFun!C482 -> Obligaciones financieras | D14: =EEFFun!P482 -> 51285.95 | E14: =E15 -> 0 | F14: =F15 -> 0 | G14: =G15 -> 0 | H14: =H15 -> 0 | I14: =I15 -> 14282.14 | J14: =J15 -> 12241.83 | K14: =K15 -> 10201.53 | L14: =L15 -> 10298.75 | ... P14: =P15 -> -0.01 | Q14: =EEFFun!Q482 -> 0 | R14: =EEFFun!R482 -> 0 | S14: =EEFFun!S482 -> 0 | T14: =EEFFun!T482 -> 0 | U14: =EEFFun!U482 -> 14282.14 | V14: =EEFFun!V482 -> 26523.97 | W14: =EEFFun!W482 -> 36725.5 | X14: =EEFFun!X482 -> 47024.25 | ... AX14: =EEFFun!AX482 -> 0 | AY14: =AY15 -> 0 | AZ14: =AZ15 -> 0 | BA14: =BA15 -> 0 | BB14: =BB15 -> 0 | BC14: =BC15 -> 0 | BD14: =BD15 -> 0 | BE14: =BE15 -> 0 | BF14: =BF15 -> 0 | ... BV14: =BV15 -> 0
A15: 6 | B15: =EEFFun!B483 -> 410345 | C15: =EEFFun!C483 -> Obligaciones con entidades del sector público | D15: =EEFFun!P483 -> 51285.95 | E15: =Q15 -> 0 | F15: =R15-Q15 -> 0 | G15: =S15-R15 -> 0 | H15: =T15-S15 -> 0 | I15: =U15-T15 -> 14282.14 | J15: =V15-U15 -> 12241.83 | K15: =W15-V15 -> 10201.53 | L15: =X15-W15 -> 10298.75 | M15: =Y15-X15 -> 8350.34 | ... P15: =AB15-AA15 -> -0.01 | Q15: =EEFFun!Q483 -> 0 | R15: =EEFFun!R483 -> 0 | S15: =EEFFun!S483 -> 0 | T15: =EEFFun!T483 -> 0 | U15: =EEFFun!U483 -> 14282.14 | V15: =EEFFun!V483 -> 26523.97 | W15: =EEFFun!W483 -> 36725.5 | X15: =EEFFun!X483 -> 47024.25 | ... AX15: =EEFFun!AX483 -> 0 | AY15: =CaptObFin!B12 -> 0 | AZ15: =CaptObFin!C12 -> 0 | BA15: =CaptObFin!D12 -> 0 | BB15: =CaptObFin!E12 -> 0 | BC15: =CaptObFin!F12 -> 0 | BD15: =CaptObFin!G12 -> 0 | BE15: =CaptObFin!H12 -> 0 | BF15: =CaptObFin!I12 -> 0 | ... BJ15: =CaptObFin!M12 -> 0 | BK15: =SUM($AY$15:AY15) -> 0 | BL15: =SUM($AY$15:AZ15) -> 0 | BM15: =SUM($AY$15:BA15) -> 0 | BN15: =SUM($AY$15:BB15) -> 0 | BO15: =SUM($AY$15:BC15) -> 0 | BP15: =SUM($AY$15:BD15) -> 0 | BQ15: =SUM($AY$15:BE15) -> 0 | BR15: =SUM($AY$15:BF15) -> 0 | ... BV15: =SUM($AY$15:BJ15) -> 0
A16: 2 | B16: =EEFFun!B484 -> 42 | C16: =EEFFun!C484 -> COMISIONES CAUSADAS | D16: =EEFFun!P484 -> 20956.38 | E16: =E17 -> 815.25 | F16: =F17 -> 765.53 | G16: =G17 -> 1150.15 | H16: =H17 -> 804.88 | I16: =I17 -> -1465.12 | J16: =J17 -> 2856.39 | K16: =K17 -> 974.96 | L16: =L17 -> 958.91 | ... P16: =P17 -> 1865.44 | Q16: =EEFFun!Q484 -> 815.25 | R16: =EEFFun!R484 -> 1580.78 | S16: =EEFFun!S484 -> 2730.93 | T16: =EEFFun!T484 -> 3535.81 | U16: =EEFFun!U484 -> 2070.69 | V16: =EEFFun!V484 -> 4927.08 | W16: =EEFFun!W484 -> 5902.04 | X16: =EEFFun!X484 -> 6860.95 | ... AX16: =EEFFun!AX484 -> 39574.44 | AY16: =AY17 -> 3957.444 | AZ16: =AZ17 -> 3957.444 | BA16: =BA17 -> 3957.444 | BB16: =BB17 -> 3957.444 | BC16: =BC17 -> 3957.444 | BD16: =BD17 -> 3957.444 | BE16: =BE17 -> 3957.444 | BF16: =BF17 -> 3957.444 | ... BV16: =BV17 -> 47489.328
A17: 4 | B17: =EEFFun!B485 -> 4290 | C17: =EEFFun!C485 -> Varias | D17: =EEFFun!P485 -> 20956.38 | E17: =Q17 -> 815.25 | F17: =R17-Q17 -> 765.53 | G17: =S17-R17 -> 1150.15 | H17: =T17-S17 -> 804.88 | I17: =U17-T17 -> -1465.12 | J17: =V17-U17 -> 2856.39 | K17: =W17-V17 -> 974.96 | L17: =X17-W17 -> 958.91 | M17: =Y17-X17 -> 455.99 | ... P17: =AB17-AA17 -> 1865.44 | Q17: =EEFFun!Q485 -> 815.25 | R17: =EEFFun!R485 -> 1580.78 | S17: =EEFFun!S485 -> 2730.93 | T17: =EEFFun!T485 -> 3535.81 | U17: =EEFFun!U485 -> 2070.69 | V17: =EEFFun!V485 -> 4927.08 | W17: =EEFFun!W485 -> 5902.04 | X17: =EEFFun!X485 -> 6860.95 | ... AX17: =EEFFun!AX485 -> 39574.44 | AY17: =+AX17/10 -> 3957.444 | AZ17: =AY17 -> 3957.444 | BA17: =AZ17 -> 3957.444 | BB17: =BA17 -> 3957.444 | BC17: =BB17 -> 3957.444 | BD17: =BC17 -> 3957.444 | BE17: =BD17 -> 3957.444 | BF17: =BE17 -> 3957.444 | BG17: =BF17 -> 3957.444 | ... BJ17: =BI17 -> 3957.444 | BK17: =SUM($AY$17:AY17) -> 3957.444 | BL17: =SUM($AY$17:AZ17) -> 7914.888 | BM17: =SUM($AY$17:BA17) -> 11872.332 | BN17: =SUM($AY$17:BB17) -> 15829.776 | BO17: =SUM($AY$17:BC17) -> 19787.22 | BP17: =SUM($AY$17:BD17) -> 23744.664 | BQ17: =SUM($AY$17:BE17) -> 27702.108 | BR17: =SUM($AY$17:BF17) -> 31659.552 | ... BV17: =SUM($AY$17:BJ17) -> 47489.328
A18: 2 | B18: =EEFFun!B486 -> 43 | C18: =EEFFun!C486 -> PERDIDAS FINANCIERAS | D18: =EEFFun!P486 -> 48476.4 | E18: =E19 -> 4714.21 | F18: =F19 -> 3126.35 | G18: =G19 -> 3398.58 | H18: =H19 -> 3675.74 | I18: =I19 -> 3504.15 | J18: =J19 -> 3970.18 | K18: =K19 -> 3468.82 | L18: =L19 -> 3512.27 | ... P18: =P19 -> 5143.75 | Q18: =EEFFun!Q486 -> 4714.21 | R18: =EEFFun!R486 -> 7840.56 | S18: =EEFFun!S486 -> 11239.14 | T18: =EEFFun!T486 -> 14914.88 | U18: =EEFFun!U486 -> 18419.03 | V18: =EEFFun!V486 -> 22389.21 | W18: =EEFFun!W486 -> 25858.03 | X18: =EEFFun!X486 -> 29370.3 | ... AX18: =EEFFun!AX486 -> 583451 | AY18: =AY19 -> 67.325 | AZ18: =AZ19 -> 67.325 | BA18: =BA19 -> 67.325 | BB18: =BB19 -> 67.325 | BC18: =BC19 -> 67.325 | BD18: =BD19 -> 67.325 | BE18: =BE19 -> 67.325 | BF18: =BF19 -> 67.325 | ... BV18: =BV19 -> 807.9
A19: 4 | B19: =EEFFun!B489 -> 4306 | C19: =EEFFun!C489 -> Prima en compra de cartera | D19: =EEFFun!P489 -> 48476.4 | E19: =Q19 -> 4714.21 | F19: =R19-Q19 -> 3126.35 | G19: =S19-R19 -> 3398.58 | H19: =T19-S19 -> 3675.74 | I19: =U19-T19 -> 3504.15 | J19: =V19-U19 -> 3970.18 | K19: =W19-V19 -> 3468.82 | L19: =X19-W19 -> 3512.27 | M19: =Y19-X19 -> 3300.88 | ... P19: =AB19-AA19 -> 5143.75 | Q19: =EEFFun!Q489 -> 4714.21 | R19: =EEFFun!R489 -> 7840.56 | S19: =EEFFun!S489 -> 11239.14 | T19: =EEFFun!T489 -> 14914.88 | U19: =EEFFun!U489 -> 18419.03 | V19: =EEFFun!V489 -> 22389.21 | W19: =EEFFun!W489 -> 25858.03 | X19: =EEFFun!X489 -> 29370.3 | ... AX19: =EEFFun!AX489 -> 673.25 | AY19: =+AX19/10 -> 67.325 | AZ19: =AY19 -> 67.325 | BA19: =AZ19 -> 67.325 | BB19: =BA19 -> 67.325 | BC19: =BB19 -> 67.325 | BD19: =BC19 -> 67.325 | BE19: =BD19 -> 67.325 | BF19: =BE19 -> 67.325 | BG19: =BF19 -> 67.325 | ... BJ19: =BI19 -> 67.325 | BK19: =SUM($AY$19:AY19) -> 67.325 | BL19: =SUM($AY$19:AZ19) -> 134.65 | BM19: =SUM($AY$19:BA19) -> 201.975 | BN19: =SUM($AY$19:BB19) -> 269.3 | BO19: =SUM($AY$19:BC19) -> 336.625 | BP19: =SUM($AY$19:BD19) -> 403.95 | BQ19: =SUM($AY$19:BE19) -> 471.275 | BR19: =SUM($AY$19:BF19) -> 538.6 | ... BV19: =SUM($AY$19:BJ19) -> 807.9
A20: 6 | B20: =EEFFun!B490 -> 44 | C20: =EEFFun!C490 -> PROVISIONES | D20: =EEFFun!P490 -> 546704.34 | E20: =E21+E26+E27+E28 -> 639.33 | F20: =F21+F26+F27+F28 -> -639.33 | G20: =G21+G26+G27+G28 -> 49479.97 | H20: =H21+H26+H27+H28 -> 39642.35 | I20: =I21+I26+I27+I28 -> 139441.52 | J20: =J21+J26+J27+J28+J29 -> 108533.41 | K20: =K21+K26+K27+K28+K29 -> 78008.17 | L20: =L21+L26+L27+L28+L29 -> 10490.39 | M20: =M21+M26+M27+M28+M29 -> 82913.25 | N20: =N21+N26+N27+N28+N29 -> 246277.72 | O20: =O21+O26+O27+O28+O29 -> -213044.74 | P20: =P21+P26+P27+P28+P29 -> 11568.42 | Q20: =EEFFun!Q490 -> 639.33 | R20: =EEFFun!R490 -> 0 | S20: =EEFFun!S490 -> 49479.97 | T20: =EEFFun!T490 -> 89122.32 | U20: =EEFFun!U490 -> 228563.84 | V20: =EEFFun!V490 -> 337097.25 | W20: =EEFFun!W490 -> 415105.42 | X20: =EEFFun!X490 -> 425595.81 | ... AG20: =EEFFun!AG490 -> 190089.38 | AH20: =AH21+AH26+AH27+AH28+AH29 -> 373141.04 | AI20: =AI21+AI26+AI27+AI28+AI29 -> 270508.12 | AJ20: =AJ21+AJ26+AJ27+AJ28+AJ29 -> 552327.26 | AK20: =AK21+AK26+AK27+AK28+AK29 -> 864971.51 | AL20: =AL21+AL26+AL27+AL28+AL29 -> 1151456.2 | AM20: =AM21+AM26+AM27+AM28+AM29 -> 1130588.2 | AN20: =AN21+AN26+AN27+AN28+AN29 -> 896982.61 | AO20: =AO21+AO26+AO27+AO28+AO29 -> 3172.77 | ... AX20: =AX21+AX26+AX27+AX28+AX29 -> 603836.6 | AY20: =AY21+AY26+AY27+AY28 -> 120761.2 | AZ20: =AZ21+AZ26+AZ27+AZ28 -> 119091.6 | BA20: =BA21+BA26+BA27+BA28 -> 116522.45 | BB20: =BB21+BB26+BB27+BB28 -> 110293.12 | BC20: =BC21+BC26+BC27+BC28 -> 113439.71 | BD20: =BD21+BD26+BD27+BD28 -> 112445.73 | BE20: =BE21+BE26+BE27+BE28 -> 110915.14 | BF20: =BF21+BF26+BF27+BF28 -> 82509.104 | ... BJ20: =BJ21+BJ26+BJ27+BJ28 -> 33944.173 | BK20: =BK21+BK26+BK27+BK28+BK29 -> 121313.06 | BL20: =BL21+BL26+BL27+BL28+BL29 -> 240956.51 | BM20: =BM21+BM26+BM27+BM28+BM29 -> 358030.83 | BN20: =BN21+BN26+BN27+BN28+BN29 -> 468875.81 | BO20: =BO21+BO26+BO27+BO28+BO29 -> 582867.38 | BP20: =BP21+BP26+BP27+BP28+BP29 -> 695864.97 | BQ20: =BQ21+BQ26+BQ27+BQ28+BQ29 -> 807331.96 | BR20: =BR21+BR26+BR27+BR28+BR29 -> 890392.93 | ... BV20: =BV21+BV26+BV27+BV28+BV29 -> 1058985.3
